Workbook

Sheet stats_2026
B1: Searched
A2: D | B2: Duplicates | C2: =countif(survey_paper_2026!$F$2:$F$164,A2) -> 0
A3: IR | B3: Invalid Record | C3: =countif(survey_paper_2026!$F$2:$F$164,A3) -> 32
A4: ST | B4: Screened Out by Title | C4: =countif(survey_paper_2026!$F$2:$F$164,A4) -> 4
A5: SA | B5: Screened Out by Abstract | C5: =countif(survey_paper_2026!$F$2:$F$164,A5) -> 22
A6: SF | B6: Screened Out by full text | C6: =countif(survey_paper_2026!$F$2:$F$164,A6) -> 3
A7: P | B7: Passed | C7: =countif(survey_paper_2026!$F$2:$F$164,A7) -> 92
A8: RT | B8: Retrected | C8: =countif(survey_paper_2026!$F$2:$F$164,A8) -> 1
A9: NA | B9: Not Available | C9: =countif(survey_paper_2026!$F$2:$F$164,A9) -> 8
C10: =SUM(C2:C9) -> 162 | D10: of 162
A12: Y | B12: In Paper | C12: =COUNTIF(survey_paper_2026!G2:G163,A12) -> 92
C13: =C7-C12 -> 0

Sheet survey_paper_2026
A1: Authors | B1: Title | C1: Year | D1: Cited by | E1: Link | F1: Status | G1: In Paper | H1: Overlap | I1: Abstract
A2: Li, Y.; Mercan, E.; Knezevitch, S.; Elmore, J.G.; Shapiro, L.G. | B2: Efficient and Accurate Mitosis Detection A Lightweight RCNN Approach | C2: 2018 | D2: 22 | E2: https://www.scopus.com/inward/record.uri?eid=2-s2.0-85052023801&doi=10.5220%2F0006550700690077&partnerID=40&md5=a8da73e482f17fc0f87fdf61f24d2a82 | F2: P | G2: Y | H2: =countif(Survey!$E$2:$E$57,E2) -> 0 | I2: The analysis of breast cancer images includes the detection of mitotic figures whose counting is important in the grading of invasive breast cancer. Mitotic figures are difficult to find in the very large whole slide images, as they may look only slightly different from normal nuclei. In the last few years, several convolutional neural network (CNN) systems have been developed for mitosis detection that are able to beat conventional, feature-based approaches. However, these networks contain many layers and many neurons per layer, so both training and actual classification require powerful computers with GPUs. In this paper, we describe a new lightweight region-based CNN methodology we have developed that is able to run on standard machines with only a CPU and can achieve accuracy measures that are almost as good as the best CNN-based system so far in a fraction of the time, when both are run on CPUs. Our system, which includes a feature-based region extractor plus two CNN stages, is tested on the ICPR 2012 and ICPR 2014 datasets, and results are given for accuracy and timing. © © 2018 by SCITEPRESS – Science and Technology Publications, Lda. All rights reserved
A3: Oliveira, H.S.; Teixeira, J.F.; Oliveira, H.P. | B3: Lightweight deep learning pipeline for detection, segmentation and classification of breast cancer anomalies | C3: 2019 | D3: 10 | E3: https://www.scopus.com/inward/record.uri?eid=2-s2.0-85072901730&doi=10.1007%2F978-3-030-30645-8_64&partnerID=40&md5=9f19b44d7075729e35846cda32bbe51b | F3: P | G3: Y | H3: =countif(Survey!$E$2:$E$57,E3) -> 0 | I3: The small amount of public available medical images hinders the use of deep learning techniques for mammogram automatic diagnosis. Deep learning methods require large annotated training sets to be effective, however medical datasets are costly to obtain and suffer from large variability. In this work, a lightweight deep learning pipeline to detect, segment and classify anomalies in mammogram images is presented. First, data augmentation using the ground-truth annotation is performed and used by a cascade segmentation and classification methods. Results are obtained using the INbreast public database in the context of lesion detection and BI-RADS classification. Moreover, a pre-trained Convolutional Neural Network using ResNet50 is modified to generate the lesion regions proposals followed by a false positive reduction and contour refinement stages while a pre-trained VGG16 network is fine-tuned to classify mammograms. The detection and segmentation stage results show that the cascade configuration achieves a DICE of 0.83 without massive training while the multi-class classification exhibits an MAE of 0.58 with data augmentation. © Springer Nature Switzerland AG 2019.
A4: Elbashir, M.K.; Ezz, M.; Mohammed, M.; Saloum, S.S. | B4: Lightweight convolutional neural network for breast cancer classification using RNA-Seq gene expression data | C4: 2019 | D4: 74 | E4: https://www.scopus.com/inward/record.uri?eid=2-s2.0-85077964825&doi=10.1109%2FACCESS.2019.2960722&partnerID=40&md5=67da4ac6fe40be475c395aa316fdb2fe | F4: P | G4: Y | H4: =countif(Survey!$E$2:$E$57,E4) -> 0 | I4: Gene expressions are considered among the most used features in cancer classification. The available gene expression data has a small number of samples and a relatively big number of dimensions, and that makes it not suitable for deep Convolutional Neural Networks (CNN) architectures, which exhibit state-of-the-art performance in many fields. In this paper, we propose a lightweight CNN architecture for breast cancer classification using gene expression data downloaded from Pan-Cancer Atlas using 'Illumina HiSeq' platform. The downloaded gene expression data is preprocessed and then transformed into 2D-images. We started the preprocessing by removing the outlier samples, which are determined based on the Array-Array Intensity Correlation (AAIC), which defines a symmetric square matrix of Spearman correlation. Then we applied a normalization process on the gene expression data to ensure that we can infer the expression level from it correctly and avoid biases in the expression measures. Finally, filtering is applied on the data. Model selection or a parameters search strategy is conducted to choose the values of the CNN hyper-parameters that give optimal performance. Our experiments show that our proposed method achieves an accuracy of 98.76%, which is the highest compared to other competing methods. © 2013 IEEE.
A5: Abdelli, A.; Saouli, R.; Djemal, K.; Youkana, I. | B5: Combined Datasets for Breast Cancer Grading Based on Multi-CNN Architectures | C5: 2020 | D5: 11 | E5: https://www.scopus.com/inward/record.uri?eid=2-s2.0-85099272967&doi=10.1109%2FIPTA50016.2020.9286653&partnerID=40&md5=2fbf0269703a803895ed30d3b9deaa9e | F5: P | G5: Y | H5: =countif(Survey!$E$2:$E$57,E5) -> 0 | I5: Breast cancer is the most leading cancer among women. Usually, pathologists have to examine the histological image slides through the whole slides tissues in different magnifications, to extract the tumor malignancy then the tumor grade. These image's interpretation is one of the time and effort consuming task to define an accurate diagnosis. Consequently, Computer-Aided Diagnosis (CAD) systems are highly demanded. However, the histological images have pervasive variability, which is a big challenge due to the variation of tissue textures and which is hard to be interpreted by the computer. For this, deep learning algorithms have been promised architectures for complex objects, but the problem of the low resource of datasets is still yet a constraint to build an efficient medical system for image classification. In this work, we propose a solution based on combining two different datasets for breast cancer grade detection. Our proposed method is about adding a new class (grade 0) to the three known classes of breast cancer grades, which make our model detect both the malignancy and the grade of the breast tumors. Furthermore, both datasets images have the same magnification factor which helps our models in avoiding overfitting problems. Our models are trained using two different convolutional neural network architectures, the ResNet50 and the MobileNet for comparing between a lightweight and heavyweight architectures. The obtained results show the best accuracy in the state-of-the-art. © 2020 IEEE.
A6: Zhang, X.; Lin, X.; Zhang, Z.; Dong, L.; Sun, X.; Sun, D.; Yuan, K. | B6: Artificial Intelligence Medical Ultrasound Equipment: Application of Breast Lesions Detection | C6: 2020 | D6: 25 | E6: https://www.scopus.com/inward/record.uri?eid=2-s2.0-85086567155&doi=10.1177%2F0161734620928453&partnerID=40&md5=cf1013a4a61fe2c418e678c32e1a8ca7 | F6: P | G6: Y | H6: =countif(Survey!$E$2:$E$57,E6) -> 0 | I6: Breast cancer ranks first among cancers affecting women’s health. Our work aims to realize the intelligence of the medical ultrasound equipment with limited computational capability, which is used for the assistant detection of breast lesions. We embed the high-computational deep learning algorithm into the medical ultrasound equipment with limited computational capability by two techniques: (1) lightweight neural network: considering the limited computational capability of ultrasound equipment, a lightweight neural network is designed, which greatly reduces the amount of calculation. And we use the technique of knowledge distillation to train the low-precision network helped with the high-precision network; (2) asynchronous calculations: consider four frames of ultrasound images as a group; the image of the first frame of each group is used as the input of the network, and the result is respectively fused with the images of the fourth to seventh frames. An amount of computation of 30 GFLO/frame is required for the proposed lightweight neural network, about 1/6 of that of the large high-precision network. After trained from scratch using the knowledge distillation technique, the detection performance of the lightweight neural network (sensitivity = 89.25%, specificity = 96.33%, the average precision [AP] = 0.85) is close to that of the high-precision network (sensitivity = 98.3%, specificity = 88.33%, AP = 0.91). By asynchronous calculation, we achieve real-time automatic detection of 24 fps (frames per second) on the ultrasound equipment. Our work proposes a method to realize the intelligence of the low-computation-power ultrasonic equipment, and successfully achieves the real-time assistant detection of breast lesions. The significance of the study is as follows: (1) The proposed method is of practical significance in assisting doctors to detect breast lesions; (2) our method provides some practical and theoretical support for the development and engineering of intelligent equipment based on artificial intelligence algorithms. © The Author(s) 2020.
A7: Laxmisagar, H.S.; Hanumantharaju, M.C. | B7: Design of an Efficient Deep Neural Network for Multi-level Classification of Breast Cancer Histology Images | C7: 2021 | D7: 4 | E7: https://www.scopus.com/inward/record.uri?eid=2-s2.0-85092725831&doi=10.1007%2F978-981-15-5566-4_40&partnerID=40&md5=6e196fdf9fa7acea758ac1273180ebe7 | F7: P | G7: Y | H7: =countif(Survey!$E$2:$E$57,E7) -> 0 | I7: Breast cancer is the second most prominent cause of death among women, and it is a major health problem across the world over the past many years. In this work, four hundred different biopsy images were collected from the Bio-imaging 2018 breast histology classification challenge by participating Grand Challenge on breast cancer histology images (BACH) for multiclass breast cancer histology image classification using deep learning technique. Computer-aided detection or diagnosis (CAD) system plays an important role in the detection and to increase death survival rate of women suffering from breast cancer, which can decrease death rate among women. The main purpose of this paper is to develop a CAD system which can be used to detect whether the input biopsy image fits one of the four different classes like benign, in situ, Invasive and Malignant. We have incorporated an efficient lightweight neural network such as MobileNet2.10ex instead of normal convolution neural network for feature extraction and at top a fully connected deep neural network is designed to do classification among different classes. The confusion matrix is developed in order to draw the model accuracy of both techniques. It is observed that MobleNet2.10ex is giving about 88.92 % training accuracy at 257 epochs and the corresponding loss value is 0.2249. In order to progress the performance during pre-processing, a staining technique was used to remove staining from a digital scan of histology microscopic image of fine-needle aspirate (FNA) slides and feature invariant approach such as data augmentation technique was used to rotate each image in pipeline about the axis 45° apart three times in order to increase dataset and prediction accuracy. The model was trained till 280 epochs to evaluate training and validation accuracy using Google Colab having strong GPU 2496 CUDA cores, 12 GB GDDR5 VRAM and 12.6 GB RAM. © 2021, Springer Nature Singapore Pte Ltd.
A8: Zahir, S.; Amir, A.; Zahri, N.A.H.; Ang, W.C. | B8: Applying the Deep Learning Model on an IoT Board for Breast Cancer Detection based on Histopathological Images | C8: 2021 | D8: 8 | E8: https://www.scopus.com/inward/record.uri?eid=2-s2.0-85102409958&doi=10.1088%2F1742-6596%2F1755%2F1%2F012026&partnerID=40&md5=3342ebdea94a79259464e7bf1b1f420c | F8: P | G8: Y | H8: =countif(Survey!$E$2:$E$57,E8) -> 0 | I8: In breast cancer diagnosis, pathologists evaluate microscopic images of tissue samples to determine if it is benign or malignant. The manual examination process could result in delayed diagnosis, which leads to late cancer treatment and can risk lives. In this paper, we proposed an automated, low-cost, and portable breast cancer detection based on histopathological images by using deep learning. The deep learning models were designed by using the Convolutional Neural Network (CNN). This paper compares the performance of the CNN model by using transfer learning utilizing a pre-trained model (VGG16) and the performance of a CNN model without transfer learning. The result shows that transfer learning provides a good base for classification of histopathological images. The model was successfully deployed on a Raspberry Pi, which demonstrates the model efficiency to run on a lightweight and portable processor. © 2021 Published under licence by IOP Publishing Ltd.
A9: Laxmisagar, H.S.; Hanumantharaju, M.C. | B9: Detection of Breast Cancer with Lightweight Deep Neural Networks for Histology Image Classification | C9: 2022 | D9: 13 | E9: https://www.scopus.com/inward/record.uri?eid=2-s2.0-85138239272&doi=10.1615%2FCritRevBiomedEng.2022043417&partnerID=40&md5=85ac07e56c86bb4fcdaee9cc247787e9 | F9: P | G9: Y | H9: =countif(Survey!$E$2:$E$57,E9) -> 0 | I9: Many researchers have developed computer-assisted diagnostic (CAD) methods to diagnose breast cancer using histopathology microscopic images. These techniques help to improve the accuracy of biopsy diagnosis with hematoxylin and eosin-stained images. On the other hand, most CAD systems usually rely on inefficient and time-consuming manual feature extraction methods. Using a deep learning (DL) model with convolutional layers, we present a method to extract the most useful pictorial information for breast cancer classification. Breast biopsy images stained with hematoxylin and eosin can be categorized into four groups namely benign lesions, normal tissue, carcinoma in situ, and invasive carcinoma. To correctly classify different types of breast cancer, it is important to classify histopathological images accurately. The MobileNet architecture model is used to obtain high accuracy with less resource utilization. The proposed model is fast, inexpensive, and safe due to which it is suitable for the detection of breast cancer at an early stage. This lightweight deep neural network can be accelerated using field-programmable gate arrays for the detection of breast cancer. DL has been implemented to successfully classify breast cancer. The model uses categorical cross-entropy to learn to give the correct class a high probability and other classes a low probability. It is used in the classification stage of the convolutional neural network (CNN) after the clustering stage, thereby improving the performance of the proposed system. To measure training and validation accuracy, the model was trained on Google Colab for 280 epochs with a powerful GPU with 2496 CUDA cores, 12 GB GDDR5 VRAM, and 12.6 GB RAM. Our results demonstrate that deep CNN with a chi-square test has improved the accuracy of histopathological image classification of breast cancer by greater than 11% compared with other state-of-the-art methods. © 2022 by Begell House, Inc.
A10: Kim, S.; Yoon, K. | B10: Deep and lightweight neural network for histopathological image classification | C10: 2022 | D10: 3 | E10: https://www.scopus.com/inward/record.uri?eid=2-s2.0-85139222990&doi=10.13052%2Fjmm1550-4646.18619&partnerID=40&md5=da2a1aa1668572887810f27b242c2214 | F10: P | G10: Y | H10: =countif(Survey!$E$2:$E$57,E10) -> 0 | I10: Breast cancer is a fatal disease affecting women, and early detection and proper treatment are crucial. Classifying medical images correctly is the first and most important step in the cancer diagnosis stage. Deep learning-based classification methods in various domains demonstrate advances in accuracy. However, as deep learning improves, the layers of neural networks get deeper, raising challenges, such as overfitting and gradient vanishing. For instance, a medical image is simpler than an ordinary one, making it vulnerable to overfitting issues. We present breast histopathological classification methods with two deep neural networks, Xception and LightXception with aid of voting schemes over split images. Most deep neural networks classify thousands classes of images, but the breast histopathological image classes are far fewer than those of other image classification tasks. Because the BreakHis dataset is relatively simpler than typical image datasets, such as ImageNet, applying the conventional highly deep neural networks may suffer from the aforementioned overfitting or gradient vanishing problems. Additionally, highly deep neural networks require more resources, leading to high computational costs. Consequently, we propose a new network; LightXception by cutting off layers at the bottom of the Xception network and reducing the number of channels of convolution filters. LightXception has only about 35% of parameters compared to those of the original Xception network with minimal expense on performance. Based on images with 100X magnification factor, the performance comparisons for Xception vs. LightXception are 97.42% vs. 97.31% on classification accuracy, 97.42% vs. 97.42% on recall, and 99.26% vs. 98.67% of precision. © 2022 River Publishers. All rights reserved.
A11: Huang, J.; Mei, L.; Long, M.; Liu, Y.; Sun, W.; Li, X.; Shen, H.; Zhou, F.; Ruan, X.; Wang, D.; Wang, S.; Hu, T.; Lei, C. | B11: BM-Net: CNN-Based MobileNet-V3 and Bilinear Structure for Breast Cancer Detection in Whole Slide Images | C11: 2022 | D11: 30 | E11: https://www.scopus.com/inward/record.uri?eid=2-s2.0-85132930127&doi=10.3390%2Fbioengineering9060261&partnerID=40&md5=2061b61f9c49957ac6fa8f9427c5bb70 | F11: P | G11: Y | H11: =countif(Survey!$E$2:$E$57,E11) -> 0 | I11: Breast cancer is one of the most common types of cancer and is the leading cause of cancer-related death. Diagnosis of breast cancer is based on the evaluation of pathology slides. In the era of digital pathology, these slides can be converted into digital whole slide images (WSIs) for further analysis. However, due to their sheer size, digital WSIs diagnoses are time consuming and challenging. In this study, we present a lightweight architecture that consists of a bilinear structure and MobileNet-V3 network, bilinear MobileNet-V3 (BM-Net), to analyze breast cancer WSIs. We utilized the WSI dataset from the ICIAR2018 Grand Challenge on Breast Cancer Histology Images (BACH) competition, which contains four classes: normal, benign, in situ carcinoma, and invasive carcinoma. We adopted data augmentation techniques to increase diversity and utilized focal loss to remove class imbalance. We achieved high performance, with 0.88 accuracy in patch classification and an average 0.71 score, which surpassed state-of-the-art models. Our BM-Net shows great potential in detecting cancer in WSIs and is a promising clinical tool. © 2022 by the authors. Licensee MDPI, Basel, Switzerland.
A12: Garg, S.; Singh, P. | B12: Transfer Learning Based Lightweight Ensemble Model for Imbalanced Breast Cancer Classification | C12: 2023 | D12: 31 | E12: https://www.scopus.com/inward/record.uri?eid=2-s2.0-85132534568&doi=10.1109%2FTCBB.2022.3174091&partnerID=40&md5=e4a812f8afb738e87a9fcc87c306ca63 | F12: P | G12: Y | H12: =countif(Survey!$E$2:$E$57,E12) -> 0 | I12: Automated classification of breast cancer can often save lives, as manual detection is usually time-consuming expensive. Since the last decade, deep learning techniques have been most widely used for the automatic classification of breast cancer using histopathology images. This paper has performed the binary and multi-class classification of breast cancer using a transfer learning-based ensemble model. To analyze the correctness and reliability of the proposed model, we have used an imbalance IDC dataset, an imbalance BreakHis dataset in the binary class scenario, and a balanced BACH dataset for the multi-class classification. A lightweight shallow CNN model with batch normalization technology to accelerate convergence is aggregated with lightweight MobileNetV2 to improve learning and adaptability. The aggregation output is fed into a multilayer perceptron to complete the final classification task. The experimental study on all three datasets was performed and compared with the recent works. We have fine-tuned three different pre-trained models (ResNet50, InceptionV4, and MobilNetV2) and compared it with the proposed lightweight ensemble model in terms of execution time, number of parameters, model size, etc. In both the evaluation phases, it is seen that our model outperforms in all three datasets. © 2004-2012 IEEE.
A13: Patel, W.; Koyuncu, H.; Ganatara, A. | B13: Revolutionizing Cancer Diagnosis in IoMT with a Novel Lightweight Deep Learning Model for Histopathological Image Classification | C13: 2023 | D13: 1 | E13: https://www.scopus.com/inward/record.uri?eid=2-s2.0-85190115921&doi=10.1109%2FMoSICom59118.2023.10458800&partnerID=40&md5=fd257c5075ecd94fecf725ea2a1fdc8a | F13: P | G13: Y | H13: =countif(Survey!$E$2:$E$57,E13) -> 0 | I13: Our proposed solution for breast cancer diagnosis offers a highly reliable and efficient alternative to the traditional manual examination method. By utilizing deep learning models designed with Convolutional Neural Networks (CNN), We have created a breast cancer detection system that is automated, inexpensive, and easy to transport. A system that significantly reduces the risk of delayed diagnosis and saves lives. This approach relies on an integrated ultrasensitive micro-bio-heat sensor array structured as a 3x3 grid using Altium software. The array functions as an embedded system aiming for the early identification of breast cancer. Leveraging IoT advancements, this system can connect with a server through smartphones. This study demonstrates the effectiveness of switch getting to know in histopathological photo classification. This research assesses the effectiveness of CNN models, both with and without transfer learning. It uses a pre-Trained VGG16 model for image classification and demonstrates its successful implementation on a Raspberry Pi. This highlights its efficiency when running on a lightweight and portable processor. Our experimental results show that our system achieves an accuracy of 78% on the BreakHis database and can run on a Raspberry Pi device with minimal resources. © 2023 IEEE.
... A24: Modu, F.; Prasad, R.; Aliyu, F. | B24: Lightweight CNN for Resource-Constrained BCD System Using Knowledge Distillation | C24: 2025 | D24: 1 | E24: https://www.scopus.com/inward/record.uri?eid=2-s2.0-105002579088&doi=10.1109%2FACCESS.2025.3556517&partnerID=40&md5=af2b9a52232016fa55ca4b11e136a7d9 | F24: P | G24: Y | H24: =countif(Survey!$E$2:$E$57,E24) -> 0 | I24: Breast cancer (BC) remains a leading cause of mortality among women worldwide, with over two million new cases annually. Early detection improves survival rates significantly, yet resource limitations in low- and middle-income countries (LMICs) hinder access to advanced diagnostic tools. While deep learning (DL) models have shown high accuracy in breast cancer detection (BCD), their computational complexity and hardware requirements make them impractical for deployment on low-power devices. To address this, we propose a lightweight convolutional neural network (CNN) for BCD, leveraging knowledge distillation (KD) to transfer knowledge from a complex teacher model (TM) to a smaller student model (SM). Our approach achieves up to 99.3% accuracy, 100% precision, and 99% recall while reducing the number of trainable parameters by 87% compared to conventional deep models. The proposed model successfully runs on a Raspberry Pi 4B with an inference time of 500 ms and memory usage of just 12% (of 8GB RAM), demonstrating its suitability for telemedicine and mobile diagnostics. Additionally, resource utilization experiments confirm that inference remains stable at 10% CPU usage and 40°C when using a heat sink and fan, ensuring sustained deployment. Future work will explore federated learning for decentralized training, integration of multimodal data for enhanced diagnosis, and cloud-based model updates using delay-tolerant networks (DTNs) for remote healthcare applications. © 2013 IEEE.
B25: 2013 4th International Conference on Material and Manufacturing Technology, ICMMT 2013 | C25: 2013 | D25: 0 | E25: https://www.scopus.com/inward/record.uri?eid=2-s2.0-84884785762&partnerID=40&md5=31e4db38afaa379c6aa0f56556b495bd | F25: IR | H25: =countif(Survey!$E$2:$E$57,E25) -> 0 | I25: The proceedings contain 251 papers. The special focus in this conference is on Materials Engineering and Technology, Mechanical Engineering, Design Technology and Engineering, Applied Thermodynamics, Mechatronics and Robotics, Modern Control, Automation and Reverse Engineering, Civil Engineering, Manufacturing and Industrial Engineering and Data Mining, Information Technologies and Networks. The topics include: Flexural strength of PLA/kenaf green composite; aging behavior of the polyether polyurethane films irradiated by UV; synthesis of Fe-Al<inf>2</inf>O<inf>3</inf> composite by high-frequency induction-heated combustion; self-propagating high-temperature synthesis of Fe-W(B, C) based composite; electrochromic performance of NiO films in alkaline medium; oxidation of oxide dispersion strengthened steels; optimization of parameters in fiber reinforced polyurethane composited reaction injection molding; study on the foaming behavior of PS-CO2 by using water or ethanol as Co-blowing agent; the metastable phase responsible for hardenig in an Al-Mg alloy aged at 473K; investigations of nanostructure and photoluminescence properties of nanoporous silicon; characterization of high density solid waste biopolymer foam; effect of applied current density on the electrodeposition of Ni on Ti substrate; morphology and mechanical properties of HDPE/bio-polymer as compounding materials; mechanical properties of UV irradiated bio polymer thin films doped with titanium dioxide; adhesive bonding strength and adhesive penetration of two malaysian medium hardwoods; research development of the laser surface modification to improve the corrosion-resistance of titanium and titanium alloys; research progress of the surface oxidation of titanium and its alloys; development status of laser clad cobalt-based alloy coatings; application of the high strength steel in the automobile; effect of crack length on mixed-mode cohesive fracture of the adhesively bonded joints; a case study on effect of feed rate on machinability of austempered ductile iron; grinding force research on nanostructured ceramic coatings; research on nano-ceramic coatings precision grinding; CO<inf>2</inf> laser cladding of mild steel using iron based powder and silicon carbide particles; acoustic study based on sustainable green polymer treated with H2O; dynamic response of FDM made ABS parts in different part orientations; scaling up process output of monomer reactor; characterization of rice straw ash and utilization in glass production; investigation on carbon fiber composites as architectural EMI shielding material; durability of traffic signs and retroreflective materials; performance study on scale inhibition of biodegradable water treatment agent; simulation of laser-induced thermoelastic behavior in metal plates; stress analysis and fatigue life estimation of bridge rubber bearing; optimization design of a framework for an infrared seeker; the higher order crack-tip field for reissners power FGMs spherical shell; A Z-map based approach for extracting the groove shape of impeller; an efficient diffusion model for a real-time gas diffusion simulation system; design and simulation on righting manipulator of the remote control in workover operations; lightweight design optimization of large-tonnage hydraulic press body structure; prediction of long-term properties of fiberglass pipe based on the shift factors method; nonlinear aerodynamics reduced-order model based on multi-input volterra series; positive solutions of a strongly coupled prey-predator system; algorithm and realization of wind power prediction system; an improved islanding detection method for photovoltaic grid-connected system; switch technology in intelligent substation; study on energy optimization of clutch based on energy design factor; a combination method for mid-long term power load simulation and prediction; study of dual-active series resonant DC-DC converter for high power applications; capacitor group zero-crossing switching control system design; research and design of air conditioning air flow test bench; mono pulse confocal microwave imaging in breast cancer detection; two-dimensional laser detection front end circuit and algorithm; detection of pilot-induced oscillation (PIO); real time web based monitoring and calibration system for diesel engine; a safety monitoring device for firefighters based on wireless localization algorithm; garlic cutting umbilical based on image processing and GUI; clustering based on a novel density estimation method; analysis based on the remote sensing image of harbin urban heat island effect; the research on multiscale image fusion based on the dualtree complex wavelet; gesture recognition for briefing application; method on 3D dense point cloud recovery of geographical scene; implementation of unitary music algorithm using Xilinx system generator; sound source localization based on microphone uniform linear array; method of harmonic detection based on the wavelet transform; research and simulation of image histogram matching; based on HMM intonation prosody prediction of Tibetan TTS; the application of CRI method in fuzzy reasoning; fuzzy recognition intelligent system based on cash character; the perception system of external world for robot; a robot simulation system for self-location by using field visual information; sound analysis and synthesis for audio simulation system of flight simulator; research on the vision processing of space robot's tracking camera; the design of servo system for azimuth of directional antenna based on PMSM; application of sliding mode cascade controller in AC servo system; research on the detection unit and control system of CNC cool frame bender; semistability of nonlinear control systems; the study of DC motor position controller parameter setting and simulation; with DGPS-RTK terminal yard cranes real-time operating system; temperature controller of heating furnace based on fuzzy neural network technology; design of direct digital synthesizer based on FPGA; a study for embedded software double-fault testability; design of the high-speed high-resolution latched comparator; design of a novel excitation circuit for low perming error fluxgate; design of SDH positive/zero/negative justification circuits based on FPGA; distribution network and multiple power bi-level programming; important position of information science in studying complex system; security research and measures for the internet of things; critical evaluation on steganography metrics; efficient scratchpad memory management for mobile multimedia application; modeling and simulation of FC-AE-ASM network; implementation of vehicle control system based on IPV6-CAN gateway; a provably secure e-cash scheme with loss-tracing; a note on optimal function for similarity measure in ontology application; a simple multi-models rendering framework - PM-OCMMRF; system design considerations for satellite communications on the move; an identity on resistance distances; simulation for view selection in data warehouse; internal cloud storage architecture implemented in crop germplasm resources data; analysis of precast piles for piling process; preparation and verification of a limit protective isolation structural analysis programs; research of cascade reservoirs flood limit level dynamic control based on game theory; hydrologic and hydraulic analysis of city flood control; the property of hierarchical structure in manufacturing; tools management solution for small enterprises; PLC-based laboratory intelligent management system; investigation on safety condition of cell phone charging; analyzing crash frequency by collision type at freeway diverge areas and study of logistics warehouse management system based on RFID.
B26: 2015 5th International Conference on Computer and Knowledge Engineering, ICCKE 2015 | C26: 2015 | D26: 0 | E26: https://www.scopus.com/inward/record.uri?eid=2-s2.0-84964444601&partnerID=40&md5=2ee5946f8c55e6a977c2c788fc1c7690 | F26: IR | H26: =countif(Survey!$E$2:$E$57,E26) -> 1 | I26: The proceedings contain 58 papers. The topics discussed include: optimization of budgeting type 2 diabetes through modeling disease burden; WS-TWSVM: weighted structural twin support vector machine by local and global information; necessity of laboratory blood tests in intensive care unit using data mining; diagnosis of type 2 diabetes using cost-sensitive learning; BetaProbe: a probability based method for predicting beta sheet topology using integer programming; design of an automated system for detection and classification of power quality disturbances; applying grey wolf optimizer-based decision tree c1assifer for cancer classification on gene expression data; designing a pervasive eye movement-based system for ALS and paralyzed patients; spectral clustering-based classification; a high-speed FPGA implementation of a bit-slice ultra-lightweight block cipher, RECTANGLE; and identification of gene signatures for classifying of breast cancer subtypes using protein interaction database and support vector machines.
A27: Li, J.; Liu, H.; Brown, M.; Kumar, P.; Challacombe, B.J.; Chandra, A.; Rottenberg, G.; Seneviratne, L.D.; Althoefer, K.; Dasgupta, P. | B27: Ex vivo study of prostate cancer localization using rolling mechanical imaging towards minimally invasive surgery | C27: 2017 | D27: 4 | E27: https://www.scopus.com/inward/record.uri?eid=2-s2.0-85013215035&doi=10.1016%2Fj.medengphy.2017.01.021&partnerID=40&md5=4c642cbfe3caf47a0794a3ac8dd7bc70 | F27: ST | H27: =countif(Survey!$E$2:$E$57,E27) -> 0 | I27: Rolling mechanical imaging (RMI) is a novel technique towards the detection and quantification of malignant tissue in locations that are inaccessible to palpation during robotic minimally invasive surgery (MIS); the approach is shown to achieve results of higher precision than is possible using the human hand. Using a passive robotic manipulator, a lightweight and force sensitive wheeled probe is driven across the surface of tissue samples to collect continuous measurements of wheel-tissue dynamics. A color-coded map is then generated to visualize the stiffness distribution within the internal tissue structure. Having developed the RMI device in-house, we aim to compare the accuracy of this technique to commonly used methods of localizing prostate cancer in current practice: digital rectal exam (DRE), magnetic resonance imaging (MRI) and transrectal ultrasound (TRUS) biopsy. Final histology is the gold standard used for comparison. A total of 126 sites from 21 robotic-assisted radical prostatectomy specimens were examined. Analysis was performed for sensitivity, specificity, accuracy, and predictive value across all patient risk profiles (defined by PSA, Gleason score and pathological score). Of all techniques, pre-operative biopsy had the highest sensitivity (76.2%) and accuracy (64.3%) in the localization of tumor in the final specimen. However, RMI had a higher sensitivity (44.4%) and accuracy (57.9%) than both DRE (38.1% and 52.4%, respectively) and MRI (33.3% and 57.9%, respectively). These findings suggest a role for RMI towards MIS, where haptic feedback is lacking. While our approach has focused on urological tumors, RMI has potential applicability to other extirpative oncological procedures and to diagnostics (e.g., breast cancer screening). © 2017
A28: Taruno, K.; Kurita, T.; Kuwahata, A.; Yanagihara, K.; Enokido, K.; Katayose, Y.; Nakamura, S.; Takei, H.; Sekino, M.; Kusakabe, M. | B28: Multicenter clinical trial on sentinel lymph node biopsy using superparamagnetic iron oxide nanoparticles and a novel handheld magnetic probe | C28: 2019 | D28: 59 | E28: https://www.scopus.com/inward/record.uri?eid=2-s2.0-85074788048&doi=10.1002%2Fjso.25747&partnerID=40&md5=70f25536527d62085c4b183b2e096bd8 | F28: SA | H28: =countif(Survey!$E$2:$E$57,E28) -> 0 | I28: Background: Sentinel lymph node biopsy is a standard staging procedure for early axillary lymph node-negative breast cancer. As an alternative to the currently used radioactive tracers for sentinel lymph node (SLN) detection during the surgical procedure, a number of studies have shown promising results using superparamagnetic iron oxide (SPIO) nanoparticles. Here, we developed a new handheld, cordless, and lightweight magnetic probe for SPIO detection. Methods: Resovist (SPIO nanoparticles) were detected by the newly developed handheld probe, and the SLN detection rate was compared to that of the standard radioisotope (RI) method using radioactive colloids (99mTc) and a blue dye (indigo carmine). This was a multicenter prospective clinical trial that included 220 patients with breast cancer scheduled for sentinel node biopsy after a clinical diagnosis of negative axillary lymph node from three facilities in Japan. Results: Of the 210 patients analyzed, SLN was detected in 94.8% (199/210 cases, 90% confidence interval [CI]) with our magnetic method and in 98.1% (206/210 cases, 90% CI) with the RI method. The magnetic method exceeded the threshold identification rate of 90%. Conclusion: This was the first clinical study to use a novel handheld magnetometer to detect SLN, which we demonstrate to be not inferior to the RI method. © 2019 Wiley Periodicals, Inc.
A29: Alam, M.W.; Wahid, K.A.; Goel, R.K.; Lukong, K.E. | B29: Development of a low-cost and portable smart fluorometer for detecting breast cancer cells | C29: 2019 | D29: 21 | E29: https://www.scopus.com/inward/record.uri?eid=2-s2.0-85061546246&doi=10.1364%2FBOE.10.000399&partnerID=40&md5=96f5a52dac94266494bd0706762bb7a5 | F29: SA | H29: =countif(Survey!$E$2:$E$57,E29) -> 0 | I29: Instruments that allow the detection of fluorescence signal are invaluable tools for biomedical and clinical researchers. The technique is widely used in cell biology to microscopically detect target proteins of interest in mammalian cells. Importantly, fluorescence microscopy finds major applications in cancer biology where cancer cells are chemically labelled for detection. However, conventional fluorescence detection instruments such as fluorescence imaging microscopes are expensive, not portable and entail potentially high maintenance costs. Here we describe the design, development and applicability of a low-cost and portable fluorometer for the detection of fluorescence signal emitted from a model breast cancer cell line, engineered to stably express the green fluorescent protein (GFP). This device utilizes a flashlight which works in the visible range as an excitation source and a photodiode as the detector. It also utilizes an emission filter to mainly allow the fluorescence signal to reach the detector while eliminating the use of an excitation filter and dichroic mirror, hence, making the device compact, low-cost, portable and lightweight. The custom-built sample chamber is fabricated with a 3D printer to house the detector circuitry. We demonstrate that the developed fluorometer is able to distinguish between the cancer cell expressing GFP and the control cell. The fluorometer we developed exhibits immense potential for future applicability in the selective detection of fluorescently-labelled breast cancer cells. © 2019 Optical Society of America.
A30: Nandhini, V.L.; Roy, S.K.; Babu, K. | B30: Detection of malignant tissue using metal dielectric interface based plasmonic biosensor | C30: 2019 | D30: 2 | E30: https://www.scopus.com/inward/record.uri?eid=2-s2.0-85071679965&doi=10.35940%2Fijitee.F1274.0486S419&partnerID=40&md5=71389f2e941c91469619606bd365f7d4 | F30: SA | H30: =countif(Survey!$E$2:$E$57,E30) -> 0 | I30: Metal-dielectric interface based Plasmonic biosensors commonly known as Surface Plasmonic Resonance (SPR) used in numerous applications in the analysis of bio reagents interaction and detection of the biological pathogen, cells and provides the advantage of real-time label-free efficient method. Sensitivity is a key parameter to measure sensor performance during development. Among all the plasmonic configurations, waveguide coupled configuration is most effective. In such a configuration an SPR and a waveguide are coupled through an evanescent field. This provides superior control over the biological reagent interaction, greater sensitivity and a multichannel-robust sensing device. Such devices are very small in size, lightweight as compared to prism coupled configuration which is bulky. These devices are also equipped to segregate specific sensor responses from non-specific response simultaneous multi analytes analysis. In view of the aforesaid benefits of waveguide coupled SPR, our present work focuses on a dual channel integrated optical waveguide based on metal dielectric interface biosensor. To study the behaviour of a waveguide coupled SPR sensor, we carried out analysis and simulation of SPR on multilayer geometries using tumour-associated antigens (TAAs). First, we started with the analysis of an SPR in the multi-layer intersection and observed the effect of variation of material characteristics on SPR profile. Further, extended our investigation to multilayered optical waveguide and the propagation constant was calculated. TAA and Newton’s method were used for Lung Cancer and Breast Cancer infected tissue and sensitivity 300nm/RIU obtained. © BEIESP.
B31: 2nd International Conference on Healthcare Science and Engineering, Healthcare 2018 | C31: 2019 | D31: 0 | E31: https://www.scopus.com/inward/record.uri?eid=2-s2.0-85065909723&partnerID=40&md5=1d86e21bff3a5377d0081b262702121e | F31: IR | H31: =countif(Survey!$E$2:$E$57,E31) -> 1 | I31: The proceedings contain 21 papers. The special focus in this conference is on Healthcare Science and Engineering. The topics include: Privacy management in social network data publishing with community structure; multidimensional correlation hierarchical differential privacy for medical data with multiple privacy requirements; injecting differential privacy in rules extraction of rough set; a lightweight neural network to detect arrhythmias; bayesian differential privacy for high-dimensional medical data optimization; Auxiliary force EEG (AFEEG) recognition oriented to stroke patients; a multi-valued fuzzy logic for qualitative reasoning in healthcare; a new approach for anonymizing relational and transaction data; fall detection using a multistage deep convolutional network architecture; robust feature selection method of radiomics for grading glioma; Performance evaluation of RPL-based sensor data collection in challenging IoT environment; low-cost system for travel aid and obstacles detection for the visually impaired people; cardiovascular disease risk prediction based on random forest; ECG beat classification based on deep bidirectional long short-term memory recurrent neural network; deep convolutional neural networks for electrocardiogram classification; transfer learning-based behavioural task decoding from brain activity; fine-tuning ResNet for breast cancer classification from mammography; lung sound diagnosis with deep convolutional neural network and two-stage pipeline model; an improved data anonymization algorithm for incomplete medical dataset publishing.
A32: Liu, S.; Ren, J.; Chen, Z.; Hu, K.; Xiao, F.; Li, X.; Gao, X. | B32: EffiDiag: An Efficient Framework for Breast Cancer Diagnosis in Multi-Gigapixel Whole Slide Images | C32: 2020 | D32: 5 | E32: https://www.scopus.com/inward/record.uri?eid=2-s2.0-85100334328&doi=10.1109%2FBIBM49941.2020.9313511&partnerID=40&md5=fb3d8f43c53000a15005cfd528649a9e | F32: P | G32: Y | H32: =countif(Survey!$E$2:$E$57,E32) -> 0 | I32: Breast cancer diagnosis in multi-gigapixel whole slide images (WSIs) is an important task that highly relevant to cancer grading and prognosis. In recent years, many computer-aided diagnosis methods were proposed and achieved promising performance. However, they mostly suffer from heavy computational burden that becomes a significant barrier to clinical practice. Efficient solutions are urgently demanded but still less studied. In this paper, we propose a novel framework named EffiDiag for a fast and lightweight breast cancer diagnosis. To this end, a loss-modified U-net is developed at first to enable a fast suspected cancer Region Of Interest (ROI) localization. Therefore the subsequent patch-based classification, which commonly executes at the finest magnification hundreds of thousands times per WSI for cancer identification, could be carried out on these ROIs only rather than the whole WSI for speedup. Meanwhile, a super-efficient convolutional neural network (CNN) is devised to optimize the classification speed and resource consumption per classification. Experiments on the Camelyonl6 benchmark demonstrate, by integrating the two contributions into a well-established approach, 47x inference acceleration is obtained with limited accuracy drop, yet with much less resource consumption even compared to popular lightweight networks. © 2020 IEEE.
A33: Sanghavi, F.; Kezebou, L.; Panetta, K.; Agaian, S. | B33: Breast cancer classification using parametric free thresholding adjacency statistics based Fibonacci patterns | C33: 2020 | D33: 2 | E33: https://www.scopus.com/inward/record.uri?eid=2-s2.0-85096352764&doi=10.1117%2F12.2558613&partnerID=40&md5=35bb3dd9c3a25059486a1936eef82f45 | F33: P | G33: Y | H33: =countif(Survey!$E$2:$E$57,E33) -> 0 | I33: According to the American cancer society, the average risk of women getting diagnosed with breast cancer during their life is 13%. The World Health Organization also reports that the number of cancer cases is projected to rise to 19.3 million by 2025. Recent research works point out that physicians can only diagnose cancer with 79% accuracy while machine learning procedures achieve 91% accuracy or more. The current challenges are early cancer detection and the efficient and accurate diagnosis of histopathology tissue samples. Several Deep Learning breast cancer classification models have been developed to assist medical practitioners. However, these methods are data hungry and require thousands of training image samples, often coupled with data augmentation to achieve satisfactory results with long training hours. In this paper, we propose a machine learning classification model by integrating the Parameter free Thresholding Adjacency Statistics (PFTAS) with Fibonacci-p patterns for breast cancer detection. Computer simulations on BreakHis cancer datasets in comparison to other machine learning and deep learning-based methods show that (i) the presented method helps eliminate dependence on large training data and data augmentation, (ii) robustness to noise and background stains, and (iii) lightweight model easy to train and deploy. © 2020 SPIE
A34: Roslidar, R.; Rahman, A.; Muharar, R.; Syahputra, M.R.; Arnia, F.; Syukri, M.; Pradhan, B.; Munadi, K. | B34: A Review on Recent Progress in Thermal Imaging and Deep Learning Approaches for Breast Cancer Detection | C34: 2020 | D34: 134 | E34: https://www.scopus.com/inward/record.uri?eid=2-s2.0-85087800211&doi=10.1109%2FACCESS.2020.3004056&partnerID=40&md5=6b6ab728d09e8e7a1c908b4e78500b47 | F34: P | G34: Y | H34: =countif(Survey!$E$2:$E$57,E34) -> 0 | I34: Developing a breast cancer screening method is very important to facilitate early breast cancer detection and treatment. Building a screening method using medical imaging modality that does not cause body tissue damage (non-invasive) and does not involve physical touch is challenging. Thermography, a non-invasive and non-contact cancer screening method, can detect tumors at an early stage even under precancerous conditions by observing temperature distribution in both breasts. The thermograms obtained on thermography can be interpreted using deep learning models such as convolutional neural networks (CNNs). CNNs can automatically classify breast thermograms into categories such as normal and abnormal. Despite their demostrated utility, CNNs have not been widely used in breast thermogram classification. In this study, we aimed to summarize the current work and progress in breast cancer detection based on thermography and CNNs. We first discuss of breast thermography potential in early breast cancer detection, providing an overview of the availability of breast thermal datasets together with publicly accessible. We also discuss characteristics of breast thermograms and the differences between healthy and cancerous thermographic patterns. Breast thermogram classification using a CNN model is described step by step including a simulation example illustrating feature learning. We cover most research related to the implementation of deep neural networks for breast thermogram classification and propose future research directions for developing representative datasets, feeding the segmented image, assigning a good kernel, and building a lightweight CNN model to improve CNN performance. © 2013 IEEE.
A35: Koma’rudin, N.; Zakaria, Z.; Soh, P.J.; Lago, H.; Alsariera, H.; Hassan, N. | B35: A review of recent microwave breast imaging | C35: 2020 | D35: 4 | E35: https://www.scopus.com/inward/record.uri?eid=2-s2.0-85092131911&doi=10.15866%2Firecap.v10i4.18560&partnerID=40&md5=8ce1c48bc14fe53278896f221f0c083c | F35: P | G35: Y | H35: =countif(Survey!$E$2:$E$57,E35) -> 0 | I35: Cancer is an asymptomatic disease that can easily affect tissues in multiple parts of the body, and it is one of the leading causes of death. Therefore, it is crucial to detect cancer tissues at the early stage. Moreover, measurement techniques and instruments that can be used for their backscattered signal gathering, processing and image reconstruction are crucial to ensure the accuracy of generated image; hence, the accuracy of tumour detection in breasts. One of the most critical components that should be carefully designed in such systems is the radiator, which functions as the main sensing component. Ideally, it should be lightweight, compact, wideband and unidirectional. By using such radiator, the performance of the antennas can be improved in terms of directivity, gain, efficiency and Specific Absorption Rate (SAR) to result in measurements with close accuracy compared to conventional medical imaging. This paper presents a review of the sensing requirements for microwave breast imaging application, which is aimed to provide a proper understanding, importance and recent developments of radiator and hardware for microwave imaging (MWI) application. © 2020 Praise Worthy Prize S.r.l.-All rights reserved.
A36: Moussa, M.N.; Madi, M.A.; Kabalan, K.Y. | B36: Miniaturized Inward Fractal Antenna for Breast Cancer Detection | C36: 2021 | D36: 6 | E36: https://www.scopus.com/inward/record.uri?eid=2-s2.0-85126741088&doi=10.1109%2FICECET52533.2021.9698733&partnerID=40&md5=187048564131139517e83cff935e163d | F36: SA | H36: =countif(Survey!$E$2:$E$57,E36) -> 0 | I36: The number of cancer diagnosed patients is rapidly increasing nowadays. Therefore, researchers are putting tremendous efforts to achieve efficient early cancer detection techniques in order to improve the survival rates as much as possible. Along this line and using EM detection approach, a miniaturized inward fractal antenna of size text{10} times 10 text{mm}{2} {(0.25lambdatimes 0.25lambda)} is designed, simulated in HFSS, fabricated on an FR4 substrate, and measured using a VNA network analyzer. It shows good impedance matching at 7.7 GHz with a gain of 2.9 dBi. This antenna is a good candidate for detecting the presence of a breast tumor because it is easy to fabricate by chemical etching with a low cost. Also, having a lightweight of 2g and a small size makes it suitable for wearable detection systems. © 2021 IEEE.
B37: International Conference on Intelligent Computing and Networking, IC-ICN 2020 | C37: 2021 | D37: 0 | E37: https://www.scopus.com/inward/record.uri?eid=2-s2.0-85096498383&partnerID=40&md5=96864cec68a1d7daf114c68cb5099620 | F37: IR | H37: =countif(Survey!$E$2:$E$57,E37) -> 1 | I37: The proceedings contain 27 papers. The special focus in this conference is on Intelligent Computing and Networking. The topics include: Exploiting Processor Variability for Efficient Application Mapping; data Sharing Over the Cloud Based on Ring Signature; data Analytics on Columnar Databases in Big Data Environment; real Time Multiple Object Detection on Low-Constrained Devices using Lightweight Deep Neural Network; Researcher Framework Using MongoDB and FCM Clustering for Prediction of the Future of Patients from EHR; performance Level Evaluation of Cryptographic Algorithms; driver Activity Monitoring Using MobileNets; a Review of Deep Learning Techniques Used in Breast Cancer Image Classification; Prediction of nMAG in PMIPv6 with the Help of MN Positions; surveillance System for Intruder Detection Using Facial Recognition; clinical Risk Prediction of Acute Coronary Syndrome Using Deep Learning Approach; genetic Algorithm for Feature Selection and Parameter Optimization to Enhance Learning on Framingham Heart Disease Dataset; securing IoT Devices Generated Data Using Homomorphic Encryption; Secure Data Aggregation and Data Transmission Using HMAC Protocol in Cluster Base Wireless Sensor Network; performance Evaluation of Adversarial Examples on Deep Neural Network Architectures; study on Analysis of Gene Expression Dataset and Identification of Differentially Expressed Genes; A Modified EDDKA Routing Approach to Enhance Quality of Service (QoS)-Enabled Data Dissemination in VANETs; a Novel and Secure Approach for Quantum Key Distribution in a Cloud Computing Environment; voting Using Blockchain Technology; deepfake Detection Approaches Using Deep Learning: A Systematic Review; secured Crowdfunding Platform Using Blockchain; review of Wireless Sensor Network Security Schemes; development of Agriculture Field Using Machine Learning.
B38: International Conference on Evolving Technologies for Computing, Communication and Smart World, ETCCS 2020 | C38: 2021 | D38: 0 | E38: https://www.scopus.com/inward/record.uri?eid=2-s2.0-85097683791&partnerID=40&md5=343726d9201692790d3e0204dad8e140 | F38: IR | H38: =countif(Survey!$E$2:$E$57,E38) -> 1 | I38: The proceedings contain 40 papers. The special focus in this conference is on Evolving Technologies for Computing, Communication and Smart World. The topics include: Event-Triggered Share Price Prediction; a Review: Efficient Transportation—Future Aspects of IoV; Compact High Gain 28 GHz Concentric Circular Director Low-Cost Antenna for 5G Millimeter-Wave Communication; preface; toward Response-Type Identification for the Real Time; questionnaire-Based Prediction of Hypertension Using Machine Learning; nature-Inspired Computing Behaviour of Cellular Automata; a Survey on Transport Layer Protocols for Reliable and Secure Wireless Sensor Networks; A Lightweight Exchangeable Encryption Scheme for IoT Devices Based on Vigenere Cipher and MLS Keystream; improving Steepest Descent Method by Learning Rate Annealing and Momentum in Neural Network; fingerprint and Face-Based Secure Biometric Authentication System Using Optimized Robust Features; DevOps, DevSecOps, AIOPS- Paradigms to IT Operations; Optimized Route Discovery and Node Registration for FANET; 4.1 GHz Low-Phase Noise Differential XCP LC-VCO with High Q and LC Noise Filtering; secured Surveillance Storage Model Using Blockchain; automatic Leaf Species Recognition Using Deep Neural Network; information Retrieval in Financial Documents; VNF Security in Telco Environment; Rank-Level Fusion of Random Indexing, Word Embedding, and TF-IDF-Based Rankings for Clinical Document Retrieval; a Novel Feature Engineering Approach for Twitter-Based Text Sentiment Analysis; Survey on DDoS and EDoS Attack in Cloud Environment; preprocessing Steps for Opinion Mining on Tweets; machine Learning-Based Lightweight Android Malware Detection System with Static Features; area and Power Efficient 2 Bit Multiplier by Using Enhanced Half Adder; the Modified Algorithm of Quantum Key Distribution System Synchronization; breast Cancer Classification Using Transfer Learning.
A39: Ahmad, B.; Sun, S.; Li, J.; Lidan, B. | B39: Comparative Study of Deep Learning Models For Automatic Detection of Metastases in HE Stained Images | C39: 2021 | D39: 4 | E39: https://www.scopus.com/inward/record.uri?eid=2-s2.0-85125349633&doi=10.1109%2FICCIS54243.2021.9676187&partnerID=40&md5=1f418c7a52230bcb6b8e2c667c7f672a | F39: P | G39: Y | H39: =countif(Survey!$E$2:$E$57,E39) -> 0 | I39: Deep learning has gained the attention of researchers around the world. We used several deep learning models to check whether they could potentially be used as a clinical utility by pathologists to detect lymph node metastases in tissue sections of women with breast cancer to save time and reduce the burden on healthcare. For that purpose, we selected three deep learning models of different depths. The deepest one (DenseNet201), medium depth (Resent50), lightweight (Mobie/Net) and trained them in different experiments under various hyperparameters settings from scratch. The test set consists of 32000 histopathological images. We used absolute accuracy, sensitivity, specificity, and F1-score as a performance measure. Apart from these measures, we observe the effect of data augmentation and the number of epochs on the classification performance. We achieved an average accuracy of 85.6%, 87.5%, and 88.4% for MobileNet V1, ResNet50, and DenseNet201, respectively, which further improves to 91.1 %, 93.8%, and 95.7%, respectively, when augmented images are used in the training set. The performance of all deep learning models was on par with that of expert pathologists reported in different studies. We may expect that deep learning could be an exceptional utility for clinicians in real-time diagnosis too. © 2021 IEEE.
B40: Proceedings - 2022 International Conference on Machine Learning and Intelligent Systems Engineering, MLISE 2022 | C40: 2022 | D40: 0 | E40: https://www.scopus.com/inward/record.uri?eid=2-s2.0-85143079638&partnerID=40&md5=f6d79e7d735d735686810e35e4b2d6ff | F40: IR | H40: =countif(Survey!$E$2:$E$57,E40) -> 1 | I40: The proceedings contain 94 papers. The topics discussed include: classification method of surface defects of aluminum profile based on transfer learning; an improved anchor-free object detection method; lightweight real-time object detection system based on embedded ai development kit; video content understanding based on feature selection and semantic alignment network; transferability of pretrained convolutional neural networks for breast cancer detection; analyzing the determinations of financial inclusion in Africa based on random forest model and logistic regression model; the impact of the distance sensors orientation on the obstacle avoidance ability of the robot; research on the performance of different convolutional neural network models on small datasets; construction method of network feasible path for power data platform; resource management scheduling-based on proximal policy optimization; and a study of fair prediction on credit assessment based on counterfactual fairness.
A41: Chavan, T.; Prajapati, K.; Jv, K.R. | B41: InvUNET: Involuted UNET for Breast Tumor Segmentation from Ultrasound | C41: 2022 | D41: 4 | E41: https://www.scopus.com/inward/record.uri?eid=2-s2.0-85135043192&doi=10.1007%2F978-3-031-09342-5_27&partnerID=40&md5=6ce2320bd96903fbe3a25baf05111e99 | F41: P | G41: Y | H41: =countif(Survey!$E$2:$E$57,E41) -> 0 | I41: Breast cancer is one of the fatal health conditions across globe and early detection of such cancerous tumor is life saver. There are various diagnostic ways to detect the tumor, however, ultrasound is more helpful for certain scenarios such as young patient, lactating or pregnant women, radiation sickness and biopsy assistance. This work attempts to detect breast tumors from the ultrasound images using Involuted UNET (InvUNET). It is based on the hybrid combination of deep learning concepts such as UNET and involution layer. UNET has been a popular choice in medical segmentation and the lightweight involution kernels embed the location-specific and channel-agnostic representation learning. The proposed method is validated using Breast Ultrasound Images (BUSI) dataset and jaccard score of 0.7146 is obtained. © 2022, The Author(s), under exclusive license to Springer Nature Switzerland AG.
A42: Das, R.; Kaur, K.; Walia, E. | B42: Feature Generalization for Breast Cancer Detection in Histopathological Images | C42: 2022 | D42: 22 | E42: https://www.scopus.com/inward/record.uri?eid=2-s2.0-85129147479&doi=10.1007%2Fs12539-022-00515-1&partnerID=40&md5=d8374dd58ba08c73282dcd71b3e3f27c | F42: SF | H42: =countif(Survey!$E$2:$E$57,E42) -> 0 | I42: Recent period has witnessed benchmarked performance of transfer learning using deep architectures in computer-aided diagnosis (CAD) of breast cancer. In this perspective, the pre-trained neural network needs to be fine-tuned with relevant data to extract useful features from the dataset. However, in addition to the computational overhead, it suffers the curse of overfitting in case of feature extraction from smaller datasets. Handcrafted feature extraction techniques as well as feature extraction using pre-trained deep networks come into rescue in aforementioned situation and have proved to be much more efficient and lightweight compared to deep architecture-based transfer learning techniques. This research has identified the competence of classifying breast cancer images using feature engineering and representation learning over the established and contemporary notion of using transfer learning techniques. Moreover, it has revealed superior feature learning capacity with feature fusion in contrast to the conventional belief of understanding unknown feature patterns better with representation learning alone. Experiments have been conducted on two different and popular breast cancer image datasets, namely, KIMIA Path960 and BreakHis datasets. A comparison of image-level accuracy is performed on these datasets using the above-mentioned feature extraction techniques. Image level accuracy of 97.81% is achieved for KIMIA Path960 dataset using individual features extracted with handcrafted (color histogram) technique. Fusion of uniform Local Binary Pattern (uLBP) and color histogram features has resulted in 99.17% of highest accuracy for the same dataset. Experimentation with BreakHis dataset has resulted in highest classification accuracy of 88.41% with color histogram features for images with 200X magnification factor. Finally, the results are contrasted to that of state-of-the-art and superior performances are observed on many occasions with the proposed fusion-based techniques. In case of BreakHis dataset, the highest accuracies 87.60% (with least standard deviation) and 85.77% are recorded for 200X and 400X magnification factors, respectively, and the results for the aforesaid magnification factors of images have exceeded the state-of-the-art. © 2022, International Association of Scientists in the Interdisciplinary Areas.
A43: Singh, S.; Arshid, N.; Cinti, S. | B43: Electrochemical nano biosensors for the detection of extracellular vesicles exosomes: From the benchtop to everywhere? | C43: 2022 | D43: 62 | E43: https://www.scopus.com/inward/record.uri?eid=2-s2.0-85138460701&doi=10.1016%2Fj.bios.2022.114635&partnerID=40&md5=029e81da191e90ca5bd7e55c7a0c97ef | F43: SA | H43: =countif(Survey!$E$2:$E$57,E43) -> 0 | I43: Detection of extracellular vesicles (EVs) exosomes is a challenge to address the need for better diagnostic tests and to create a point-of-care (POC) platform that can detect, monitor and treat health conditions early to allow personalized therapies. A multidisciplinary approach is needed to address these health-related technical issues. Over the past decade, materials scientists and engineers have worked on the same platform to develop flexible, lightweight, miniaturized, and integrated POC devices for exosome detection. Therefore, exosome detection based on various nanomaterials is of particular interest. In this paper, we describe the current state of knowledge on 0D-3D nanostructured materials and present a POC-based technique for exosome detection. Finally, the challenges that need to be solved to expand their clinical application are discussed. © 2022 Elsevier B.V.
A44: Althobaiti, M.M.; Ashour, A.A.; Alhindi, N.A.; Althobaiti, A.; Mansour, R.F.; Gupta, D.; Khanna, A. | B44: Deep Transfer Learning-Based Breast Cancer Detection and Classification Model Using Photoacoustic Multimodal Images | C44: 2022 | D44: 23 | E44: https://www.scopus.com/inward/record.uri?eid=2-s2.0-85130057030&doi=10.1155%2F2022%2F3714422&partnerID=40&md5=b7f95ce78e0d5074d983f835ee26d1e5 | F44: RT | H44: =countif(Survey!$E$2:$E$57,E44) -> 0 | I44: The rapid development of technologies in biomedical research has enriched and broadened the range of medical equipment. Magnetic resonance imaging, ultrasonic imaging, and optical imaging have been discovered by diverse research communities to design multimodal systems, which is essential for biomedical applications. One of the important tools is photoacoustic multimodal imaging (PAMI) which combines the concepts of optics and ultrasonic systems. At the same time, earlier detection of breast cancer becomes essential to reduce mortality. The recent advancements of deep learning (DL) models enable detection and classification the breast cancer using biomedical images. This article introduces a novel social engineering optimization with deep transfer learning-based breast cancer detection and classification (SEODTL-BDC) model using PAI. The intention of the SEODTL-BDC technique is to detect and categorize the presence of breast cancer using ultrasound images. Primarily, bilateral filtering (BF) is applied as an image preprocessing technique to remove noise. Besides, a lightweight LEDNet model is employed for the segmentation of biomedical images. In addition, residual network (ResNet-18) model can be utilized as a feature extractor. Finally, SEO with recurrent neural network (RNN) model, named SEO-RNN classifier, is applied to allot proper class labels to the biomedical images. The performance validation of the SEODTL-BDC technique is carried out using benchmark dataset and the experimental outcomes pointed out the supremacy of the SEODTL-BDC approach over the existing methods. © 2022 Maha M. Althobaiti et al.
B45: 3rd International Conference on Artificial Intelligence and Speech Technology, AIST 2021 | C45: 2022 | D45: 0 | E45: https://www.scopus.com/inward/record.uri?eid=2-s2.0-85124670761&partnerID=40&md5=74871ff483593045ff21f5c5f621c2bf | F45: IR | H45: =countif(Survey!$E$2:$E$57,E45) -> 1 | I45: The proceedings contain 54 papers. The special focus in this conference is on Artificial Intelligence and Speech Technology. The topics include: Feature Extraction and Sentiment Analysis Using Machine Learning; a Neural Network Based Approach for Text-Level Sentiment Analysis Using Sentiment Lexicons; cross Linguistic Acoustic Phonetic Study of Punjabi and Indian English; prashn: University Voice Assistant; spectrogram Analysis and Text Conversion of Sound Signal for Query Generation to Give Input to Audio Input Device; a Contrastive View of Vowel Phoneme Assessment of Hindi, Indian English and American English Speakers; Text-Based Analysis of COVID-19 Comments Using Natural Language Processing; indian Languages Requirements for String Search/comparison on Web; dictionary Vectorized Hashing of Emotional Recognition of Text in Mutual Conversation; Speaker Independent Accent Based Speech Recognition for Malayalam Isolated Words: An LSTM-RNN Approach; Comparative Analysis of NLP Text Embedding Techniques with Neural Network Layered Architecture on Online Movie Reviews; current State of Speech Emotion Dataset-National and International Level; context-Aware Emoji Prediction Using Deep Learning; development of ManiTo: A Manipuri Tonal Contrast Dataset; deep Neural Networks for Spoken Language Identification in Short Utterances; a Lightweight Deep Learning Approach for Diabetic Retinopathy Classification; machine Hearing a Cognitive Service for Aiding Clinical Diagnosis; critical Insights on Cancer Detection Using Deep Learning; OHF: An Ontology Based Framework for Healthcare; enhancing the Deep Learning-Based Breast Tumor Classification Using Multiple Imaging Modalities: A Conceptual Model; a Review on Speech Synthesis Based on Machine Learning; EEG Based Stress Classification in Response to Stress Stimulus; hindi Phoneme Recognition - A Review.
B46: 2022 5th International Conference on Computational Intelligence and Networks, CINE 2022 | C46: 2022 | D46: 0 | E46: https://www.scopus.com/inward/record.uri?eid=2-s2.0-85148874918&partnerID=40&md5=1319f99a2518dcd8b271472f212eae60 | F46: IR | H46: =countif(Survey!$E$2:$E$57,E46) -> 1 | I46: The proceedings contain 29 papers. The topics discussed include: a distributed software agent-oriented traceability milieu for blockchain-enabled supply chain; distributed hash table with extensible remote procedure calls; an approach for word segmentation from a line segment in Odia text using quartiles; improving learner's comprehension using entailment-based question generation; breast cancer prediction using long short-term memory algorithm; multiple feature selection frameworks based on evolutionary computing and ensemble learning for software defect prediction; futuristic opportunities and challenges for cognitive tutoring systems; smart prediction of severity in vehicular crashes: a machine learning approach; continuous cloud user authentication by efficient facial recognition; diagnosing skin lesion using multi-modal analysis; Hindi document extractive summarization: neural method on a new data set; outlier and trend detection using approximate median and median absolute deviation; and a lightweight DoS and DDoS attack detection mechanism-based on deep learning.
B47: 14th Mexican Conference on Pattern Recognition, MCPR 2022 | C47: 2022 | D47: 0 | E47: https://www.scopus.com/inward/record.uri?eid=2-s2.0-85133002409&partnerID=40&md5=4cd265e78079bd54e50202f6c6364fb5 | F47: IR | H47: =countif(Survey!$E$2:$E$57,E47) -> 1 | I47: The proceedings contain 33 papers. The special focus in this conference is on Pattern Recognition. The topics include: Factorized U-net for Retinal Vessel Segmentation; Multi-view Learning for EEG Signal Classification of Imagined Speech; leveraging Multiple Characterizations of Social Media Users for Depression Detection Using Data Fusion; a Wide & Deep Learning Approach for Covid-19 Tweet Classification; Does This Tweet Report an Adverse Drug Reaction? An Enhanced BERT-Based Method to Identify Drugs Side Effects in Twitter; we Will Know Them by Their Style: Fake News Detection Based on Masked N-Grams; multi-document Text Summarization Based on Genetic Algorithm and the Relevance of Sentence Features; OSLeD-wA: A One-Stage Lesion Detection Method with Attention Mechanisms; Detection of Pain Caused by a Thermal Stimulus Using EEG and Machine Learning; Lane Changing Model from NGSIM Dataset; efficient Methodology Based on Convolutional Neural Networks with Augmented Penalization on Hard-to-Classify Boundary Voxels on the Task of Brain Lesion Segmentation; Delimitation of Benign and Malignant Masses in Breast Ultrasound by Clustering of Intuitionistic Fuzzy Superpixels Using DBSCAN Algorithm; machine Learning and Symbolic Learning for the Recognition of Leukemia L1, L2 and L3; A Preliminary Study of SMOTE on Imbalanced Big Datasets When Dealing with Sparse and Dense High Dimensionality; A CNN-Based Driver’s Drowsiness and Distraction Detection System; 3D Convolutional Neural Network to Enhance Small-Animal Positron Emission Tomography Images in the Sinogram Domain; preface; clustering of Twitter Networks Based on Users’ Structural Profile; deep Variational Method with Attention for High-Definition Face Generation; extreme Machine Learning Architectures Based on Correlation; on Labelling Pointclouds with the Nearest Facet of Triangulated Building Models; cable-Driven Parallel Robot Controlled by Servo-Vision System; a Lightweight Convolutional Neural Network for Breast Cancer Diagnosis with Histology Images; a Robust Fault Diagnosis Method in Presence of Noise and Missing Information for Industrial Plants; a Novel Survival Analysis-Based Approach for Predicting Behavioral Probability of Default.
A48: Shinde, R.K.; Alam, M.S.; Hossain, M.B.; Imtiaz, S.; Kim, J.; Padwal, A.A.; Kim, N. | B48: Squeeze-MNet: Precise Skin Cancer Detection Model for Low Computing IoT Devices Using Transfer Learning | C48: 2023 | D48: 34 | E48: https://www.scopus.com/inward/record.uri?eid=2-s2.0-85145999195&doi=10.3390%2Fcancers15010012&partnerID=40&md5=e71f32193da4c869f31db79c97fb065d | F48: ST | H48: =countif(Survey!$E$2:$E$57,E48) -> 0 | I48: Cancer remains a deadly disease. We developed a lightweight, accurate, general-purpose deep learning algorithm for skin cancer classification. Squeeze-MNet combines a Squeeze algorithm for digital hair removal during preprocessing and a MobileNet deep learning model with predefined weights. The Squeeze algorithm extracts important image features from the image, and the black-hat filter operation removes noise. The MobileNet model (with a dense neural network) was developed using the International Skin Imaging Collaboration (ISIC) dataset to fine-tune the model. The proposed model is lightweight; the prototype was tested on a Raspberry Pi 4 Internet of Things device with a Neo pixel 8-bit LED ring; a medical doctor validated the device. The average precision (AP) for benign and malignant diagnoses was 99.76% and 98.02%, respectively. Using our approach, the required dataset size decreased by 66%. The hair removal algorithm increased the accuracy of skin cancer detection to 99.36% with the ISIC dataset. The area under the receiver operating curve was 98.9%. © 2022 by the authors.
A49: Chengxiao, C.; Zeng, X.; Xi, R.; Ahmed, A.; Hou, M.; Tunio, M.H. | B49: PLA—A Privacy-Embedded Lightweight and Efficient Automated Breast Cancer Accurate Diagnosis Framework for the Internet of Medical Things | C49: 2023 | D49: 7 | E49: https://www.scopus.com/inward/record.uri?eid=2-s2.0-85180677552&doi=10.3390%2Felectronics12244923&partnerID=40&md5=10fad17f7a199a625cfd8ed269f9abc0 | F49: P | G49: Y | H49: =countif(Survey!$E$2:$E$57,E49) -> 0 | I49: The Internet of Medical Things (IoMT) can automate breast tumor detection and classification with the potential of artificial intelligence. However, the leakage of sensitive data can cause harm to patients. To address this issue, this study proposed an intrauterine breast cancer diagnosis method, namely “Privacy-Embedded Lightweight and Efficient Automated (PLA)”, for IoMT, which represents an approach that combines privacy-preserving techniques, efficiency, and automation to achieve our goals. Firstly, our model is designed to achieve lightweight classification prediction and global information processing of breast cancer by utilizing an advanced IoMT-friendly ViT backbone. Secondly, PLA protects patients’ privacy by federated learning, taking the classification task of breast cancer as the main task and introducing the texture analysis task of breast cancer images as the auxiliary task to train the model. For our PLA framework, the classification accuracy is 0.953, the recall rate is 0.998 for the best, the F1 value is 0.969, the precision value is 0.988, and the classification time is 61.9 ms. The experimental results show that the PLA model performs better than all of the comparison methods in terms of accuracy, with an improvement of more than 0.5%. Furthermore, our proposed model demonstrates significant advantages over the comparison methods regarding time and memory. © 2023 by the authors.
A50: Abdelmawgood, Z.; Abdalawy, S.; Mohamed, H.; R Eldamak, A.; Fahmy, O.; Elshaekh, D. | B50: Modeling of Textile Antenna Sensors for Breast Cancer Detection Using Artificial Intelligence Techniques | C50: 2023 | D50: 3 | E50: https://www.scopus.com/inward/record.uri?eid=2-s2.0-85189925974&doi=10.1109%2FMoSICom59118.2023.10458762&partnerID=40&md5=5b24cc23540d95cd95843549f780446f | F50: SA | H50: =countif(Survey!$E$2:$E$57,E50) -> 0 | I50: This paper proposes modelling and simulations for textile antenna-based sensors acting as tumor detection system for breast using artificial intelligence. The proposed textile sensors are lightweight, comfortable to wear with low fabrication cost at microwave frequencies. The sensors are modelled with a 3-layer breast phantom with skin, gland, and fatty tissue, along with a tumor with high water content. Simulations are conducted using three dimensions electromagnetic wave CST Studio simulator with 4 elements of antenna-based sensors. The utilized sensor operates on breast phantom in the band from 3.5 to 5 GHz with an average gain of 6 dBi. Tumors are simulated with diameters from 5 mm to 15 mm at the centre of breast and 45o offset of the centre. For tumor detection, different machine learning techniques are applied to classify between malignant and benign cells using Scattering parameters. These techniques provide accurate estimation for tumor detection at different tumor sizes. 98% classification accuracy is realized for centre and shifted tumor using developed machine learning techniques. © 2023 IEEE.
A51: Nneji, G.U.; Monday, H.N.; Mgbejime, G.T.; Pathapati, V.S.R.; Nahar, S.; Ukwuoma, C.C. | B51: Lightweight Separable Convolution Network for Breast Cancer Histopathological Identification | C51: 2023 | D51: 16 | E51: https://www.scopus.com/inward/record.uri?eid=2-s2.0-85146743965&doi=10.3390%2Fdiagnostics13020299&partnerID=40&md5=7c3a1c014812efda09822639fbab7e86 | F51: P | G51: Y | H51: =countif(Survey!$E$2:$E$57,E51) -> 0 | I51: Breast cancer is one of the leading causes of death among women worldwide. Histopathological images have proven to be a reliable way to find out if someone has breast cancer over time, however, it could be time consuming and require much resources when observed physically. In order to lessen the burden on the pathologists and save lives, there is need for an automated system to effectively analysis and predict the disease diagnostic. In this paper, a lightweight separable convolution network (LWSC) is proposed to automatically learn and classify breast cancer from histopathological images. The proposed architecture aims to treat the problem of low quality by extracting the visual trainable features of the histopathological image using a contrast enhancement algorithm. LWSC model implements separable convolution layers stacked in parallel with multiple filters of different sizes in order to obtain wider receptive fields. Additionally, the factorization and the utilization of bottleneck convolution layers to reduce model dimension were introduced. These methods reduce the number of trainable parameters as well as the computational cost sufficiently with greater non-linear expressive capacity than plain convolutional networks. The evaluation results depict that the proposed LWSC model performs optimally, obtaining 97.23% accuracy, 97.71% sensitivity, and 97.93% specificity on multi-class categories. Compared with other models, the proposed LWSC obtains comparable performance. © 2023 by the authors.
A52: Oladimeji, O.; Ayaz, H.; McLoughlin, I.; Unnikrishnan, S. | B52: Lightweight Deep Learning for Breast Cancer Diagnosis Based on Slice Selection Techniques | C52: 2023 | D52: 3 | E52: https://www.scopus.com/inward/record.uri?eid=2-s2.0-85189939027&doi=10.1109%2FAICS60730.2023.10470496&partnerID=40&md5=8d529085a39d70e254723aadb160592a | F52: P | G52: Y | H52: =countif(Survey!$E$2:$E$57,E52) -> 0 | I52: Breast cancer is a prevalent form of cancer with significant mortality and morbidity rates among women worldwide. Early detection is vital in increasing the chances of survival and one of the major approaches for breast cancer screening and detection is medical imaging. Advancements in technology have given rise to 3D medical imaging such as Abbreviated Breast MRI and DBT, overcoming the challenges of tissue overlapping in 2D modalities. However, deep learning model development using this 3D medical imaging comes with higher computational costs and complexity. This study proposes a lightweight deep learning technique based on three slice selection techniques using entropy, variance, and gradient magnitude values from DBT medical imaging modality. The selection techniques help select only the most informative slices making computational cost and complexity reduced. Entropy value-based slice selection performed best with an accuracy of 91%. The results obtained using the slice selection techniques for lightweight deep learning model development show that it can diagnose breast cancer with a lower number of slices and less computational complexity compared to existing methods. © 2023 IEEE.
B53: ICIAI 2023 - 7th International Conference on Innovation in Artificial Intelligence | C53: 2023 | D53: 0 | E53: https://www.scopus.com/inward/record.uri?eid=2-s2.0-85168921202&partnerID=40&md5=b0f7b1d94443d41f6f82fbda63f1c53d | F53: IR | H53: =countif(Survey!$E$2:$E$57,E53) -> 1 | I53: The proceedings contain 29 papers. The topics discussed include: obstacle avoidance system based on electromagnetic sensor and visual ranging; a lightweight model for object detection in computer motherboard images; early breast cancer detection based on high-boost filtration, data fusion and modified object detection; maritime low-light image enhancement by joint EN-decoder architecture and feature enhancement network; collaborative representation based fisher discrimination dictionary learning for image classification; image colorization with fast Fourier convolution; image defogging method based on multi-scale and frequency domain features; usability of pre-trained diffusion models in generating novel datasets and its performance evaluation; and research on flight mechanism of pterodactyl based on Runge-Kutta algorithm.
A54: Patil, A.; Diwakar, H.; Sawant, J.; Kurian, N.C.; Yadav, S.; Rane, S.; Bameta, T.; Sethi, A. | B54: Efficient quality control of whole slide pathology images with human-in-the-loop training | C54: 2023 | D54: 19 | E54: https://www.scopus.com/inward/record.uri?eid=2-s2.0-85152659545&doi=10.1016%2Fj.jpi.2023.100306&partnerID=40&md5=ab74843ff4b0e0784100da5a8e7d0040 | F54: P | G54: Y | H54: =countif(Survey!$E$2:$E$57,E54) -> 0 | I54: Histopathology whole slide images (WSIs) are being widely used to develop deep learning-based diagnostic solutions, especially for precision oncology. Most of these diagnostic softwares are vulnerable to biases and impurities in the training and test data which can lead to inaccurate diagnoses. For instance, WSIs contain multiple types of tissue regions, at least some of which might not be relevant to the diagnosis. We introduce HistoROI, a robust yet lightweight deep learning-based classifier to segregate WSI into 6 broad tissue regions—epithelium, stroma, lymphocytes, adipose, artifacts, and miscellaneous. HistoROI is trained using a novel human in-the-loop and active learning paradigm that ensures variations in training data for labeling efficient generalization. HistoROI consistently performs well across multiple organs, despite being trained on only a single dataset, demonstrating strong generalization. Further, we have examined the utility of HistoROI in improving the performance of downstream deep learning-based tasks using the CAMELYON breast cancer lymph node and TCGA lung cancer datasets. For the former dataset, the area under the receiver operating characteristic curve (AUC) for metastasis versus normal tissue of a neural network trained using weakly supervised learning increased from 0.88 to 0.92 by filtering the data using HistoROI. Similarly, the AUC increased from 0.88 to 0.93 for the classification between adenocarcinoma and squamous cell carcinoma on the lung cancer dataset. We also found that the performance of the HistoROI improves upon HistoQC for artifact detection on a test dataset of 93 annotated WSIs. The limitations of the proposed model are analyzed, and potential extensions are also discussed. © 2023
A55: Ruza, N.; Hussain, S.I.; Mohamed, S.K.C.; Arzmi, M.H. | B55: Early detection of breast cancer in mammograms using the lightweight modification of efficientNet B3 | C55: 2023 | D55: 3 | E55: https://www.scopus.com/inward/record.uri?eid=2-s2.0-85193588868&doi=10.23967%2Fj.rimni.2023.08.002&partnerID=40&md5=693b397c8f41ed1e9bfec302313e3ed7 | F55: P | G55: Y | H55: =countif(Survey!$E$2:$E$57,E55) -> 0 | I55: Breast cancer is one of the leading causes of death in women worldwide and early detection is critical to improving survival rates. In this study, we present a modified deep learning method for automatic feature detection for breast mass classification on mammograms. We propose to use EfficientNet, a Convolutional Neural Network (CNN) architecture that requires minimal parameters. The main advantage of EfficientNet is the small number of parameters, which allows efficient and accurate classification of mammogram images. Our experiments show that EfficientNet, with an overall accuracy of 86.5 percent, has the potential to be the basis for a fully automated and effective breast cancer detection system in the future. Our results demonstrate the potential of EfficientNet to improve the accuracy and efficiency of breast cancer detection compared to other approaches. © 2023, Scipedia S.L.. All rights reserved.
A56: Chaudhury, S.; Sau, K.; Khan, M.A.; Shabaz, M. | B56: Deep transfer learning for IDC breast cancer detection using fast AI technique and Sqeezenet architecture | C56: 2023 | D56: 17 | E56: https://www.scopus.com/inward/record.uri?eid=2-s2.0-85152938328&doi=10.3934%2Fmbe.2023457&partnerID=40&md5=9f25c627e323db9a1853641158e98277 | F56: P | G56: Y | H56: =countif(Survey!$E$2:$E$57,E56) -> 0 | I56: One of the most effective approaches for identifying breast cancer is histology, which is the meticulous inspection of tissues under a microscope. The kind of cancer cells, or whether they are cancerous (malignant) or non-cancerous, is typically determined by the type of tissue that is analyzed by the test performed by the technician (benign). The goal of this study was to automate IDC classification within breast cancer histology samples using a transfer learning technique. To improve our outcomes, we combined a Gradient Color Activation Mapping (Grad CAM) and image coloring mechanism with a discriminative fine-tuning methodology employing a one-cycle strategy using FastAI techniques. There have been lots of research studies related to deep transfer learning which use the same mechanism, but this report uses a transfer learning mechanism based on lightweight Squeeze Net architecture, a variant of CNN (Convolution neural network). This strategy demonstrates that fine-tuning on Squeeze Net makes it possible to achieve satisfactory results when transitioning generic features from natural images to medical images. ©2023 the Author(s),
A57: Wen, K.; Jin, X.; An, H.; He, J.; Wang, J. | B57: CentroidNet：a light-weight，fast nuclei centroid detection model for breast Ki67 scoring; CentroidNet：轻量快速的乳腺癌 Ki67 细胞核中心点检测模型 | C57: 2023 | D57: 1 | E57: https://www.scopus.com/inward/record.uri?eid=2-s2.0-85162885117&doi=10.11834%2Fjig.211207&partnerID=40&md5=043d6c230cdd8bfed947080bd9374f24 | F57: SA | G57: SA | H57: =countif(Survey!$E$2:$E$57,E57) -> 0 | I57: Objective Breast cancer-prognostic Ki67 score can be as a key indicator for the proliferation rate of malignant （invasive）cells. Negative and positive nuclei detection is an essential part of Ki67 scoring. An automated algorithm for nuclei detection can alleviate the negative impact of intra/inter-observer variation and labor-intensive nuclei counting. In recent years，deep learning methods have been developing intensively in relevant to recognition tasks on pathology images in terms of their learning potentials. Deep learning-based model can learn features derived from the raw data and relieve labor-intensive annotation of training images for pathologists. To alleviate the labor cost of annotation，our research is focused on modeling Ki67 nuclei detection as the centroid detection problem. The existing centroid detection models are commonly used to convert the centroid annotation into a probability map with the same size as the input image，the centroid detection problem is thus converted to a semantic segmentation-like problem. However，a semantic segmentation model has restricted by huge computation cost due to its huge amount of convolutional layers-related decoder. Nevertheless，due to the non-deep-learning post processing on the output heatmap，the whole detection process is complicated and inefficient，and the quality of a deep learning model is required to be developed further. Our CentroidNet model is facilitated to optimize nucleus centroid detection. Method The CentroidNet consists of a fully convolutional centroid detector initiated by ResNeXt，along with the detector’s training and inference methods. The CentroidNet can place evenly spaced anchor points on the input image. Actually，the anchor points are the places where the center of the detector’s receptive field is sited on. Each anchor point-interconnected detector can predict the classification probabilities and the offset to the anchor point，which is called a candidate point as a whole. In this way，the anchor points are the niches of the candidate points. A candidate point has the highest probability and is higher than 0. 9. It is treated as predicted point. To assign labels for anchor/candidate points，we implement the“nearest anchor”strategy. This strategy can assign any annotated point to its nearest anchor point literally. Those anchor points are not assigned via any background label-assigned annotated point，whereas those classified label is“background”and label-coordinated is the anchor’s coordinate. This strategy is mutual-benefited between annotated points and anchor/candidate points. The label jittering problem can be avoided，which is often seen in current one-to-one assignment strategies. The anchors-between spacing is concerned about more. We recommend that the anchor spacing approximate the First Percentile of the minimal distance between each annotated point in the training set to its neighboring annotated points. Such spacing can balance the ratio of foreground labels，regression-coordinated，and optimal efficiency. The CentroidNet’s detector can avoid the commonly adopted paradigm of U-Net or feature pyramid network（FPN），which involves shortcut connections and multiple upsampling layers. This lightweight detector can improve quality and efficiency. Result We evaluate the quality and efficiency of CentroidNet model on BCData，the largest publicly available dataset for centroid detection of Ki67 carcinoma nuclei in breast cancer. For quality analysis，the CentroidNet can achieve an averaged F1 score of 0. 879 1 compared to the SOTA（state of the art）score. For efficiency evaluation，the CentroidNet can achieve SOTA with an inference speed of 12. 96 ms/image and a GPU memory footprint of 138. 8 MB/image. Conclusion The CentroidNet is featured of light-weight，efficient and ease of use. It has the potentials for centroid detection of Ki67 carcinoma nuclei in breast cancer. © 2023 Journal of Image and Graphics. All rights reserved.
A58: Tu, S.; Li, W.; Ai, X.; Li, H.; Yue, Q.; Ur Rehman, S.U. | B58: A Hybrid Deep Learning Model for Breast Cancer Detection and Classification | C58: 2023 | D58: 3 | E58: https://www.scopus.com/inward/record.uri?eid=2-s2.0-85191413740&doi=10.1145%2F3638782.3638836&partnerID=40&md5=b5f5b52c04d36fdf85f00ea1f966c253 | F58: P | G58: Y | H58: =countif(Survey!$E$2:$E$57,E58) -> 0 | I58: One of the main areas of study in diagnostic radiology and medical imaging is computer-aided diagnosis (CAD). In reality, a significant number of CAD systems have been used to help doctors identify breast tumours early on mammograms. Medical image analysis algorithms are helpful in providing a better and more accurate comprehension of medical images as well as in boosting the dependability of medical images in the healthcare system because therapy and illness diagnosis are so crucial in medical imaging. Leveraging advanced machine learning techniques has become an invaluable tool for healthcare professionals, enhancing early detection and personalizing treatment plans.Therefore, in this work, we began by mentioning several cutting-edge techniques for detecting breast cancer using a deep learning methodology. The primary drawback of current research is that existing models only concentrate on identifying or detecting benign or malignant tumours, rather than specific types of tumours such adenosis, phyllodes tumour, or lobular carcinoma. We used a number of lightweight deep learning models, like ShuffleNet, to create a flexible model. [11]Additionally, in order to achieve recognition, we create the Resnet50 classical CNN model based on transfer learning.By incorporating transfer learning, the model can effectively use pre-trained networks to enhance its learning capability, potentially yielding better performance than training from scratch.number of lightweight deep learning models, like ShuffleNet, to create a flexible model. [4] A new multi-label breast cancer tissues classification model that combines the benefits of Resnet and the Attention mechanism is also taken into consideration.This innovative approach is designed to focus on specific regions of interest within the images, which can potentially lead to a higher accuracy in detecting subtler signs of various tumour types. © 2023 ACM.
B59: 7th International Conference on Emerging Applications of Information Technology, EAIT 2022 | C59: 2023 | D59: 0 | E59: https://www.scopus.com/inward/record.uri?eid=2-s2.0-85161397779&partnerID=40&md5=825b7662f9eaffc00460cb0eda33583b | F59: IR | H59: =countif(Survey!$E$2:$E$57,E59) -> 1 | I59: The proceedings contain 57 papers. The special focus in this conference is on Emerging Applications of Information Technology. The topics include: A Method of Genome Sequence Comparison Based on a New Form of Fuzzy Polynucleotide Space; identification of Humans by Using Machine Learning Models on Gait Features; efficient Heart Disease Prediction Using Modified Hybrid Classifier; an Unstructured Mammogram Analysis for Feasible Classification and Detection of Breast Cancer Using a Convolutional Approach; Emotion Recognition from EEG Data Using Hybrid Deep Learning Approach; colon Cancer Prediction with Transfer Learning and K-Means Clustering; lightweight Authentication Protocol for E-Healthcare Systems Using Fuzzy Commitment Scheme; performance Analysis of Machine Learning Algorithms for Prediction of Cerebral Attack (Stroke); breast Cancer Detection Using Transfer Learning Techniques in Convolutional Neural Networks; improving Mental Health Through Multimodal Emotion Detection from Speech and Text Data Using Long-Short Term Memory; a Machine Learning-Based Prediction Model for Fetal Health Assessment; A Smart System for Assessment of Mental Health Using Explainable AI Approach; binary Classification of Thyroid Using Comprehensive Set of Machine Learning Algorithms; Interpretability Approaches of Explainable AI in Analyzing Features for Lung Cancer Detection; impregnable Healthcare Ecosystem Using Blockchain and Artificial Intelligence Approaches; RIWT Generative Feedback Residual Network for Secure Clinical Data Communication in Healthcare Unit; blockchain-Based Smart Integrated Healthcare System; Designing a Secure Robust Medical Image Authentication Based on Watermarking Using the ED-DWT and Encryption; IoT-Based Secure Blockchain Framework for Patient Record Management Using MPRESENT Lightweight Block Cipher; hybridized Support Vector Machine and Adaboost Technique for Malaria Diagnosis; feather-Light Vessel Segregation Model.
B60: 2nd International Conference on Trends in Electronics and Health Informatics, TEHI 2022 | C60: 2023 | D60: 0 | E60: https://www.scopus.com/inward/record.uri?eid=2-s2.0-85164922761&partnerID=40&md5=d880d5fc9abc57f7b03363fc1dc6a912 | F60: IR | H60: =countif(Survey!$E$2:$E$57,E60) -> 1 | I60: The proceedings contain 35 papers. The special focus in this conference is on Trends in Electronics and Health Informatics. The topics include: Cognitive Assessment and Trading Performance Correlations; molecular Docking Study of Oxido-Vanadium Complexes with Proteins Involved in Breast Cancer; multi-Level Stress Detection using Ensemble Filter-based Feature Selection Method; a Hybrid Transfer Learning and Segmentation Approach for the Detection of Acute Lymphoblastic Leukemia; Logistic Regression Approach to a Joint Classification and Feature Selection in Lung Cancer Screening Using CPRD Data; HI Applications for ADHD Children: A Case for Enhanced Visual Representations Using Novel and Adapted Guidelines; Trimmed-TDL-Based Time-to-Digital Converter for Time-of-Flight Applications Implemented on Cyclone V FPGA; CO<inf>2</inf> Monitoring System to Warn of Possible Risk of Spread of COVID-19 in Classrooms; high-Power Analysis for Outage Probability and Average Symbol Error Probability over Non-identical κ - μ Double Shadowed Fading; Flexible Systolic Hardware Architecture for Computing a Custom Lightweight CNN in CT Images Processing for Automated COVID-19 Diagnosis; hjorth Parameters in Event-Related Potentials to Detect Minimal Hepatic Encephalopathy; The V-Band Substrate Integrated Waveguide Antenna for MM Wave Application; the Influence of an Extended Optical Mode on the Performance of Microcavity Forced Oscillator; synthesis and Characterization of Fe<inf>3</inf>O<inf>4</inf>@SiO<inf>2</inf> Core/shell Nanocomposite Films; optical and Structural Study of a Fibonacci Structure Manufactured by Porous Silicon and Porous SiO<inf>2</inf> ; amyloid-β Can Form Fractal Antenna-Like Networks Responsive to Electromagnetic Beating and Wireless Signaling; how Does Microtubular Network Assists in Determining the Location of Daughter Nucleus: Electromagnetic Resonance as Key to 3D Geometric Engineering; computational Study of Absorption and Emission of Luteolin Molecule.
B61: 2023 31st Irish Conference on Artificial Intelligence and Cognitive Science, AICS 2023 | C61: 2023 | D61: 0 | E61: https://www.scopus.com/inward/record.uri?eid=2-s2.0-85189982479&partnerID=40&md5=79f59d0abd7b45837c07bbc68f2ad606 | F61: IR | H61: =countif(Survey!$E$2:$E$57,E61) -> 1 | I61: The proceedings contain 47 papers. The topics discussed include: towards improving clinical practice guidelines through named entity recognition: model development and evaluation; lightweight deep learning for breast cancer diagnosis based on slice selection techniques; deep reinforcement learning for advanced persistent threat detection in wireless networks; identifying influential citations in scientific papers; empowering federated learning: tackling client drift and resource constraints with knowledge distillation by combining losses; speech-based Alzheimer’s disease classification system with noise-resilient features optimization; ChatPapers: an AI chatbot for interacting with academic research; machine learning-assisted multi-objective optimization of biomass combustion process; and reinforcement learning for stock option trading.
B62: 15th International Conference on Electronics, Computers and Artificial Intelligence, ECAI 2023 - Proceedings | C62: 2023 | D62: 0 | E62: https://www.scopus.com/inward/record.uri?eid=2-s2.0-85168135808&partnerID=40&md5=4a0fd9326cdc3d557756a1486b1692eb | F62: IR | H62: =countif(Survey!$E$2:$E$57,E62) -> 1 | I62: The proceedings contain 150 papers. The topics discussed include: an efficient mixed integer nonlinear program model for optimal positions of pressure reducing valves in water distribution systems; scalable web-based application for dynamic multi-tenant hotel reservation management; breast cancer detection using thermal infrared image analysis based on Dempster-Shafer decision fusion of CNN classifiers; impact of feature encoding on malware classification explainability; system for smart blood donation and stimulation with blockchain; study on the finite element modeling of the mechanical stresses of the samples of nuclear structural materials; arrhythmia classifier based on ultra-lightweight binary neural network; feature selection using genetic algorithms for improving accuracy in image classification tasks; preparing students for university and research careers in science and engineering; improving air pollution forecasting in smart cities using clustering techniques; and blockchain technology in improving transparency and efficiency in government operations.
A63: Jiang, X.; Wang, S.; Zhang, Y. | B63: Vision transformer promotes cancer diagnosis: A comprehensive review | C63: 2024 | D63: 20 | E63: https://www.scopus.com/inward/record.uri?eid=2-s2.0-85191815479&doi=10.1016%2Fj.eswa.2024.124113&partnerID=40&md5=9183e2d869057da768091324b7932d88 | F63: NA | H63: =countif(Survey!$E$2:$E$57,E63) -> 0 | I63: Background: The approaches based on vision transformers (ViTs) are advancing the field of medical artificial intelligence (AI) and cancer diagnosis. Recently, many researchers have developed artificial intelligence methods for cancer diagnosis based on ViTs. In this paper, 98 pertinent articles since 2020 were carefully chosen from digital databases, including Google scholar, Elsevier, and Springer Link, to review the research progress of artificial intelligence methods for cancer imaging based on ViT. Method: The basic structure of ViT is introduced, and corresponding modules such as patch embedding, positional embedding, transformer encoder, multi-head self-attention (MSA), layer normalization (LN), and residual connections, multilayer perceptron (MLP) are elaborated; a comprehensive review of improved ViT models in the medical field is presented. The application of ViT technology in cancer analysis based on medical images was reviewed. Results: ViT has achieved great success in cancer diagnosis based on medical images, showing its advantages in image classification, image reconstruction, image detection, image segmentation, image registration, image fusion, and other tasks. In these task studies, the most common task is cancer image classification and segmentation. There is still a lot of room for improvement in the aspects of multi-task learning, multi-modal learning, model generality, generalization ability, and explainability, and it also faces the mutual restriction of model scale and performance. Conclusion: The ViT training model for cancer diagnosis can potentially improve. The ViT model of self-supervised learning and semi-supervised learning mechanism is promising research. The lightweight attention module design, ViTs based on mobile networks, and the development of 3DViT will promote cancer diagnosis based on medical images to be more accurate and efficient. © 2024 Elsevier Ltd
A64: Abimouloud, M.L.; Bensid, K.; Elleuch, M.; Ben Ammar, M.B.; Kherallah, M. | B64: Vision transformer based convolutional neural network for breast cancer histopathological images classification | C64: 2024 | D64: 22 | E64: https://www.scopus.com/inward/record.uri?eid=2-s2.0-85197368415&doi=10.1007%2Fs11042-024-19667-x&partnerID=40&md5=07c57692e436c8a336eca0f5a784b8e8 | F64: P | G64: Y | H64: =countif(Survey!$E$2:$E$57,E64) -> 0 | I64: Breast cancer (BC) is a widespread and lethal cancer affecting women world- wide. Early diagnosis plays a pivotal role in ensuring survival, as late detection can result in a fatal outcome. Convolutional neural networks (CNNs) have made significant contributions to the task of medical imaging modalities and have dis- played promise in addressing this challenge. Recently, the success of the vision transformer (ViT) architecture has encouraged the use of the attention mecha- nism in computer-aided diagnosis (CAD) tasks. However, the ViT is known for its data-intensive nature and a substantial number of parameters and needs power- ful computer resources when training, which often leads to the same performance compared to CNNs. These challenges are particularly evident in tasks involving medical image datasets with complex images and limited data. This problem- atic situation led to the suggestion three of low-weight parameter systems based on convolution and attention techniques: vision transformer base model (ViT), compact convolution transformers (CCT), and lightweight mobile vision trans- formers (MVIT). These systems are developed by using the BreakHis dataset, which includes images captured at different magnification levels (40x, 100x, 200x, 400x), for both binary and multi classification of breast cancer subtypes. These low-weight hybrid ViT-CNN networks operate directly on input patches and convolution layers, to improve feature extraction and attention layers to train patches in all networks. This approach results in lower training time and fewer parameters while achieving accurate breast tumors classification. The proposed method is based on splitting the input image into patches and then focusing them on the area of cancerous lumps, providing a sequence of linear embedding of these patches as input. Second, we applied a convolution layer directly to the histopathology input patches, with the fewest possible modifications. Finally, we train patches in all transformer encoder layers to evaluate the performance of the classification of breast subtypes. The performance accuracies of our suggested models are 98.64% for VIT, 96.99% for CCT and 97.52% for MVIT. Moreover, the proposed models were compared with state-of-the-art models using the same dataset. Our study demonstrates how convolution and attention mechanisms can minimize computational training resources and decision time, to develop high- performing computer-aided analyses for breast cancer diagnosis. The source codes are accessible at https://github.com/abimouloud/ViT-CNN. © The Author(s), under exclusive licence to Springer Science+Business Media, LLC, part of Springer Nature 2024.
A65: Zhang, Y.; Li, P.; Lan, Y.; Jia, X.; Lv, Y. | C65: 2024 | D65: 0 | E65: https://www.scopus.com/inward/record.uri?eid=2-s2.0-85210976449&doi=10.1109%2FACCESS.2024.3508780&partnerID=40&md5=89e2a949087bf423612dd6995ba31f92 | F65: P | G65: Y | H65: =countif(Survey!$E$2:$E$57,E65) -> 0 | I65: Breast cancer has the highest incidence rate among women worldwide. Early screening and timely treatment can effectively control breast cancer progression and significantly reduce mortality. In this paper, we proposed a method of breast cancer detection based on full-dimensional dynamic convolution and multiple attention mechanism to solve the problems of missing detection and low detection accuracy caused by breast tumor occlusion by breast muscle, poor contrast between tumor and surrounding glandular tissue and indistinct features of small tumor. First, a target detection head based on an attention mechanism is proposed to improve lump detection sensitivity in complex backgrounds. Second, a lightweight backbone network, MobileNetV2-ODConv, is used to improve the ability of the network to extract features of lumps in breast X-ray images while reducing the number of parameters and floating-point operations. Finally, a loss function based on the minimum point distance is used to improve target localization accuracy and convergence speed. The experimental results show that the improved model achieves higher accuracy, sensitivity, and detection speed than previous models, and reduces false positive and false negative rates. In addition, two-core convolution is used instead of the normal 2D convolution in the C3 module. The experimental results show that: the number of parameters of the improved model is reduced by about 47%, and the recall rate and average detection accuracy of the improved model in DDSM dataset, MIAS dataset and INBreast dataset are increased by 8.2% and 6.7%, 3.7% and 2.2%, 1.3% and 2.4% respectively. © 2013 IEEE.
A66: Pandian, R.; Danasegaran, S.K.; Lalithakumari, S.; Rajalakshmi, G.; Sathish Kumar, G.S. | B66: Photonic crystal based hour glass patch antenna for the detection of breast cancer | C66: 2024 | D66: 14 | E66: https://www.scopus.com/inward/record.uri?eid=2-s2.0-85188515279&doi=10.1007%2Fs11082-024-06657-4&partnerID=40&md5=94125599b780210029ddace59492ce78 | F66: SA | H66: =countif(Survey!$E$2:$E$57,E66) -> 0 | I66: Breast cancer is the most prevalent cancer in females in a large number of countries around the world. One in every twenty females gets confirmed to have breast cancer during their lifetime, though the number varies significantly by country. There are various conventional methods to spot the breast cancer cells, such as magnetic resonance imaging, X-ray mammography, biopsies, and ultrasound. The early identification of cancer cells helps to save many human lives. This paper investigates tumor detection in a breast phantom using a Photonic crystal (PhC) based hourglass terahertz patch antenna. This paper designed four different antenna structures: conventional hourglass patch antenna (with and without breast phantom) and PhC-based hourglass patch antenna (with and without breast phantom). The proposed PhC antenna models and the breast phantom are designed using the CST studio suite and analyzed the various antenna parameters. The observed S11 parameter for the proposed structures is − 21.50, − 25.34, − 33.78 and − 50.32 dB. The proposed antenna resonated in THz frequency, which does not affect human health and is safer due to non-ionizing characteristics. The suggested PhC structure is tiny, less expensive, lightweight, environmentally benign, and can be utilized as a primary screening technique for people with breast cancer, especially in resource-limited areas. © The Author(s), under exclusive licence to Springer Science+Business Media, LLC, part of Springer Nature 2024.
A67: Gong, Z.; Chen, Y.; Ding, Y.; Zhang, H. | B67: Perspective: Microwave Medical Imaging Using Space-Time-Frequency A Priori Knowledge for Health Monitoring | C67: 2024 | D67: 5 | E67: https://www.scopus.com/inward/record.uri?eid=2-s2.0-85180281854&doi=10.1109%2FJERM.2023.3337660&partnerID=40&md5=2aa183a8fcfc96be6315b0821b83857c | F67: NA | H67: =countif(Survey!$E$2:$E$57,E67) -> 0 | I67: Microwave medical imaging (MMI) operating over the frequency range covering hundreds of megahertz to tens of gigahertz has the potential to provide proactive healthcare solutions to patients with acute (for early diagnosis) or chronic (for daily monitoring) medical conditions. This technology exploits the tissue dielectric properties for disease diagnosis by using quantitative or qualitative algorithms. The advantages of MMI include low health risk, low operational cost, lightweight implementation, and ease of use, given its perspective of miniaturization and integration into portable and handheld devices with networking capability. MMI has been proposed for cancer detection, stroke detection, heart imaging, bone imaging, tracking of in-body drug-loaded nanorobots, etc. It is, however, challenging to develop accurate and robust MMI algorithms for both sensitive and selective diagnosis, due to the inherently ill-conditioned inverse scattering problems and the low dielectric contrast between healthy and diseased tissues. As such, using the a priori knowledge (APK) about the scattering profile to improve the performance of MMI is crucial for practical implementation and clinical deployment of MMI systems. This perspective article presents a new viewpoint of categorizing and utilizing various types of APK, which is acquired from the space, time, or frequency (STF) domain. The article starts with a general categorization framework of APK, followed by formulations of MMI algorithms utilizing APK. Subsequently, the existing APK-oriented MMI algorithms are reviewed in the respective STF domain. Finally, the influence of accuracy of APK on MMI performance is discussed using numerical examples. Through the analysis of the distorted Born iterative method (DBIM) and the pulse radar method, we have discussed the accurate usage of time-domain APK for both quantitative and qualitative evaluations, and the performance improvements of the quantitative and qualitative algorithms are 92% and 80%, respectively. The results demonstrate that the proper implementation of APK can significantly improve imaging accuracy, further validating the effectiveness and generalizability of the proposed model. This perspective would offer some useful insights into the future directions of MMI algorithmic development. © 2016 IEEE.
A68: Agrawal, K.; Borthakur, A.; Singh, A.K.; Srikaran, P.; Nandi, D.; Pujari, O. | B68: Neural Decision Tree for Bio-TinyML | C68: 2024 | D68: 2 | E68: https://www.scopus.com/inward/record.uri?eid=2-s2.0-85216213302&doi=10.1109%2FBioCAS61083.2024.10798396&partnerID=40&md5=6d39fdc7c5885d43c96b17842393756f | F68: P | G68: Y | H68: =countif(Survey!$E$2:$E$57,E68) -> 0 | I68: Deep neural networks(NN) are widely popular candidates for introducing machine learning in resource-constrained devices(tinyML). However, NNs in tinyML applications come with constraints such as high memory footprint and power consumption. Another popular candidate is decision trees (DT), which are lightweight, but in DT - choosing the tree depth, the best feature, and the threshold for subsetting data is not end-to-end as in parameter tuning of NNs. Hence, we here design a Neural Decision Tree (NDT), which can be trained using backpropagation in an end-to-end fashion and is simultaneously lightweight. We evaluate NDT for potential healthcare applications in Epileptic Seizure, Cervical Cancer, Breast Cancer, Parkinson's, and Heart Disease Detection. Careful studies reveal that NDT performs at par with NNs but is computationally simpler with fewer neurons and with a hugely reduced number of multiply-accumulate operations(MACs). In addition, we propose methods for interpreting NDT behavior. Moreover, we perform systematic ablation studies on NDT to justify the design choices. © 2024 IEEE.
A69: Hasan Mahfuz, M.M.H.; Mahfouz, A.M.; Baladi, E.; Kishk, A.A. | B69: Microstrip Patch Antennas for Breast Tumor/Cancer Cell Detection-Challenges, Designs, and Future Opportunities: A Review | C69: 2024 | D69: 4 | E69: https://www.scopus.com/inward/record.uri?eid=2-s2.0-85209652985&doi=10.1109%2FACCESS.2024.3496117&partnerID=40&md5=a43c653493f65263f3c6a05d6fd82e76 | F69: P | G69: Y | H69: =countif(Survey!$E$2:$E$57,E69) -> 0 | I69: Breast cancer is a major killer of women worldwide and one of the leading causes of death overall. It involves the progressive abnormal growth of breast tissue which, if detected at an early stage, can be diagnosed as a tumor. Traditional breast cancer screening methods, such as X-ray mammography, magnetic resonance imaging, and ultrasound scanning, present several drawbacks, making them less than ideal. These drawbacks include high costs, exposure to potentially hazardous radiation, and patient inconvenience. Due to these challenges, researchers have been motivated to seek alternative methods, one of which involves the application of microwave technology. In recent years, wearable and flexible patch antennas have gained popularity due to their appealing characteristics and the potential to develop lightweight, compact, low-cost, and adaptable solutions for biomedical applications. This article provides an overview of microwave approaches for breast tumor detection using microstrip patch antennas. In particular, recent advancements in active microwave imaging and microwave-based methods are reviewed. The primary goal of this work is to offer researchers and medical professionals an understanding of the underlying principles, techniques, and challenges associated with microwave imaging for breast tumor/cancer detection. Additionally, this study aims to highlight the fact that, as of now, commercially available, cost-effective microwave-based technologies for imaging or detecting breast tumors/cancer are relatively scarce. This observation is not meant to imply that microwave technology is ineffective for breast tumor/cancer diagnosis; rather, it seeks to spark a constructive discussion about why, despite years of dedicated research, a widely accessible commercial technology has yet to be made available. © 2024 The Authors.
A70: Din, S.; Mourad, O.; Serpedin, E. | B70: LSCS-Net: A lightweight skin cancer segmentation network with densely connected multi-rate atrous convolution | C70: 2024 | D70: 17 | E70: https://www.scopus.com/inward/record.uri?eid=2-s2.0-85189008135&doi=10.1016%2Fj.compbiomed.2024.108303&partnerID=40&md5=e9e7bbd56b1aa8cc55d278cc8213bfec | F70: ST | H70: =countif(Survey!$E$2:$E$57,E70) -> 0 | I70: The rising occurrence and notable public health consequences of skin cancer, especially of the most challenging form known as melanoma, have created an urgent demand for more advanced approaches to disease management. The integration of modern computer vision methods into clinical procedures offers the potential for enhancing the detection of skin cancer. The UNet model has gained prominence as a valuable tool for this objective, continuously evolving to tackle the difficulties associated with the inherent diversity of dermatological images. These challenges stem from diverse medical origins and are further complicated by variations in lighting, patient characteristics, and hair density. In this work, we present an innovative end-to-end trainable network crafted for the segmentation of skin cancer. This network comprises an encoder–decoder architecture, a novel feature extraction block, and a densely connected multi-rate Atrous convolution block. We evaluated the performance of the proposed lightweight skin cancer segmentation network (LSCS-Net) on three widely used benchmark datasets for skin lesion segmentation: ISIC 2016, ISIC 2017, and ISIC 2018. The generalization capabilities of LSCS-Net are testified by the excellent performance on breast cancer and thyroid nodule segmentation datasets. The empirical findings confirm that LSCS-net attains state-of-the-art results, as demonstrated by a significantly elevated Jaccard index. © 2024 The Author(s)
A71: Li, F.; Ma, J.; Wen, T.; Tian, Z.; Liang, H.-N. | B71: HI-Net: A novel histopathologic image segmentation model for metastatic breast cancer via lightweight dataset construction | C71: 2024 | D71: 0 | E71: https://www.scopus.com/inward/record.uri?eid=2-s2.0-85205341198&doi=10.1016%2Fj.heliyon.2024.e38410&partnerID=40&md5=4edc8cb7c9c4442322cf8493b0c31c0b | F71: SF | H71: =countif(Survey!$E$2:$E$57,E71) -> 0 | I71: Since 2020, breast cancer has remained the most prevalent cancer worldwide and the World Health Organisation projects significant increases by 2040, with new cases expected to exceed 3 million annually (a 40% increase) and deaths to surpass 1 million (a 50% increase), highlighting the urgent need for advancements in detection and treatment. Current detection of metastasis is highly dependent on labour-intensive and error-prone pathological examination of large-scale biotissue. Given the high-resolution (100,000 × 100,000 gigapixels) but limited quantity of open-source pathological slide datasets, existing deep learning models face preprocessing challenges. This paper introduces HI-Net, a high-speed panoramic feature-extraction pyramid network for rapid and accurate detection of metastatic breast cancer, balancing panoramic segmentation and local attention. Additionally, a lightweight pathological slide dataset optimised for 512 x 512-pixel resolution, derived from downsampled and reassembled competitive datasets, accelerates training and reduces computational costs. HI-Net demonstrates superior performance on existing medical imaging competition datasets and our lightweight dataset, evidencing its effectiveness across datasets and potential for contributing to the generalisation of intelligent diagnostics. © 2024 The Author(s)
A72: Agarwal, M.; Dwivedi, A.K.; Gupta, S.K.; Najafzadeh, M.; Jindal, M. | B72: Genetic Algorithm-Based Optimization of UNet for Breast Cancer Classification: A Lightweight and Efficient Approach for IoT Devices | C72: 2024 | D72: 0 | E72: https://www.scopus.com/inward/record.uri?eid=2-s2.0-85190406689&doi=10.1007%2F978-3-031-56703-2_31&partnerID=40&md5=aee99544cb9a181b8138485e1f6af6cd | F72: P | G72: Y | H72: =countif(Survey!$E$2:$E$57,E72) -> 0 | I72: IoT devices are widely used in medical domain for detection of high blood sugar and life threatening disease such as cancer. Breast cancer is one of the most challenging type of cancer which not only affects women but in some cases men also. Deep learning is one of the widely used technology which provides efficient classification of cancerous lumps but it is not useful for IoT devices as the devices lack resources such as storage and computation. For the suitability in IoT devices, in this work, we are compressing UNet, the popular semantic segmentation technique, for the pixel-wise classification of breast cancer. For compressing the deep learning model, we use genetic algorithm which removes the unwanted layers and hidden units in the existing UNet model. We have evaluated the proposed model and compared with the existing model(s) and found that the proposed compression technique suppresses the storage requirement to 77.1%. Additionally, it also improves the inference time by 3.82× without compromising the accuracy. We conclude that the primary reason of inference time improvement is the requirement of less number of weight and bias by the proposed model. © The Author(s), under exclusive license to Springer Nature Switzerland AG 2024.
A73: Kamaruddin, N.S.; Rahim, H.A.; Al-Bawri, S.S. | B73: Enhanced Bandwidth of Hexagonal Slotted UWB Textile Antenna Sensor for Breast Cancer Detection System | C73: 2024 | D73: 0 | E73: https://www.scopus.com/inward/record.uri?eid=2-s2.0-85209649163&doi=10.1109%2FICoCET63343.2024.10730618&partnerID=40&md5=166d6663e9c2e809288ecee6e68a55f5 | F73: SA | H73: =countif(Survey!$E$2:$E$57,E73) -> 0 | I73: Breast cancer is the most common disease among women and has become one of the leading causes of death in women worldwide. Early breast cancer detection is very crucial to attain an optimum medical treatment. This paper presents a hexagonal slotted Ultra-Wideband (UWB) textile antenna for breast cancer detection systems. The proposed antenna has a dimension of 44× 38mm2^2, with a substrate made of felt material characterized by a relative permittivity, r of 1.44, a loss tangent, tanδ of 0.044, and a thickness, h of 1.5 mm. The radiating element and ground plane of the antenna are using ShieldIt Super and the thickness is set to be 0.17 mm. The proposed antenna sensor consists of a hexagonal slotted monopole antenna and a partial ground plane. The partial ground plane technique is used to enhance the performance as well as to tune in the desired frequency range. The antenna operates from 2 to 10 GHz with a maximum gain of 3.62 dBi. In addition, the proposed textile antenna has a compact structure, wide bandwidth, lightweight, and flexible, thus meeting the requirements of breast cancer detection systems. © 2024 IEEE.
A74: Majumder, S.; Mallick, K.; Pal, W.; Chakraborty, S.; Sarkar, R. | B74: EMDA-Net: Earth Mover’s Distance (EMD) influenced Attention-aided Neural Network for Medical Image Classification | C74: 2024 | D74: 0 | E74: https://www.scopus.com/inward/record.uri?eid=2-s2.0-85217407092&doi=10.1109%2FCogMI62246.2024.00040&partnerID=40&md5=fce7c1565014bc8830fb73c89da45299 | F74: P | G74: Y | H74: =countif(Survey!$E$2:$E$57,E74) -> 0 | I74: Medical image analysis methods need to be more generalized in order to meet the substantial problems associated with cancer detection and treatment, including skin, cervical, and breast cancer. In this work, we propose a novel lightweight convolutional neural network (CNN) architecture, named EMDA-Net (Earth Mover’s Distance (EMD) influenced Attention-aided Neural Network), specifically designed to meet the requirements of cancer subtype classification. It is built on the MobileNetV2 backbone and is equipped with hybrid statistical mechanism-aided attention mechanisms. Our model ensures high-performance while maintaining a lightweight design by leveraging the capabilities of the MobileNetV2 architecture and the attention mechanism. To improve similarity detection across data channels, we present a novel EMD influenced attention technique. We have examined datasets related to skin, cervical, and breast cancer for experimentation. Our model especially outperforms the state-of-the-art techniques, demonstrating its effectiveness in maximizing diagnosis precision for various cancer types across the datasets. The code of the proposed model will be made public at: https://t.ly/q5DlN. © 2024 IEEE.
A75: Kaladevi, P.; Vivekananthan, P.; Sanjith, B.; Praveen, S.V. | B75: Efficient Breast Cancer Detection using Lightweight Multimodal Approach | C75: 2024 | D75: 1 | E75: https://www.scopus.com/inward/record.uri?eid=2-s2.0-85195398942&doi=10.1109%2FICNWC60771.2024.10537581&partnerID=40&md5=0708e44e542b3302a8a667101a738a34 | F75: P | G75: Y | H75: =countif(Survey!$E$2:$E$57,E75) -> 0 | I75: In the realm of breast cancer detection, the pursuit of efficiency and accuracy remains paramount. This paper explores the integration of lightweight multimodal approaches to enhance the efficacy of breast cancer detection systems. By leveraging various modalities such as imaging, clinical data, and emerging technologies, this approach seeks to optimize detection processes while minimizing computational burdens. Through a comprehensive review of existing methodologies and the development of novel algorithms, this study aims to contribute to the advancement of early detection techniques. The proposed framework demonstrates promising results in terms of both sensitivity and specificity, offering a pragmatic solution to the challenges faced in breast cancer diagnosis. © 2024 IEEE.
A76: Karthikeyan, V.; Selva Nidhyananthan, S.S.; Renganathan, G.H.; Sri Vishnu, S.I. | B76: Detection of Breast Cancer using the Microstrip Patch Antenna on a PBG | C76: 2024 | D76: 2 | E76: https://www.scopus.com/inward/record.uri?eid=2-s2.0-85199145295&doi=10.1109%2FICITIIT61487.2024.10580378&partnerID=40&md5=6b6a6257d6458f53ea05bcf2752704f8 | F76: SA | H76: =countif(Survey!$E$2:$E$57,E76) -> 0 | I76: The microstrip patch antenna (MSPA) consists of a dielectric substrate positioned between a metallic steering cover and an earth plane. Microstrip patch antennas are increasingly popular due to their ease of analysis and fabrication, cost-effectiveness, lightweight design, ease of feeding, and appealing radiation characteristics. This paper focuses on designing a compact antenna suitable for an extensive domain of radio frequency solicitations, including military purposes. Typically, the MSPA operates through a microstrip edge feed or a coaxial cable. The rectangular and circular patch MSPAs represents the canonical forms of this structure. This paper introduces an innovative photonic band gap substrate-centered MSPA intended for tumor identification. The antenna dimensions are 600 × 600 × 157 μ m3, with a reverberation frequency of 0.203THz. It exhibits a reflection factor of -23.7554 ~dB and a gain of 7.2 ~dB. The design demonstrates excellent matching with the feedline, as indicated by a VSWR value of 1.1290. The achieved total radiation efficiency is 98.339 %. We conduct a comprehensive exploration of variations in the antenna's radiation properties resulting from changes in its geometry. The antenna's radiation characteristics are utilized for cancer diagnosis. © 2024 IEEE.
A77: Cherakhloo, M.; Ranjbar, M.; Mohebbi, M.; Vosoughi-Vahdat, B.V. | B77: DCT-HistoTransformer: Efficient Lightweight Vision Transformer with DCT Integration for histopathological image analysis | C77: 2024 | D77: 0 | E77: https://www.scopus.com/inward/record.uri?eid=2-s2.0-105000626612&doi=10.1109%2FICBME64381.2024.10895619&partnerID=40&md5=ba3ab5ef28d277b2e76410d8ec4f92aa | F77: P | G77: Y | H77: =countif(Survey!$E$2:$E$57,E77) -> 0 | I77: In recent years, the integration of advanced imaging techniques and deep learning methods has significantly advanced computer-aided diagnosis (CAD) systems for breast cancer detection and classification. Transformers, which have shown great promise in computer vision, are now being applied to medical image analysis. However, their application to histopathological images presents challenges due to the need for extensive manual annotations of whole-slide images (WSIs), as these models require large amounts of data to work effectively, which is costly and time-consuming. Furthermore, the quadratic computational cost of Vision Transformers (ViTs) is particularly prohibitive for large, high-resolution histopathological images, especially on edge devices with limited computational resources. In this study, we introduce a novel lightweight breast cancer classification approach using transformers that operates effectively without large datasets. By incorporating parallel processing pathways for Discrete Cosine Transform (DCT) Attention and MobileConv, we convert image data from the spatial domain to the frequency domain to utilize the benefits such as filtering out high frequencies in the image, which reduces computational cost. This demonstrates the potential of our approach to improve breast cancer classification in histopathological images, offering a more efficient solution with reduced reliance on extensive annotated datasets. Our proposed model achieves an accuracy of 9 6 0 0% ± 0 4 8% for binary classification and 8 7 8 5% ± 0.93% for multiclass classification, which is comparable to state-of-the-art models while significantly reducing computational costs. This demonstrates the potential of our approach to improve breast cancer classification in histopathological images, offering a more efficient solution with reduced reliance on extensive annotated datasets. © 2024 IEEE.
A78: Kanagamalliga, S.; Varma, D.B. | B78: Cutting-Edge Neural Networks Elevating Breast Cancer Diagnosis Accuracy through Image Analysis | C78: 2024 | D78: 0 | E78: https://www.scopus.com/inward/record.uri?eid=2-s2.0-105001473402&doi=10.1109%2FICSCSA64454.2024.00070&partnerID=40&md5=9be84a9c4fc8c0a306d37383c9b96b47 | F78: P | G78: Y | H78: =countif(Survey!$E$2:$E$57,E78) -> 0 | I78: The diagnosis of breast cancer is being enhanced by cutting-edge neural networks, with lightweight Convolutional Neural Networks (CNNs) optimized for mobile devices playing a pivotal role. Early-stage prediction is enabled through the automatic analysis of breast imaging data, such as mammograms and ultrasounds, directly on portable devices. Models like MobileNet, designed for efficient image analysis with minimal computational power, are ideally suited for smartphones and tablets. By incorporating cloud-based transfer learning, pretrained networks can be used to improve diagnostic accuracy, even in areas with limited access to advanced medical facilities. Real-Time image analysis is facilitated, allowing for faster and more precise breast cancer screening at the point of care. Through mobile applications, patients are able to conduct preliminary self-screening, reducing dependence on centralized medical systems and promoting early recognition, which is critical for successful treatment. This method has the potential to significantly increase access to breast cancer screening, especially in underserved regions, improving early diagnosis and patient outcomes. By combining CNN technology with mobile devices, a more accessible, scalable, and efficient approach to breast cancer diagnosis is provided, offering advanced medical tools directly to patients. © 2024 IEEE.
A79: Ahmed, S.T.; Barua, S.; Fahim-Ul-Islam, M.; Chakrabarty, A. | B79: CoAtNet-Lite: Advancing Mammogram Mass Detection Through Lightweight CNN - Transformer Fusion with Attention Mapping | C79: 2024 | D79: 4 | E79: https://www.scopus.com/inward/record.uri?eid=2-s2.0-85195238134&doi=10.1109%2FICEEICT62016.2024.10534420&partnerID=40&md5=50c61d5be0a8e8214385c5e27f92d4de | F79: P | G79: Y | H79: =countif(Survey!$E$2:$E$57,E79) -> 0 | I79: Mammograms are a main diagnostic technique for breast cancer screening, but their interpretation can be difficult and prone to human error. In the field of medical imaging, with a specific focus on mammogram analysis, this research paper introduces an innovative approach to mammogram mass detection. The study leverages an optimized CoAtNet (a hybrid model that combines depthwise convolution and self-attention via relative attention while stacking convolution and attention layers selectively) applied to a publicly available mammography dataset. The proposed model exhibits encouraging performance metrics, boasting precision and recall rates of 0.77 and 0.78, respectively, along with an F1-score of 0.77. This notable improvement distinguishes it from other existing deep learning (DL) and machine learning (ML) models that we have tested before-hand. Additionally, we attempt to enhance the interpretability and transparency of the model's decision-making process, the research integrates explainable AI techniques such as LIME (Local Interpretable Model-agnostic Explanations) and Grad-CAM (Gradient-weighted Class Activation Mapping). These tools play a pivotal role in providing insightful explanations for the model's predictions, thereby increasing the trustworthiness and reliability of AI in medical diagnostics, especially in the context of breast cancer detection. Moreover, the research underscores the significance of combining deep learning architectures with explainable AI methodologies, highlighting their potential to advance the accuracy and transparency of medical imaging technologies. © 2024 IEEE.
A80: Saha, M.; Chakraborty, M.; Maiti, S.; Das, D. | B80: Breast-NET: a lightweight DCNN model for breast cancer detection and grading using histological samples | C80: 2024 | D80: 7 | E80: https://www.scopus.com/inward/record.uri?eid=2-s2.0-85200950698&doi=10.1007%2Fs00521-024-10298-9&partnerID=40&md5=3f912bba6607085a2482b4147b7e4d35 | F80: NA | H80: =countif(Survey!$E$2:$E$57,E80) -> 0 | I80: Breast cancer is a prevalent and highly lethal cancer affecting women globally. While non-invasive techniques like ultrasound and mammogram are used for diagnosis, histological examination after biopsy is considered the gold standard. However, manual examination of tissues for abnormality is labor-intensive, expensive, and requires prior domain knowledge. Early detection, awareness, and access to specialized medical infrastructure in resource-constrained and remote areas are significant challenges but crucial for saving lives. In recent years, deep learning-based approaches have shown promising results in breast cancer detection, facilitated by advancements in GPU memory, computation power, and the availability of digital data. Motivated by these observations, we propose the Breast-NET deep convolutional neural network model for breast cancer detection and grading using histological images. Our model’s performance is evaluated on the BreakHis dataset, and we demonstrate its generalization ability on the Invasive Ductal Carcinoma (IDC) grading and IDC datasets. Extensive experimental and statistical performance analysis, along with an ablation study, validates the efficiency of our proposed model. Furthermore, we demonstrate the effectiveness of transfer learning with seven pre-trained convolutional neural networks for breast cancer detection and grading. Experimental results show that our framework outperforms state-of-the-art approaches in terms of accuracy, space, and computational complexity for the BreakHis, IDC grading, and IDC datasets. © The Author(s), under exclusive licence to Springer-Verlag London Ltd., part of Springer Nature 2024.
A81: Vickram, A.S.; Bhavani Sowndharya, B.B. | B81: Breast Histology Slides Classification using Fused Lightweight Deep Features | C81: 2024 | D81: 2 | E81: https://www.scopus.com/inward/record.uri?eid=2-s2.0-85209943697&doi=10.1109%2FICOSEC61587.2024.10722394&partnerID=40&md5=26443f2258316dd51126958af9781df0 | F81: P | G81: Y | H81: =countif(Survey!$E$2:$E$57,E81) -> 0 | I81: One of the most serious illnesses that affect women is breast cancer (BC), hence early detection and treatment are crucial. The course of treatment for BC is determined by its stage; hence, histology slide-supported BC confirmation is frequently used in medical facilities. The purpose of this study is to provide a method for classifying selected histology slides into the Benign/Malignant class using a binary classifier used with Lightweight Deep Learning Method (LDLM). The suggested approach has several stages: gathering and resizing images; extracting features using a selected LDLM; reducing features with 50% dropout and fusing features to create a new feature vector; and binary classification with 3 -fold cross validation and performance confirmation. Individual deep features (ID) and fused deep features (FD) are used in the suggested experimental work, which was conducted using the pre-trained LDLM for the investigation. The created scheme's effectiveness is confirmed by binary classification with the SoftMax classifier, and the obtained outcomes are contrasted and validated. The study's experimental results validate that the suggested methodology yields >89% detection accuracy with the ID and >98% accuracy with the FD. © 2024 IEEE.
A82: Tanim, S.A.; Alam, G.M.I.; Shrestha, T.E.; Islam, M.; Jahan, F.; Nur, K. | B82: Breast Cancer Diagnosis with XAI-Integrated Deep Learning Approach | C82: 2024 | D82: 1 | E82: https://www.scopus.com/inward/record.uri?eid=2-s2.0-85217440966&doi=10.1109%2F3ICT64318.2024.10824574&partnerID=40&md5=8de2b5ca7cdcccf5e04ea0738c381256 | F82: P | G82: Y | H82: =countif(Survey!$E$2:$E$57,E82) -> 0 | I82: Breast cancer is one of the world’s significant health challenges. There is a need to have better techniques in the early diagnosis of this disease to increase patients’ survival rates. This paper introduces a robust approach for breast cancer detection by integrating deep-learning and classical machine-learning techniques into a custom lightweight neural network model. This approach is based on integrating conventional machine-learning and deep-learning paradigms using a range of data pre-processing steps, including data cleaning, label converting, scaling, and feature selecting to improve the given dataset’s readiness for training. The proposed model demonstrated impressive accuracy in breast cancer detection compared to individual classifiers by achieving an overall accuracy of 97.54%. Additionally, integrating eXplainable Artificial Intelligence (XAI) techniques gives the application interpretability and transparency for clinicians to make sense of the feature’s importance and individual prognosis. It is a more accurate and easy-to-understand tool for clinicians, making it a better use of faulty or confusing reference values. This study presents the need to learn more about making deep learning and eXplainable Artificial Intelligence (XAI) complementary approaches to breast cancer diagnosis and treatment research. ©2024 IEEE.
A83: Aslam, S.M. | B83: Benign/Malignant Breast Cancer Detection in Histopathology Image using Fused Deep-Learning Features | C83: 2024 | D83: 0 | E83: https://www.scopus.com/inward/record.uri?eid=2-s2.0-105015892537&doi=10.1109%2FICETAS62372.2024.11119958&partnerID=40&md5=2fb5de5458b9789098a36410aa807184 | F83: P | G83: Y | H83: =countif(Survey!$E$2:$E$57,E83) -> 0 | I83: Abnormal cell growth in organs is recognized as cancer, one of the most severe and life-threatening diseases. Timely detection of cancer is essential to treat the illness using recommended treatment procedures. This research work considered the Breast Cancer (BC) for the investigation. It is one of the common cancers in women and clinical level diagnosis is performed using the medical-image guided methods. Histopathology-image based examination of the BC is essential for detecting its harshness. This research aims to develop Lightweight Deep-learning (LD) approach to classify the images into benign/malignant class. The stages of this scheme includes; image collection and resizing, feature extraction using the LD approach, feature reduction using 50% dropout and serial features generation, and classification and 3-fold cross validation. This investigation considered the BreakHis benchmark database with 40X and 100X magnification for the study. In this work, the LD methods, like MobileNet and NASNet are considered to develop the proposed examination scheme. BC detection is executed using the individual-features (IF), and fused-features (FF) using SoftMax classifier. The experimental outcome of this study confirms that the FF based classification provides 100% detection accuracy on both 40X and 100X magnified images. © 2024 IEEE.
A84: Ekta; Bhatia, V. | B84: Auto-BCS: A Hybrid System for Real-Time Breast Cancer Screening from Pathological Images | C84: 2024 | D84: 3 | E84: https://www.scopus.com/inward/record.uri?eid=2-s2.0-105007789133&doi=10.1007%2Fs10278-024-01056-3&partnerID=40&md5=e410330f12c93ac71a07908580e96e1e | F84: P | G84: Y | H84: =countif(Survey!$E$2:$E$57,E84) -> 0 | I84: Breast cancer is recognized as a prominent cause of cancer-related mortality among women globally, emphasizing the critical need for early diagnosis resulting improvement in survival rates. Current breast cancer diagnostic procedures depend on manual assessments of pathological images by medical professionals. However, in remote or underserved regions, the scarcity of expert healthcare resources often compromised the diagnostic accuracy. Machine learning holds great promise for early detection, yet existing breast cancer screening algorithms are frequently characterized by significant computational demands, rendering them unsuitable for deployment on low-processing-power mobile devices. In this paper, a real-time automated system “Auto-BCS” is introduced that significantly enhances the efficiency of early breast cancer screening. The system is structured into three distinct phases. In the initial phase, images undergo a pre-processing stage aimed at noise reduction. Subsequently, feature extraction is carried out using a lightweight and optimized deep learning model followed by extreme gradient boosting classifier, strategically employed to optimize the overall performance and prevent overfitting in the deep learning model. The system’s performance is gauged through essential metrics, including accuracy, precision, recall, F1 score, and inference time. Comparative evaluations against state-of-the-art algorithms affirm that Auto-BCS outperforms existing models, excelling in both efficiency and processing speed. Computational efficiency is prioritized by Auto-BCS, making it particularly adaptable to low-processing-power mobile devices. Comparative assessments confirm the superior performance of Auto-BCS, signifying its potential to advance breast cancer screening technology. © The Author(s) under exclusive licence to Society for Imaging Informatics in Medicine 2024.
A85: Tuo, S.; Jiang, J. | B85: A Novel Detection Method for High-Order SNP Epistatic Interactions Based on Explicit-Encoding-Based Multitasking Harmony Search | C85: 2024 | D85: 9 | E85: https://www.scopus.com/inward/record.uri?eid=2-s2.0-85197428747&doi=10.1007%2Fs12539-024-00621-2&partnerID=40&md5=7c640ad93f559c11f522172e6ca7bd7d | F85: SA | H85: =countif(Survey!$E$2:$E$57,E85) -> 0 | I85: To elucidate the genetic basis of complex diseases, it is crucial to discover the single-nucleotide polymorphisms (SNPs) contributing to disease susceptibility. This is particularly challenging for high-order SNP epistatic interactions (HEIs), which exhibit small individual effects but potentially large joint effects. These interactions are difficult to detect due to the vast search space, encompassing billions of possible combinations, and the computational complexity of evaluating them. This study proposes a novel explicit-encoding-based multitasking harmony search algorithm (MTHS-EE-DHEI) specifically designed to address this challenge. The algorithm operates in three stages. First, a harmony search algorithm is employed, utilizing four lightweight evaluation functions, such as Bayesian network and entropy, to efficiently explore potential SNP combinations related to disease status. Second, a G-test statistical method is applied to filter out insignificant SNP combinations. Finally, two machine learning-based methods, multifactor dimensionality reduction (MDR) as well as random forest (RF), are employed to validate the classification performance of the remaining significant SNP combinations. This research aims to demonstrate the effectiveness of MTHS-EE-DHEI in identifying HEIs compared to existing methods, potentially providing valuable insights into the genetic architecture of complex diseases. The performance of MTHS-EE-DHEI was evaluated on twenty simulated disease datasets and three real-world datasets encompassing age-related macular degeneration (AMD), rheumatoid arthritis (RA), and breast cancer (BC). The results demonstrably indicate that MTHS-EE-DHEI outperforms four state-of-the-art algorithms in terms of both detection power and computational efficiency. The source code is available at https://github.com/shouhengtuo/MTHS-EE-DHEI.git. Graphical abstract: (Figure presented.) © International Association of Scientists in the Interdisciplinary Areas 2024.
A86: Vinod, A.; Guddati, P.; Panda, A.; Tripathy, R. | B86: A Lightweight Deep Convolutional Neural Network Implemented on FPGA and Android Devices for Detection of Breast Cancer Using Ultrasound Images | C86: 2024 | D86: 6 | E86: https://www.scopus.com/inward/record.uri?eid=2-s2.0-85210989418&doi=10.1109%2FACCESS.2024.3506334&partnerID=40&md5=f07481c6be34536b577aac8c7ec8bb39 | F86: P | G86: Y | H86: =countif(Survey!$E$2:$E$57,E86) -> 0 | I86: Breast cancer (BC) continues to be the primary cause of high mortality rates among women globally. Early and automated detection of this disease plays a significant role in clinical standards for better diagnosis and improved survival rates. Ultrasonography is a widely used non-invasive imaging test to diagnose BC. The traditional ultrasound-based automated diagnostic systems for detecting BC rely on cloud-based processing, which has high latency, requires constant internet connectivity, and raises the privacy of patient's ultrasound image data. This paper proposes a lightweight deep convolutional neural network (LWDCNN) implemented on edge devices (field programmable gate array (FPGA) and android devices) for real-time detection of BC using breast ultrasound (BUS) images. FPGA is used due to its parallel processing capability, low latency, and low power for the real-time processing of BUS images. Similarly, the Android device provides portability and a user-friendly system to process BUS images for automated detection of BC. The proposed LWDCNN is trained on the Google Cloud CPU-based framework to obtain the optimized model with weight and bias parameters. The compression methods (pruning and fixed-point precision-based representation of weight values) are applied to the LWDCNN model, and the inference of this model is performed on Android and PYNQ-Z2 FPGA-based edge devices to detect malignant tumor classes using BUS images. The proposed approach is evaluated using BUS images from Kaggle and breast ultrasound imaging databases. The experimental results reveal that the LWDCNN achieved average accuracy values of 94.15% on Google Cloud CPU and 93.16% on FPGA-based edge devices for detecting malignant tumors in the inference phase using hold-out validation. Similarly, the post-training quantization of LWDCNN with an integer 8-bit (INT8) case implemented on an Android device has yielded an accuracy value of 93.76% for detecting malignant tumors using BUS images. The presented deep-learning approach has demonstrated higher classification accuracy than different transfer-learning techniques and existing methods using the BUS images from the same database. © 2013 IEEE.
A87: Sahu, A.; Das, P.K.; Meher, S. | B87: A Deep Hybrid System for Effective Diagnosis of Breast Cancer | C87: 2024 | D87: 2 | E87: https://www.scopus.com/inward/record.uri?eid=2-s2.0-85200196856&doi=10.1201%2F9781003450153-14&partnerID=40&md5=46f8f51dfd5e9bea468ddadbb15ec6c5 | F87: NA | G87: UA | H87: =countif(Survey!$E$2:$E$57,E87) -> 0 | I87: Breast cancer is still a major global health concern, which emphasizes the need for reliable and effective screening techniques. This work provides a deep learning–based breast cancer detection system that leverages the potent combination of ShuffleNet for feature extraction and Random Forest for classification. In the initial stage of the pipeline, ShuffleNet, a lightweight deep convolution neural network (CNN) architecture, is used to extract features. ShuffleNet is perfect for large-scale medical image analysis because of its effective design, which provides faster processing while maintaining discriminative information. The collected features are then fed into the widely used random forest classifier. The collected features are then sent into a random forest classifier, a well-liked ensemble learning technique that excels at handling high-dimensional data and robustness. The proposed method makes use of ultrasound (BUSI) and mammography (mini-DDSM) datasets for training and evaluation in order to improve the precision and dependability of breast cancer diagnosis. The efficiency of the proposed deep learning–based breast cancer detection system is shown by experimental findings. It displays the best performance among the comparing schemes with a malignancy identification accuracy of 97.50% and 92.31% in mini-DDSM and BUSI datasets. © 2024 CRC Press.
A88: Varun, C.; Poreddy, A.K.; Krishna, T.; Kokil, P. | B88: A Computer Aided Detection System for Breast Cancer using Lightweight CNN Models for Smart Healthcare | C88: 2024 | D88: 1 | E88: https://www.scopus.com/inward/record.uri?eid=2-s2.0-85197567970&doi=10.1109%2FICBSII61384.2024.10564079&partnerID=40&md5=395cae1567e04dccd21457ef3d793001 | F88: P | G88: Y | H88: =countif(Survey!$E$2:$E$57,E88) -> 0 | I88: Breast cancer (BC) is a potentially life-threatening disease that occurs because of uncontrolled growth of abnormal corpuscles in the breast tissue. Pathologists analyze the tissue structures using histopathological whole slide images to identify cancerous anomalies. However, pathologists face severe challenges such as fatigue, subjectivity, and inter-observer variability in the early detection of BC. Understanding the intricacies of BC from molecular tissue structures is complex, and inexpertise leads to adverse outcomes. This paper proposes a computed aided detection (CAD) system that can assist histopathologists in the early detection of BC, potentially reducing the abnormalities and diagnostic time. Leveraging the power of convolutional neural networks (CNNs), a stacked ensemble-based model is developed to identify benign and malignant cancerous tissues using histopathological images. The ensemble models comprise three deep CNNs, namely MobileNetV2, ShuffleNet, and SqueezeNet, trained on the BreakHis dataset. Finally, individual CNNs predictions are fed to the average voting-based classifier to identify benign and malignant tissues. The stacked ensemble-based deep CNN model outperformed the individual CNN models in BC prediction, achieving superior accuracy and robustness. © 2024 IEEE.
B89: 7th International Conference on Innovative Computing and Communication, ICICC 2024 | C89: 2024 | D89: 0 | E89: https://www.scopus.com/inward/record.uri?eid=2-s2.0-85208977565&partnerID=40&md5=2ae3f4300e63387c2ef8a2a99545a23a | F89: IR | H89: =countif(Survey!$E$2:$E$57,E89) -> 0 | I89: The proceedings contain 144 papers. The special focus in this conference is on Innovative Computing and Communication. The topics include: Breast Cancer Prediction and Detection: Comparison of the Latest Machine Learning Techniques; GIS-Based Identification and Representation of Particulate Matters Using Ontology and SPARQL; Advancements in Arrhythmia Classification: A Comprehensive Survey of AI Techniques; Survey on VANET Authentication Scheme Based on Cryptographic Protocols; exploring Machine Learning Models for Age Recognition; novel Authentication Scheme to Increase Security of Vehicular Ad Hoc Networks; a Study on the Working of Swarm-Based Metaheuristic Algorithms Using Theoretical Framework; Financial Fortunes: A Stock Price Prediction Using LSTM; utilization of Data Mining in Spatial Analysis of Displacement Crisis in Iraq; integrating Multimodal Data for Parkinson’s Disease Prediction: An Ensemble Approach; Mental Health Assessment Using EEG Sensor and Machine Learning; enhancing Patterns Accessibility for Visually Impaired Programmers; lung and Colon Cancer Detection: Advancing Automated Diagnosis Through Deep Learning; detection of Micro and Macro Nutrient Deficiency in Okra (Abelmoschus Esculentus L) Plant Leaves Using Machine Learning Approach; empowering Aspiring Artists: A Machine Learning-Powered Carnatic Music Tutor; image Denoising Using Autoencoder: Utilizing Deep Learning and Autoencoder Techniques to Enhance Natural Images by Eliminating Noisy Pixels and Grains; an IoT-Based Animal Health Monitoring System; experimental Analysis of Four Gamma Correction Variants on Brain Tumor Images; WSD-Based Bangla Cyberbullying Detection Using Transform Learning; Proposed Hybrid Approach Using Swarm Intelligence in VANETs; investigation on Performance Evaluation of Loosely Coupled Microservice for Scalable Computation in Agriculture; a Study on Lightweight Object Detection in Thermal Images and Its Recent Advances.
B90: 7th International Conference on Innovative Computing and Communication, ICICC 2024 | C90: 2024 | D90: 0 | E90: https://www.scopus.com/inward/record.uri?eid=2-s2.0-85206393432&partnerID=40&md5=d1ae3838e15f103670f22c0c42a1d549 | F90: IR | H90: =countif(Survey!$E$2:$E$57,E90) -> 0 | I90: The proceedings contain 144 papers. The special focus in this conference is on Innovative Computing and Communication. The topics include: Breast Cancer Prediction and Detection: Comparison of the Latest Machine Learning Techniques; GIS-Based Identification and Representation of Particulate Matters Using Ontology and SPARQL; Advancements in Arrhythmia Classification: A Comprehensive Survey of AI Techniques; Survey on VANET Authentication Scheme Based on Cryptographic Protocols; exploring Machine Learning Models for Age Recognition; novel Authentication Scheme to Increase Security of Vehicular Ad Hoc Networks; a Study on the Working of Swarm-Based Metaheuristic Algorithms Using Theoretical Framework; Financial Fortunes: A Stock Price Prediction Using LSTM; utilization of Data Mining in Spatial Analysis of Displacement Crisis in Iraq; integrating Multimodal Data for Parkinson’s Disease Prediction: An Ensemble Approach; Mental Health Assessment Using EEG Sensor and Machine Learning; enhancing Patterns Accessibility for Visually Impaired Programmers; lung and Colon Cancer Detection: Advancing Automated Diagnosis Through Deep Learning; detection of Micro and Macro Nutrient Deficiency in Okra (Abelmoschus Esculentus L) Plant Leaves Using Machine Learning Approach; empowering Aspiring Artists: A Machine Learning-Powered Carnatic Music Tutor; image Denoising Using Autoencoder: Utilizing Deep Learning and Autoencoder Techniques to Enhance Natural Images by Eliminating Noisy Pixels and Grains; an IoT-Based Animal Health Monitoring System; experimental Analysis of Four Gamma Correction Variants on Brain Tumor Images; WSD-Based Bangla Cyberbullying Detection Using Transform Learning; Proposed Hybrid Approach Using Swarm Intelligence in VANETs; investigation on Performance Evaluation of Loosely Coupled Microservice for Scalable Computation in Agriculture; a Study on Lightweight Object Detection in Thermal Images and Its Recent Advances.
B91: 7th International Conference on Innovative Computing and Communication, ICICC 2024 | C91: 2024 | D91: 0 | E91: https://www.scopus.com/inward/record.uri?eid=2-s2.0-85206081792&partnerID=40&md5=63abc2e3f5b27bd81515551637c17ea4 | F91: IR | H91: =countif(Survey!$E$2:$E$57,E91) -> 0 | I91: The proceedings contain 144 papers. The special focus in this conference is on Innovative Computing and Communication. The topics include: Breast Cancer Prediction and Detection: Comparison of the Latest Machine Learning Techniques; GIS-Based Identification and Representation of Particulate Matters Using Ontology and SPARQL; Advancements in Arrhythmia Classification: A Comprehensive Survey of AI Techniques; Survey on VANET Authentication Scheme Based on Cryptographic Protocols; exploring Machine Learning Models for Age Recognition; novel Authentication Scheme to Increase Security of Vehicular Ad Hoc Networks; a Study on the Working of Swarm-Based Metaheuristic Algorithms Using Theoretical Framework; Financial Fortunes: A Stock Price Prediction Using LSTM; utilization of Data Mining in Spatial Analysis of Displacement Crisis in Iraq; integrating Multimodal Data for Parkinson’s Disease Prediction: An Ensemble Approach; Mental Health Assessment Using EEG Sensor and Machine Learning; enhancing Patterns Accessibility for Visually Impaired Programmers; lung and Colon Cancer Detection: Advancing Automated Diagnosis Through Deep Learning; detection of Micro and Macro Nutrient Deficiency in Okra (Abelmoschus Esculentus L) Plant Leaves Using Machine Learning Approach; empowering Aspiring Artists: A Machine Learning-Powered Carnatic Music Tutor; image Denoising Using Autoencoder: Utilizing Deep Learning and Autoencoder Techniques to Enhance Natural Images by Eliminating Noisy Pixels and Grains; an IoT-Based Animal Health Monitoring System; experimental Analysis of Four Gamma Correction Variants on Brain Tumor Images; WSD-Based Bangla Cyberbullying Detection Using Transform Learning; Proposed Hybrid Approach Using Swarm Intelligence in VANETs; investigation on Performance Evaluation of Loosely Coupled Microservice for Scalable Computation in Agriculture; a Study on Lightweight Object Detection in Thermal Images and Its Recent Advances.
B92: 7th International Conference on Innovative Computing and Communication, ICICC 2024 | C92: 2024 | D92: 0 | E92: https://www.scopus.com/inward/record.uri?eid=2-s2.0-85202775536&partnerID=40&md5=8da973598f682212c8284d8514d2c3c2 | F92: IR | H92: =countif(Survey!$E$2:$E$57,E92) -> 0 | I92: The proceedings contain 144 papers. The special focus in this conference is on Innovative Computing and Communication. The topics include: Breast Cancer Prediction and Detection: Comparison of the Latest Machine Learning Techniques; GIS-Based Identification and Representation of Particulate Matters Using Ontology and SPARQL; Advancements in Arrhythmia Classification: A Comprehensive Survey of AI Techniques; Survey on VANET Authentication Scheme Based on Cryptographic Protocols; exploring Machine Learning Models for Age Recognition; novel Authentication Scheme to Increase Security of Vehicular Ad Hoc Networks; a Study on the Working of Swarm-Based Metaheuristic Algorithms Using Theoretical Framework; Financial Fortunes: A Stock Price Prediction Using LSTM; utilization of Data Mining in Spatial Analysis of Displacement Crisis in Iraq; integrating Multimodal Data for Parkinson’s Disease Prediction: An Ensemble Approach; Mental Health Assessment Using EEG Sensor and Machine Learning; enhancing Patterns Accessibility for Visually Impaired Programmers; lung and Colon Cancer Detection: Advancing Automated Diagnosis Through Deep Learning; detection of Micro and Macro Nutrient Deficiency in Okra (Abelmoschus Esculentus L) Plant Leaves Using Machine Learning Approach; empowering Aspiring Artists: A Machine Learning-Powered Carnatic Music Tutor; image Denoising Using Autoencoder: Utilizing Deep Learning and Autoencoder Techniques to Enhance Natural Images by Eliminating Noisy Pixels and Grains; an IoT-Based Animal Health Monitoring System; experimental Analysis of Four Gamma Correction Variants on Brain Tumor Images; WSD-Based Bangla Cyberbullying Detection Using Transform Learning; Proposed Hybrid Approach Using Swarm Intelligence in VANETs; investigation on Performance Evaluation of Loosely Coupled Microservice for Scalable Computation in Agriculture; a Study on Lightweight Object Detection in Thermal Images and Its Recent Advances.
B93: 6th conference on Computing Systems and Applications, CSA 2024 | C93: 2024 | D93: 0 | E93: https://www.scopus.com/inward/record.uri?eid=2-s2.0-85211798400&partnerID=40&md5=631aee0523b6cb2b440291c02fcce15b | F93: IR | H93: =countif(Survey!$E$2:$E$57,E93) -> 0 | I93: The proceedings contain 37 papers. The special focus in this conference is on Computing Systems and Applications. The topics include: Investigating Person Attribute Recognition in Challenging Environments; Layer-Wise Compression Analysis of CNN Architectures: Insights from VGG16; Enhanced ECG Signals Classification with Image-Driven Ensemble Deep Transfer Learning; learning N:M Structured Sparse Neural Networks from Scratch: A Comparative Study; breast Density Prediction from Mammograms: A Comprehensive Review; effective Writer Identification from Text Fragments Using Lightweight Convolutional Autoencoder; efficient End-to-End Deep Learning Model for Algerian Drug Label Recognition; exploring the Extremes of Two-Layer Convolutional Autoencoders Architecture in Image Inpainting; Enhancing Diabetic Retinopathy Identification Through Novel Image Representation and Hybrid CNN-Transformer Segmentation; enhancing Breast Mass Cancer Detection Through Hybrid ViT-Based Image Segmentation Model; New Adaptive PolSAR Speckle Filtering Based on Sigma Edge Detection; deep Learning for Effective Tuberculosis Detection from Chest Radiographs: A Comparative Study; On the Joint Use of CNN and OC-PCA Classifier for Cross-Domain Potato Disease Identification; memory-Aware Scheduling for Time-Sensitive Many-Core Systems; efficient Congestion and Popularity-Aware Caching Solution for Named Data Networking; multicast Routing over Industrial Internet of Things; When Curriculum Learning Meets Multi-Agent DRL in Connected Autonomous Vehicles; fault Tolerant Aware Scheduling on IoT Systems: A Comparative Study; multi-agent Deep Reinforcement Learning for Self-organized Aggregation of a Swarm of Robots; enhanced Navigation Based Obstacle Avoidance and Target Tracking with Raspberry-Pi for Mobile Robots; ioT Based Road Surface Condition Monitoring Using Spatiotemporal Feature Learning; longitudinal Evaluation of Android Malware Detection Using Deep Learning Classifiers; addressing Poisoning Attacks Against Federated Intrusion Detection Systems in Internet of Healthcare Things; a Dynamic Heuristic Search for Textual Adversarial Attacks; DDPG-PER for an IRS-Aided Secure Wireless Communication; model Checking-Enhanced Spectrum-Based Fault Localization; SGSN: Tool Support for GSN Development; SysML Model-Driven Development for Digital Twins.
B94: 2024 International Conference on Intelligent Systems and Advanced Applications, ICISAA 2024 | C94: 2024 | D94: 0 | E94: https://www.scopus.com/inward/record.uri?eid=2-s2.0-85217269728&partnerID=40&md5=5c201409a8a86a3e8db33485f392fafb | F94: IR | H94: =countif(Survey!$E$2:$E$57,E94) -> 0 | I94: The proceedings contain 180 papers. The topics discussed include: monitoring the battery health in electric vehicles through IOT; a CNN-based approach for early detection of breast cancer using infrared imaging; the development and impact of an intelligent scheduling system for educational institutions; vitamin deficiency detection using image processing through dermatological symptoms; enhancing large language models with google knowledge integration for rapid response in healthcare challenges; a novel lightweight encryption scheme based on transformation matrix and ChaCha20 algorithm for secure snap transmission; AI-driven energy management system for industrial and commercial facilities to enhance energy optimization; and mitigating denial of service attacks through machine learning-based intrusion detection.
B95: 1st International Conference on Artificial Intelligence in Healthcare, AIiH 2024 | C95: 2024 | D95: 0 | E95: https://www.scopus.com/inward/record.uri?eid=2-s2.0-85202507213&partnerID=40&md5=f8bddf1a083b2b2afbb3e32fb37a4b48 | F95: IR | H95: =countif(Survey!$E$2:$E$57,E95) -> 0 | I95: The proceedings contain 47 papers. The special focus in this conference is on Artificial Intelligence in Healthcare. The topics include: Assessing the Impact of Deep Learning Backbones for Mass Detection in Breast Imaging; Transferable Variational Feedback Network for Vendor Generalization in Accelerated MRI; CVD_Net: Head and Neck Tumor Segmentation and Generalization in PET/CT Scans Across Data from Multiple Medical Centers; applying Deep Learning Based Super-Resolution to Knee Imaging; FM-LiteLearn: A Lightweight Brain Tumor Classification Framework Integrating Image Fusion and Multi-teacher Distillation Strategies; towards Improving Single-Cell Segmentation in Heterogeneous Configurations of Cardiomyocyte Networks; Texture Feature Analysis for Classification of Early-Stage Prostate Cancer in MpMRI; DELRecon: Depth Electrode Reconstruction Toolbox for Stereo-EEG; segmenting Breast Ultrasound Scans Using a Generative Adversarial Network Embedding U-Net; enhancing Predictive Accuracy in Embryo Implantation: The Bonna Algorithm and its Clinical Implications; bacterial Behaviour Analysis Through Image Segmentation Using Deep Learning Approaches; innovations in Mosquito Identification: Integrating Deep Learning with Citizen Science; action Recognition for Privacy-Preserving Ambient Assisted Living; weight Perturbations for Simulating Virtual Lesions in a Convolutional Neural Network; Using GANs to Visualise Class-Specific Features in Digital Histopathology Images; artificial Intelligence for Predicting Responses to Thyroid Cancer Treatment; ZMAM: A ZKP-Based Mutual Authentication Scheme for the IoMT; Demystifying the Ethical Framework for Generative AI in Healthcare: A Data Science Perspective; explainable Machine Learning: Predicting Clinical Outcomes in Welsh Emergency Departments; enhancing Performance for Highly Imbalanced Medical Data via Data Regularization in a Federated Learning Setting; intelligent Multi-document Summarisation for Extracting Insights on Racial Inequalities from Maternity Incident Investigation Reports; synthetic Patient Perspective Data for the Curation and Evaluation of Rare Disease Patient-Facing Technology.
A96: Ahmed, S.; Ahmad, W.A.K.; Suneel, S.; Kaur Bhatia, M.; Gopinath, D.; singh, S. | B96: Zero-Knowledge AI Enhancing Data Privacy in Federated Learning Models | C96: 2025 | D96: 0 | E96: https://www.scopus.com/inward/record.uri?eid=2-s2.0-105021946444&doi=10.1109%2FICIMIA67127.2025.11200577&partnerID=40&md5=a87a108a89689e25b638b8c44e26cb7c | F96: SA | G96: ST | H96: =countif(Survey!$E$2:$E$57,E96) -> 0 | I96: With the increasing need to train AI models on sensitive healthcare data, Federated Learning (FL) has emerged as a decentralized approach that avoids raw data sharing. However, existing methods such as DP-FL and zkFL still suffer from high privacy leakage, computational overhead, and scalability challenges. To overcome these limitations, this study introduces ZK-FedTransformer++, a novel privacy-preserving FL framework. It integrates lightweight TinyViT transformers, zk-SNARKs for verifiable training, differential privacy for statistical protection, and heuristic client selection for robust participation The approach provides secure model updates via cryptographic proof circuits and noise-perturbed gradients. Experiments based on the RSNA Breast Cancer Detection dataset achieve 91.2% accuracy and 35% less privacy leakage. Tools utilized include PyTorch, zk-SNARK libraries, and privacy accounting protocols. In summary, ZK- FedTransformer++ is an effective privacy enhancement, accuracy improvement, and scalability solution that is a feasible solution for secure, decentralized AI applications in real-world healthcare and IoT settings. © 2025 IEEE.
A97: Chen, L.; Zhang, X. | B97: YOLO-MAFS: Multi-scale Attention Fusion Network for Precise Breast Cancer Segmentation in Ultrasound Images | C97: 2025 | D97: 0 | E97: https://www.scopus.com/inward/record.uri?eid=2-s2.0-105022247344&partnerID=40&md5=3e1c730e026d9d30a0b1de328a2663e1 | F97: P | G97: Y | H97: =countif(Survey!$E$2:$E$57,E97) -> 0 | I97: In recent years, the incidence of breast cancer has continued to rise. Early screening and precise segmentation of lesion regions are essential for improving diagnostic accuracy and patient prognosis. However, limited data availability and the blurred boundaries of lesions often lead to false detections and missed segmentations in existing models. To address these challenges, this paper proposes a novel model for breast cancer ultrasound image segmentation, named YOLO-MAFS. The model integrates group convolution into the C3k2 module, effectively reducing computational complexity while enhancing segmentation accuracy. Additionally, a lightweight feature fusion module, MAFM, is introduced to handle the diverse appearances of lesion regions. To further address the issue of blurred lesion boundaries, the HAFB module is incorporated between the backbone and the detection head. Moreover, the LASH segmentation head is employed to improve the model’s ability to capture subtle features. Experimental results on the BUS-BRA dataset demonstrate that YOLO-MAFS achieves improvements of 4.2% and 2.5% in mAP@50 and mAP@50–95, respectively, compared to YOLOv11. The model maintains a lightweight architecture while delivering high accuracy, making it well-suited for lesion segmentation in breast cancer ultrasound imaging. © 2025, International Association of Engineers. All rights reserved.
A98: Damodharan, D.; Jain, R.; Premavathi, T.; Parmar, K.; Ghribi, W.; Ahmed, A.M.; Ahmad, N. | B98: YOLO in Healthcare: A Comprehensive Review of Detection Architectures, Domain Applications, and Future Innovations | C98: 2025 | D98: 0 | E98: https://www.scopus.com/inward/record.uri?eid=2-s2.0-105013755493&doi=10.1109%2FACCESS.2025.3599358&partnerID=40&md5=13d30e58f1d3749764d115e9db52da43 | F98: P | G98: Y | H98: =countif(Survey!$E$2:$E$57,E98) -> 0 | I98: The growing adoption of deep learning in medical imaging has propelled object detection frameworks into clinical relevance, with YOLO (You Only Look Once) standing out for its real-time inference and high accuracy. This survey offers a comprehensive review of YOLO-based medical object detection, synthesizing findings from 123 peer-reviewed papers published between 2018 and 2024. Across oncology, radiology, pathology, surgery, and PPE detection, YOLO models have demonstrated strong performance in tumor localization, lesion segmentation, tool tracking, and anomaly detection. YOLOv3 and YOLOv5 remain the most frequently deployed variants, while YOLOv8 and YOLO-NAS are emerging in recent studies with improved mAP and lower latency. Findings reveal that mAP scores exceeding 85% were commonly achieved in breast cancer and pulmonary nodule detection tasks, while lightweight versions such as YOLOv5s maintained detection speed above 50 FPS in surgical environments. Despite its clinical promise, persistent challenges include poor sensitivity to small or rare lesions, absence of benchmark datasets across modalities, and variability in annotation practices. This survey introduces a structured taxonomy of YOLO architectures, benchmarks their comparative performance, highlights key limitations, and proposes forward-looking trends involving multimodal fusion, transformer-enhanced backbones, and privacy-preserving learning. The work consolidates YOLO’s growing role in healthcare AI and serves as a foundational reference for researchers and practitioners alike. © 2013 IEEE.
A99: Hasan Mahfuz, M.M.H.; Islam, M.R.; Malek, N.F.A.; Habaebi, M.H.; Sakib, N.; Baladi, E. | B99: WEARABLE TEXTILE PATCH DSSRS ANTENNA FOR BODY TUMORS DETECTION WITH REDUCED SAR | C99: 2025 | D99: 2 | E99: https://www.scopus.com/inward/record.uri?eid=2-s2.0-85216392400&doi=10.31436%2FIIUMEJ.V26I1.3221&partnerID=40&md5=d5c4afba48d38caacbbeceee7ead2d51 | F99: SA | H99: =countif(Survey!$E$2:$E$57,E99) -> 0 | I99: The purpose of this study is to present a lightweight wearable (jeans) monopole antenna configuration for body area network (BAN) communication, breast and head tumors detections with back lobe reduction (i.e., low SAR), and it does so without introducing any special methodologies like as, AMC, EBG, HIS. The planned antenna has dual symmetrical slots as well as a ring-shaped slot (DSSRS) at the top, and it is in the form of a radiating rectangular patch with a ground plane. The design procedure has been finished with the help of CST MWS, and the next step will be to fine-tune the parameters of the antenna structure to achieve resonance at the ISM band (5.79 GHz). Testing for BAN, breast, and brain tumor detection was done using this prototype. With the proper impedance matching, the antenna achieves an operational bandwidth of 5.798 GHz (5.739–5.865 GHz), 5.77 GHz (5.715–5.838 GHz), 5.77 GHz (5.718–5.843 GHz) and 5.78 GHz (5.725–5.834 GHz), with an overall peak gain of 8.18 dBi, 7.69 dBi, 5.73 dBi, and 4.59 dBi; when proposed antenna placed on the free space, on the body, on the breast, and the head respectively. The suggested antenna meets the specific absorption rate (SAR) standards given by the FCC (1 gm) and the ICNIRP (10 gm). © (2025), (International Islamic University Malaysia). All rights reserved.
A100: Gong, J.; Ye, P.; Chang, Z. | B100: The application of lightweight AI algorithms in postoperative rehabilitation of breast cancer | C100: 2025 | D100: 1 | E100: https://www.scopus.com/inward/record.uri?eid=2-s2.0-85179734403&doi=10.1080%2F10255842.2023.2292009&partnerID=40&md5=4c588f2638cac677f5d89fbcf609c9bc | F100: ST | H100: =countif(Survey!$E$2:$E$57,E100) -> 0 | I100: The prevalence of breast cancer as a major global cancer has underscored the importance of postoperative recovery for breast cancer patients. Among the issues, postoperative patients are prone to spinal deformities, including scoliosis, which has drawn significant attention from healthcare professionals. The primary aim of this study is to design a postoperative recovery platform for breast cancer patients that can effectively detect posture changes, provide feedback and support to medical staff, assist doctors in formulating recovery plans, and prevent spinal deformities. The feasibility of the recovery platform is also validated through experiments. The development and validation of the experimental recovery platform. The recovery platform includes instrument design, patient data collection, model training and fine-tuning, and postoperative body posture evaluation by comparing preoperative and postoperative conditions. The evaluation results are provided to doctors to facilitate the formulation of personalized postoperative recovery plans. This paper comprehensively designs and implements the recovery platform and verifies its feasibility through simulation experiments. Statistical methods were employed for the validation of the rehabilitation platform in simulated experiments, with a significance level of p < 0.05. In comparison to static assessments like CT scans, this paper introduces a dynamic detection method that provides a more insightful analysis of body posture. The experiments also demonstrate the preventive capability of this method against post-operative spinal deformities, ultimately enhancing patients’ self-image, restoring their confidence, and enabling them to lead more fulfilling lives. © 2023 Informa UK Limited, trading as Taylor & Francis Group.
A101: Alkhazaali, A.A.T.; Ahmed, J.I.; Alansari, S.Z.A.; Mohammed, H.C.; Amanah, L.N. | B101: TC-XGBoost: Efficient Feature Selection Method using Tetrachoric Correlation with Machine Learning Classifiers for Enhanced Breast Cancer Diagnosis | C101: 2025 | D101: 0 | E101: https://www.scopus.com/inward/record.uri?eid=2-s2.0-105019357660&doi=10.22266%2Fijies2025.1130.51&partnerID=40&md5=3dae90700e7ba2b83aedcde89df638c7 | F101: SA | H101: =countif(Survey!$E$2:$E$57,E101) -> 0 | I101: This study introduces an innovative feature selection method grounded in Tetrachoric Correlation (TC) to improve the accuracy and efficiency of breast cancer classification systems. Conventional techniques such as Information Gain and Pearson Correlation Coefficient (PCC) non-linear and hidden relationships between features and target labels are often overlooked by these methods. In contrast, the proposed TC-based method evaluates hidden binary correlations, allowing the identification of key features for classification. Then wrought with four machine learning models-XGBoost, Naive Bayes (NB), Logistic Regression (LR), and Random Forests (RF), these final features were used to demonstrate that the proposed method outperformed the existing models on the Wisconsin Diagnostic Breast Cancer (WDBC) dataset. The TC-XGBoost model was found to be very effective, achieving an accuracy of 99.12% on the WDBC breast cancer dataset-which was an improvement over the baseline XGBoost accuracy of 94.74%, without the use of any feature selection. The TC method also pruned the original 30 features down to just 9, or a 70% decrease in dimensionality, which decreased execution time by more than 45%, thus enhancing computational efficiency without sacrificing accuracy. With effective performance, reduced feature set, low runtime cost, the TC-based framework is an attractive lightweight diagnostic tool for early breast cancer detection, particularly for resource-limited clinical environments or real-time applications. © This article is licensed under a Creative Commons Attribution-ShareAlike 4.0 International License. License details: https://creativecommons.org/licenses/by-sa/4.0/
A102: Majumder, S.; Paul, A.; Schwenker, F.; Sarkar, R. | B102: SAWL-Net: A Statistical Attentions and Wavelet Aided Lightweight Network for Classification of Cancers in Histopathological Images | C102: 2025 | D102: 2 | E102: https://www.scopus.com/inward/record.uri?eid=2-s2.0-85217015380&doi=10.1109%2FTAI.2025.3536424&partnerID=40&md5=3a16379b22710aecb9e00307936919cb | F102: P | G102: Y | H102: =countif(Survey!$E$2:$E$57,E102) -> 0 | I102: Addressing the formidable challenges posed by the diagnosis and management of various types of cancer, including breast, colon, lung, and colorectal cancer, demands innovative solutions to streamline histopathological analysis processes. In this study, we propose a novel lightweight convolutional neural network (CNN) called statistical attentions and wavelet aided lightweight network (SAWL-Net) architecture based on MobileNetV2 equipped with hybrid statistical similarity and wave format-aided attention mechanisms, specifically tailored to the demands of cancer histopathology. By leveraging the capabilities, our model incorporates a lightweight design while ensuring high-performance outcomes. We introduce a unique combination of Pearson correlation coefficient, Spearman rank correlation, and cosine similarity metrics, alongside a specialized wave conversion technique to enhance the detection of similarities across different channels of histopathological data, while providing a holistic approach to the model. In this study, we have considered breast, colorectal, and lung & colon cancer datasets for experimentation. Notably, our model surpasses prevailing state-of-the-art methodologies, showcasing its efficacy in optimizing diagnostic accuracy and expediting treatment strategies for varied cancer types. Our codes are publicly available at the GitHub repository. © IEEE. 2020 IEEE.
A103: Liu, Y.; Li, H.; Zhu, Z.; Chen, C.; Zhang, X.; Jin, G.; Li, H. | B103: RSDCNet: An efficient and lightweight deep learning model for benign and malignant pathology detection in breast cancer | C103: 2025 | D103: 0 | E103: https://www.scopus.com/inward/record.uri?eid=2-s2.0-105002973748&doi=10.1177%2F20552076251336286&partnerID=40&md5=ace3391d039f324f6e94b157d7c13bce | F103: P | G103: Y | H103: =countif(Survey!$E$2:$E$57,E103) -> 0 | I103: Background: Breast cancer is a leading malignant tumor among women globally, with its pathological classification into benign or malignant directly influencing treatment strategies and prognosis. Traditional diagnostic methods, reliant on manual interpretation, are not only time-intensive and subjective but also susceptible to variability based on the pathologist's expertise and workload. Consequently, the development of an efficient, automated, and precise pathological detection method is crucial. Methods: This study introduces RSDCNet, an enhanced lightweight neural network architecture designed for the automatic detection of benign and malignant breast cancer pathology. Utilizing the BreakHis dataset, which comprises 9109 microscopic images of breast tumors including various differentiation levels of benign and malignant samples, RSDCNet integrates depthwise separable convolution and SCSE modules. This integration aims to reduce model parameters while enhancing key feature extraction capabilities, thereby achieving both lightweight design and high efficiency. Results: RSDCNet demonstrated superior performance across multiple evaluation metrics in the classification task. The model achieved an accuracy of 0.9903, a recall of 0.9897, an F1 score of 0.9888, and a precision of 0.9879, outperforming established deep learning models such as EfficientNet, RegNet, HRNet, and ViT. Notably, RSDCNet's parameter count stood at just 1,199,662, significantly lower than HRNet's 19,254,102 and ViT's 85,800,194, highlighting its enhanced resource efficiency. Conclusion: The RSDCNet model presented in this study excels in the efficient and accurate classification of benign and malignant breast cancer pathology. Compared to traditional methods and other leading models, RSDCNet not only reduces computational resource consumption but also offers improved feature extraction and clinical interpretability. This advancement provides substantial technical support for the intelligent diagnosis of breast cancer, paving the way for more effective treatment planning and prognosis assessment. © The Author(s) 2025.
A104: Gupta, D. | B104: Reducing Global Breast Cancer Mortality with Early, Low-Cost Diagnosis Using Generative AI and Hybrid DL Architecture | C104: 2025 | D104: 0 | E104: https://www.scopus.com/inward/record.uri?eid=2-s2.0-105011275624&doi=10.1109%2FCAI64502.2025.00089&partnerID=40&md5=6a408a12e8ceaec0d3099306e4c7680e | F104: P | G104: Y | H104: =countif(Survey!$E$2:$E$57,E104) -> 0 | I104: Breast cancer is the most common cancer in the world [1]. Mortality rates stand at 27 percent in India and 60 in Africa, compared to 7 in the US [2]. This disconnect boils down to the time of diagnosis. According to the CDC late-stage diagnosis has a five-year mortality rate of 69 percent, compared to 2 percent for early diagnosis [3]. Underserved communities lack access to high-cost, advanced diagnostic tech-nologies (MRIs/Mammograms) and cancer specialists (Oncolo-gists/Radiologists) [4]. Patients must depend on low-cost, low-resolution modalities (Ultrasounds) and the limited breast cancer expertise of general physicians (and gynecologists in developing countries), significantly delaying diagnosis and subsequent in-tervention [5]. This study aims to reduce global breast cancer mortality and healthcare costs by enabling accurate, early, and low-cost diagnosis using the existing ultrasound infrastructure in developing countries and underserved communities. To address data scarcity and skew, advanced image augmentation techniques such as deep convolutional GANs and stable diffusion models were evaluated. In each case of data augmentation, two classification approaches were compared: a lightweight MobileNetV2 convolutional neural network and a hybrid model combining ResNet50 for feature extraction with statistical machine learning models. The highest detection accuracy (95 percent) was achieved using the hybrid model with ResNet50 and XGBoost, paired with Stable Diffusion augmentation. An iOS app was implemented to demonstrate the feasibility of this approach in resource-constrained settings, showcasing its potential for scalable, efficient diagnostic solutions. © 2025 IEEE.
A105: Ur Rehman, K.; Tian, Y.; Li, J.; Yasin, A.; Jabbar, A.; Shin, J.; Al-Shamri, M.Y.H.; Ullah, I. | B105: Radiomic V-Net Deep Learning Architecture for Breast Cancer Prediction Deployed on Medical Consumer Electronics | C105: 2025 | D105: 0 | E105: https://www.scopus.com/inward/record.uri?eid=2-s2.0-105021269521&doi=10.1109%2FTCE.2025.3630000&partnerID=40&md5=4b94fcfe2989fcf1a8d3c79788190624 | F105: P | G105: Y | H105: =countif(Survey!$E$2:$E$57,E105) -> 0 | I105: This paper introduces a radiomic-integrated 2D V-Net architecture designed for deployment on medical consumer electronics (MCE) platforms. The system targets real-time detection of architectural distortion in mammograms, a critical indicator for early breast cancer screening. Unlike conventional clinical models, our approach is optimized for consumer-grade edge devices, including Jetson Nano, Raspberry Pi 4, and Snapdragon 865, enabling diagnostic capability in home, rural, and mobile health settings. To achieve this, we employ lightweight design strategies such as top-hat morphological preprocessing, radiomic feature integration, and skip-connected V-Net layers. Deployment efficiency is further enhanced with INT8 quantization, pruning, and operator fusion, reducing model size and latency while preserving accuracy. Experimental evaluation on the CBIS-DDSM and PINUM datasets demonstrates robust performance, with accuracies of 0.98 and 0.97 and specificities of 0.97 and 0.87, respectively. A dedicated visualization interface for smartphones and tablets provides interactive feedback and encrypted report sharing, bridging patients and healthcare providers. By combining radiomic insights, edge AI deployment, and consumer-grade accessibility, this work contributes a scalable, privacy-aware solution for smart healthcare ecosystems and next-generation MCE. © 1975-2011 IEEE.
B106: Proceedings of the 2nd International Conference on Innovations in Electronics and Communication Systems, ICIECS 2022 | C106: 2025 | D106: 0 | E106: https://www.scopus.com/inward/record.uri?eid=2-s2.0-85216120907&partnerID=40&md5=8e84515b90dfa1ef6cc5b268b830c812 | F106: IR | H106: =countif(Survey!$E$2:$E$57,E106) -> 0 | I106: The proceedings contain 75 papers. The topics discussed include: Bluetooth based home automation; priority ranked search of multiple keywords for authentication mechanism using cloud data management; object detection in visual recognition system based on deep learning techniques; block chain based novel energy efficient routing protocol for wireless sensor network; a real-time human eye pupil tracking system using FPGA; design and analysis of forward problem of electrical impedance tomography for breast cancer screening; lightweight sybil attack detection framework for wireless sensor network with cluster topology; breast cancer detection using enhanced preprocessing techniques to trace accurate skin air interface; and fractal texture analysis for automated breast cancer detection.
A107: Oladimeji, O.; Ayaz, H.; McLoughlin, I.; Unnikrishnan, S. | B107: Optimizing BI-RADS 4 Lesion Assessment Using Lightweight Convolutional Neural Network with CBAM in Contrast Enhanced Mammography | C107: 2025 | D107: 0 | E107: https://www.scopus.com/inward/record.uri?eid=2-s2.0-85219183459&doi=10.1007%2F978-3-031-77789-9_10&partnerID=40&md5=1c4f86926593d3f500e6a340e24aba67 | F107: P | G107: Y | H107: =countif(Survey!$E$2:$E$57,E107) -> 0 | I107: Breast cancer is the leading cause of cancer-related mortality and morbidity among women worldwide. Early detection plays a crucial role in improving survival rates and BI-RADS classification is one of the effective ways of predicting breast cancer. However, BI-RADS Category 4 encompasses a broad spectrum of malignancy probabilities, ranging from over 2% to 95%. Due to the wide malignancy likelihood range and the ambiguous qualitative attributes of BI-RADS 4, patients are subjected to overdiagnosis and unnecessary procedures, such as biopsy, which entail a certain degree of physical trauma as well as financial strain. This study proposed a lightweight CNN where MobileNet serves as the backbone architecture, augmented with the Convolutional Block Attention Module (CBAM), resulting in the MobileNet-CBAM model. The model demonstrated good performance in discriminating BI-RADS 4 category malignant and benign cases in Contrast Enhanced Spectral Mammogram (CESM) with a prediction of 82%, 82% and 0.91 for accuracy, f1-score and roc-auc respectively. Additionally, for clinical friendliness, the model explanation was given using SHAP. Hence, the model presents potential utility in predicting breast cancer for lesions categorized as BI-RADS category 4 in breast imaging. © The Author(s), under exclusive license to Springer Nature Switzerland AG 2025.
A108: Sreekala, K.; Sahoo, J. | B108: Optimized Lightweight Temporal Attention-Based Convolutional Neural Network Espoused Automatic Diagnosis and Classification of Breast Cancer | C108: 2025 | D108: 0 | E108: https://www.scopus.com/inward/record.uri?eid=2-s2.0-105024009698&doi=10.1007%2Fs44174-025-00527-7&partnerID=40&md5=4da6f0308fefc016ed35c08d079c86ab | F108: NA | G108: UA | H108: =countif(Survey!$E$2:$E$57,E108) -> 0 | I108: Breast cancer is still a life-threatening and common disease in women globally. Early identification is essential to improve outcomes and lower death rates. Recently, number of innovative approaches has been developed for creating an efficient diagnosis and classification of such a harmful sort of cancer. But there is a lack of accuracy. For improving diagnostic accuracy and minimizing false negatives, this research proposes an optimized deep learning model called LTACNN-ADC-BC (Lightweight Temporal Attention-based Convolutional Neural Network for Automatic Detection with Classification of Breast Cancer). The proposed model analyzes mammography images through Multi-window Savitzky–Golay Filter (MWSGF) for noise removal, followed by feature extraction and classification through a Lightweight Temporal Attention-Based Convolution Neural Network (LTACNN). For further optimization, the model incorporates the Stock Exchange Trading Optimization Algorithm (SETOA) for the fine-tuning of network parameters. The proposed approach is tested with MIAS dataset, real-time dataset, and CBIS-DDSM dataset. Performance indicators reflect remarkable improvements over prior methods, with the model identifying 99.51% accuracy and 0.9992 AUC for MIAS, 99.26% accuracy for the real-time dataset, and 98.54% accuracy with 0.983 AUC for CBIS-DDSM dataset. These performances indicate the efficacy of the LTACNN-ADC-BC method in differentiating between normal, benign, and malignant cases. The LTACNN-ADC-BC model has strong potential for integration into computer-assisted diagnostic systems. It provides improved assistance to radiologists for the diagnosis and screening of breast cancer. © The Author(s), under exclusive licence to Springer Science+Business Media, LLC, part of Springer Nature 2025.
A109: Esen, G.; Nurtas, M.; La Paglia, L.; Amankulov, J.; Matkerim, B.; Altaibek, A. | B109: Multi-Task Attention-Guided Deep Learning for Simultaneous Breast Cancer Detection and Density Estimation in Mammography | C109: 2025 | D109: 0 | E109: https://www.scopus.com/inward/record.uri?eid=2-s2.0-105022621387&doi=10.1109%2FACCESS.2025.3634473&partnerID=40&md5=2cb3cd8eee3e3601b19971294596ca22 | F109: P | G109: Y | H109: =countif(Survey!$E$2:$E$57,E109) -> 0 | I109: Early detection of breast cancer is critical for improving patient outcomes, and deep learning (DL) has shown promise in mammographic analysis. However, many existing systems tackle a single task (e.g., malignancy classification) and provide limited interpretability, which hinders clinical adoption. We present a multi-task, attention-guided framework that jointly predicts malignancy (benign vs. malignant) and BI-RADS breast density (A–D) from a single mammogram while producing interpretable attention maps. The architecture couples a pretrained convolutional backbone with lightweight channel–spatial attention and two task-specific heads. We evaluate six backbones (ResNet-50, DenseNet-121, EfficientNet-B0/B3/B7, MobileNetV3-Large) under a rigorous evaluation protocol with stratified hold-out split (64%/16%/20%) and 5-fold cross-validation. To support reliable deployment, we report comprehensive metrics including discrimination measures (ROC-AUC, PR-AUC, F1-score, sensitivity, specificity), calibration metrics (Brier score, Expected Calibration Error), and ablation studies contrasting single-task vs. multi-task learning and models with vs. without attention mechanisms. Across all evaluation protocols, multi-task learning consistently outperforms single-task baselines by 2.8% in pathology accuracy and 3.5% in density estimation, indicating that density cues provide complementary information for malignancy assessment. Among backbones, EfficientNet-B3 attains the strongest discrimination (AUC= 0.962, accuracy= 93.6%) on hold-out test with excellent calibration (Brier= 0.010), while MobileNetV3-Large achieves competitive performance (AUC= 0.940, accuracy= 91.2%) with only 4.26M parameters—an optimal accuracy–efficiency trade-off for resource-constrained deployment. Cross-validation results demonstrate robust generalization (AUC = 0.954 ± 0.003 , accuracy = 93.0 ± 0.3% ). Attention maps highlight diagnostically relevant regions including architectural distortions and suspicious calcifications, offering interpretable visual rationale aligned with radiological assessment. We discuss limitations including dataset size (410 images), class imbalance in rare density categories, and calibration challenges (ECE= 0.365–0.419), and outline directions for external validation on multi-institutional cohorts and integration of uncertainty quantification methods. © 2013 IEEE.
A110: Wang, X.; Zeng, W.; Xu, J.; Zhang, S.; Gu, Y.; Li, B.; Wang, X. | B110: MM-3D Unet: development of a lightweight breast cancer tumor segmentation network utilizing multi-task and depthwise separable convolution | C110: 2025 | D110: 0 | E110: https://www.scopus.com/inward/record.uri?eid=2-s2.0-105006687915&doi=10.3389%2Ffonc.2025.1563959&partnerID=40&md5=faab156d9a85e140c94cb47c6fa02971 | F110: P | G110: Y | H110: =countif(Survey!$E$2:$E$57,E110) -> 0 | I110: Background and objectives: This paper introduces a novel lightweight MM-3DUNet (Multi-task Mobile 3D UNet) network designed for efficient and accurate segmentation of breast cancer tumors masses from MRI images, which leverages depth-wise separable convolutions, channel expansion units, and auxiliary classification tasks to enhance feature representation and computational efficiency. Methods: We propose a 3D depth-wise separable convolution, and construct channel expansional convolution (CEC) unit and inverted residual block (IRB) to reduce the parameter count and computational load, making the network more suitable for use in resource-constrained environments. In addition, an auxiliary classification task (ACT) is introduced in the proposed architecture to provide additional supervisory signals for the main task of segmentation. The network architecture features a contracting path for downsampling and an expanding path for precise localization, enhanced by skip connections that integrate multi-level semantic information. Results: The network was evaluated using a dataset of Dynamic Contrast Enhanced MRI (DCE-MRI) breast cancer images, and the results show that compared to the classical 3DU-Net, MM-3DUNet could significantly reduce model parameters by 63.16% and computational demands by 80.90%, while increasing segmentation accuracy by 1.30% in IoU (Intersection over Union). Conclusions: MM-3DUNet offers a substantial reduction in computational requirements of breast cancer mass segmentation network. This network not only enhances diagnostic precision but also supports deployment in diverse clinical settings, potentially improving early detection and treatment outcomes for breast cancer patients. © © 2025 Wang, Zeng, Xu, Zhang, Gu, Li and Wang.
...

Sheet raw_2026
