Workbook

Sheet Scopus_WOS
A1: C | B1: Article Title | C1: Publication Year | D1: Source Title | E1: Cited Reference Count | F1: Affiliations | G1: Abstract | H1: Author Keywords | I1: Keywords Plus | J1: Publisher | K1: Document Type | L1: Open Access Designations | M1: status | N1: In_paper | O1: Exclusion reason
A2: Modu, F; Prasad, R; Aliyu, F | B2: development of a knowledge-distillation-based breast cancer classifier for lmics: comparison with pruning and quantization | C2: 2025 | D2: ELECTRONICS | E2: 71 | F2: African University of Science & Technology; King Fahd University of Petroleum & Minerals | G2: Breast cancer (BC) mortality rates remain high in Low- and Middle-Income Countries (LMICs) due to limited awareness, poverty, and inadequate medical facilities that hinder early detection. Although deep learning models have achieved high accuracy in BC detection (BCD), they require substantial computational resources, making them unsuitable for deployment in remote or rural areas. This study proposes a lightweight convolutional neural network (CNN) using Knowledge Distillation (KD) for BCD, where a large Teacher Model (TM) transfers learned representations to a smaller Student Model (SM), which is better suited for deployment on low-power devices. We compare it with two prominent model compression techniques: pruning and quantization. Experimental results indicate that the TensorFlow Lite (TFLite)-optimized Student Model (SM_TFLite) achieved 97.67% accuracy, representing a 2.33% relative loss to its teacher, a result comparable to other compression techniques. Its mean accuracy is 73.97% with a 95% Confidence Interval of [65.04%, 82.90%] in a cross-dataset experiment. However, SM_TFLite was the most compact (5.21 kB) and fastest (3.3 ms latency), outperforming both pruned (2924.31 kB, 13.68 ms) and quantized models (746-751 kB, 4-5 ms). Evaluation on a Raspberry Pi 4 Model B demonstrated that all models exhibited similar CPU and memory usage, with SM_TFLite causing only a minor increase in device temperature. These results demonstrate that KD combined with TFLite conversion offers the best trade-off between accuracy, compactness, and speed. | H2: breast cancer detection; lightweight CNN; Knowledge Distillation; pruning; quantization; IoT; healthcare; telemedicine; breast cancer; deep learning; convolutional neural network; Keras | J2: MDPI | K2: Article | L2: gold | M2: P | N2: Y
A3: Yeh, WC; Shia, WC; Hsu, YT; Huang, CH; Lee, YS | B3: a lightweight breast cancer mass classification model utilizing simplified swarm optimization and knowledge distillation | C3: 2025 | D3: BIOENGINEERING-BASEL | E3: 55 | F3: National Tsing Hua University; Chung Yuan Christian University; Changhua Christian Hospital; Chang Gung University; Feng Chia University | G3: In recent years, an increasing number of women worldwide have been affected by breast cancer. Early detection is crucial, as it is the only way to identify abnormalities at an early stage. However, most deep learning models developed for classifying breast cancer abnormalities tend to be large-scale and computationally intensive, often overlooking the constraints of cost and limited computational resources. This research addresses these challenges by utilizing the CBIS-DDSM dataset and introducing a novel concatenated classification architecture and a two-stage strategy to develop an optimized, lightweight model for breast mass abnormality classification. Through data augmentation and image preprocessing, the proposed model demonstrates a superior performance compared to standalone CNN and DNN models. The two-stage strategy involves first constructing a compact model using knowledge distillation and then refining its structure with a heuristic approach known as Simplified Swarm Optimization (SSO). The experimental results confirm that knowledge distillation significantly enhances the model's performance. Furthermore, by applying SSO's full-variable update mechanism, the final model-SSO-Concatenated NASNetMobile (SSO-CNNM)-achieves outstanding performance metrics. It attains a compression rate of 96.17%, along with accuracy, precision, recall, and AUC scores of 96.47%, 97.4%, 94.94%, and 98.23%, respectively, outperforming other existing methods. | H3: lightweight breast cancer mass classification model; simplified swarm optimization; knowledge distillation; convolutional neural networks | J3: MDPI | K3: Article | L3: Green Submitted, gold | M3: {=IFERROR( INDEX(survey_paper_2026!$F:$F, MATCH(LOWER(TRIM(B3)), LOWER(TRIM(survey_paper_2026!$B:$B)),0) ), "New" )} -> P | N3: {=IFERROR( INDEX(survey_paper_2026!$G:$G, MATCH(LOWER(TRIM(B3)), LOWER(TRIM(survey_paper_2026!$B:$B)),0) ), "New" )} -> Y
A4: Khalid, N; Dagli, C; Obafenai-Ajayi, T; Wunsch, DW II | B4: knowledge distillation-based tinyml model for breast cancer detection using real and wasserstein gan-generated microwave imaging data | C4: 2025 | D4: 2025 47TH ANNUAL INTERNATIONAL CONFERENCE OF THE IEEE ENGINEERING IN MEDICINE AND BIOLOGY SOCIETY (EMBC) | E4: 17 | F4: University of Missouri System; Missouri University of Science & Technology; University of Missouri System; Missouri University of Science & Technology; Missouri State University | G4: Tiny Machine Learning (TinyML) offers a transformative approach to efficient, intelligent cancer diagnostics on edge devices. However, designing optimized TinyML models for breast cancer diagnosis using Microwave Imaging datasets remains a challenge due to domain-specific customization requirements. To address this, we propose a novel Knowledge Distillation framework, where a teacher model, built using residual convolutional neural networks, transfers its knowledge to a lightweight student model, enhancing efficiency while maintaining high accuracy. The teacher model achieves a 95.42% accuracy on test data. Through knowledge distillation, the student model attains 95.32% accuracy while achieving a 96% reduction in model size, significantly enhancing computational efficiency without compromising performance. Without distillation, the student model reaches a testing accuracy of 86.5%. A major contribution of this work is the generation of a highquality synthetic breast cancer dataset to address the scarcity of microwave imaging data. We employ a Wasserstein Generative Adversarial Network with Gradient Penalty (WGAN-GP) to synthesize realistic breast cancer scans, ensuring reliability through rigorous validation with a one-class Support Vector Machine. By training all models on a combination of real and synthetic datasets, our approach enhances robustness, making TinyML-powered breast cancer detection more viable for realworld deployment. | J4: IEEE | K4: Proceedings Paper | M4: P | N4: Y
A5: Sepahvand, M; Abdali-Mohammadi, F | B5: joint learning method with teacher-student knowledge distillation for on-device breast cancer image classification | C5: 2023 | D5: COMPUTERS IN BIOLOGY AND MEDICINE | E5: 46 | F5: Razi University | G5: The deep learning models such as AlexNet, VGG, and ResNet achieved a good performance in classifying the breast cancer histopathological images in BreakHis dataset. However, these models are not practically appro-priate due to their computational complexity and too many parameters; as a result, they are rarely utilized on devices with limited computational resources. This paper develops a lightweight learning model based on knowledge distillation to classify the histopathological images of breast cancer in BreakHis. This method employs two teacher models based on VGG and ResNext to train two student models, which are similar to the teacher models in development but have fewer deep layers. In the proposed method, the adaptive joint learning approach is adopted to transfer the knowledge in the final-layer output of a teacher model along with the feature maps of its middle layers as the dark knowledge to a student model. According to the experimental results, the student model designed by ResNeXt architecture obtained the recognition rate 97.09% for all histopathological images. In addition, this model has-69.40 million fewer parameters,-0.93 G less GPU memory use, and 268.17 times greater compression rate than its teacher model. While in the student model the recognition rate merely dropped down to 1.75%. The comparisons indicated that the student model had a rather acceptable outputs compared with state-of-the-art methods in classifying the images of breast cancer in BreakHis. | H5: Breast cancer images; On -device classification; Knowledge distillation; Teacher-student learning; Lightweight classification | I5: NEURAL-NETWORKS; COMPRESSION | J5: PERGAMON-ELSEVIER SCIENCE LTD | K5: Article | M5: P | N5: Y
A6: Meraj, T; Alosaimi, W; Alouf, B; Rauf, HT; Kumar, SA; Dama, R; Alyami, H | B6: a quantization assisted u-net study with ica and deep features fusion for breast cancer identification using ultrasonic data | C6: 2021 | D6: PEERJ COMPUTER SCIENCE | E6: 57 | F6: COMSATS University Islamabad (CUI); Taif University; Taif University; University of Bradford; Silesian University of Technology | G6: Breast cancer is one of the leading causes of death in women worldwide-the rapid increase in breast cancer has brought about more accessible diagnosis resources. The ultrasonic breast cancer modality for diagnosis is relatively cost-effective and valuable. Lesion isolation in ultrasonic images is a challenging task due to its robustness and intensity similarity. Accurate detection of breast lesions using ultrasonic breast cancer images can reduce death rates. In this research, a quantization-assisted U-Net approach for segmentation of breast lesions is proposed. It contains two step for segmentation: (1) U-Net and (2) quantization. The quantization assists to U-Net-based segmentation in order to isolate exact lesion areas from sonography images. The Independent Component Analysis (ICA) method then uses the isolated lesions to extract features and are then fused with deep automatic features. Public ultrasonic-modality-based datasets such as the Breast Ultrasound Images Dataset (BUSI) and the Open Access Database of Raw Ultrasonic Signals (OASBUD) are used for evaluation comparison. The OASBUD data extracted the same features. However, classification was done after feature regularization using the lasso method. The obtained results allow us to propose a computer-aided design (CAD) system for breast cancer identification using ultrasonic modalities. | H6: Quantization; Features fusion; Breast cancer; Ultrasonic images; Computer vision; Image processing | I6: CONVOLUTIONAL NEURAL-NETWORK; IMAGE SEGMENTATION; CLASSIFICATION; LESIONS | J6: PEERJ INC | K6: Article | L6: Green Submitted, gold | M6: SA | N6: {=IFERROR( INDEX(survey_paper_2026!$G:$G, MATCH(LOWER(TRIM(B6)), LOWER(TRIM(survey_paper_2026!$B:$B)),0) ), "New" )} -> New
A7: Hossain, MB; Shaban, M | B7: low-complexity low-memory vgg models for accurate diagnosis of breast cancer | C7: 2024 | D7: SOUTHEASTCON 2024 | E7: 14 | F7: University of South Alabama | G7: Breast cancer is considered the most prevalent cancer among women and may spread to other organs if it is not detected and treated early. In addition, mammography is the primary imaging modality and is widely used for screening and diagnosing breast cancer. Recent studies have applied deep learning for mammogram-based breast cancer detection. However, these methods have high computational and memory requirements. In this paper, we propose low-complexity light-weight VGG-16 and VGG-19 models that are able to detect breast cancer at an accuracy of 98% and a sensitivity of 95%. While the performance of the proposed models is comparable to that of the-state-of-the-art architectures, the proposed models were extensively compressed using a novel combination of filter pruning, node pruning and post-training quantization offering up to 98.4% reduction in the number of learning parameters, up to 97.6% drop in the number of FLOPs, and almost 99.6% decrease in the allocated memory. This will potentially facilitate the efficient implementation of the models on edge Internet of Things (IoT) devices deployed in future IoT healthcare platforms. | H7: Breast Cancer; Mammography; Deep Learning; Pruning; Quantization | J7: IEEE | K7: Proceedings Paper | M7: P | N7: Y
A8: Si, JL; Jia, W; Jiang, HF | B8: breast cancer histopathology images classification through multi-view augmented contrastive learning and pre-learning knowledge distillation | C8: 2024 | D8: IEEE ACCESS | E8: 43 | F8: Ningxia University; Ningxia Medical University | G8: Breast cancer is one of the most common malignant tumors in women, and accurate classification of benign and malignant breast cancer histopathology images is critical for diagnosis and treatment. Knowledge distillation techniques have recently received considerable attention for enabling cost-effective image classification of breast cancer histopathology images. However, there are still challenges, including the inefficient extraction of global and local features from breast cancer histopathology images by the teacher network, and the over-prioritization of feature fusion within the same encoder layer, which tends to neglect valuable information from adjacent encoder layers during knowledge extraction. To address these challenges, we propose a method that combines multi-view augmented contrastive learning and pre-learning knowledge distillation. Multi-view augmented contrastive learning improves the ability of the teacher network to extract global and local features. Pre-learning knowledge distillation merges features from adjacent encoder layers of the teacher network, reducing feature loss between these layers. Empirical experiments demonstrate the effectiveness of our proposed method in classifying histopathology images of benign and malignant breast cancer, achieving excellent results on the BreakHis dataset. These results confirm our method as an effective tool for the classification of benign and malignant breast cancer histopathology images. | H8: Breast cancer; Histopathology; Feature extraction; Self-supervised learning; Computational modeling; Knowledge transfer; Knowledge representation; Knowledge discovery; Contrast resolution; Image classification; Biomedical imaging; Knowledge distillation; contrastive learning; breast cancer histopathology image; global feature; local feature | I8: ATTENTION; STATISTICS | J8: IEEE-INST ELECTRICAL ELECTRONICS ENGINEERS INC | K8: Article | L8: Green Submitted, gold | M8: P | N8: Y
A9: Garg, S; Singh, P | B9: transfer learning based lightweight ensemble model for imbalanced breast cancer classification | C9: 2023 | D9: IEEE-ACM TRANSACTIONS ON COMPUTATIONAL BIOLOGY AND BIOINFORMATICS | E9: 42 | F9: National Institute of Technology (NIT System); National Institute of Technology Raipur | G9: Automated classification of breast cancer can often save lives, as manual detection is usually time-consuming & expensive. Since the last decade, deep learning techniques have been most widely used for the automatic classification of breast cancer using histopathology images. This paper has performed the binary and multi-class classification of breast cancer using a transfer learning-based ensemble model. To analyze the correctness and reliability of the proposed model, we have used an imbalance IDC dataset, an imbalance BreakHis dataset in the binary class scenario, and a balanced BACH dataset for the multi-class classification. A lightweight shallow CNN model with batch normalization technology to accelerate convergence is aggregated with lightweight MobileNetV2 to improve learning and adaptability. The aggregation output is fed into a multilayer perceptron to complete the final classification task. The experimental study on all three datasets was performed and compared with the recent works. We have fine-tuned three different pre-trained models (ResNet50, InceptionV4, and MobilNetV2) and compared it with the proposed lightweight ensemble model in terms of execution time, number of parameters, model size, etc. In both the evaluation phases, it is seen that our model outperforms in all three datasets. | H9: Convolution; Breast cancer; Feature extraction; Computational modeling; Computer architecture; Transfer learning; Deep learning; lightweight model; classification; ensemble | J9: IEEE COMPUTER SOC | K9: Article | M9: {=IFERROR( INDEX(survey_paper_2026!$F:$F, MATCH(LOWER(TRIM(B9)), LOWER(TRIM(survey_paper_2026!$B:$B)),0) ), "New" )} -> P | N9: {=IFERROR( INDEX(survey_paper_2026!$G:$G, MATCH(LOWER(TRIM(B9)), LOWER(TRIM(survey_paper_2026!$B:$B)),0) ), "New" )} -> Y
A10: Maisen, C; Auephanwiriyakul, S; Theera-Umpon, N | B10: learning vector quantization inference classifier in breast abnormality classification | C10: 2018 | D10: JOURNAL OF INTELLIGENT & FUZZY SYSTEMS | E10: 33 | F10: Chiang Mai University; Chiang Mai University; Chiang Mai University; Chiang Mai University | G10: The Mammographic image is a tool for observing breast cancer. Analyzing difficulties include shape, size variety, nearby tissue, and noise. In this paper, we propose a method to classify mammogram abnormalities based on learning vector quantization inference classifier (LVQIC) with fuzzy co-occurrence matrix (FCOM) textural features. The system is implemented on the Mini-MIAS data set with a 5-class problem, i.e., the classification of architectural distortion (AD), spiculated mass (SPIC), calcification (CALC), well-defined/circumscribed masses (CIRC), and normal (NORM). The implementation is also on a 2-class problem consisting of AD-vs-All, SPIC-vs-All, CALC-vs-All, CIRC-vs-All, and NORM/abnormal. The best blind test result is from the 5-class problem with features from fuzzy co-occurrence matrix (FCOM) with 4 clusters, co-occurrence distance d = 2, and 16 prototypes per class. The best classification result is 100% correct classification with 0.03, 0.04, 0.06, and 0.02 false positive rate for AD, SPIC, CALC, and CIRC, respectively. | H10: Mammograms; breast cancer; breast abnormality detection; neuro fuzzy; feature selection | I10: MASS DETECTION; MAMMOGRAMS | J10: IOS PRESS | K10: Article; Proceedings Paper | M10: SA | N10: {=IFERROR( INDEX(survey_paper_2026!$G:$G, MATCH(LOWER(TRIM(B10)), LOWER(TRIM(survey_paper_2026!$B:$B)),0) ), "New" )} -> New
A11: Jiang, L; Zhang, C; Zhang, H; Cao, H | B11: a lightweight spatially-aware classification model for breast cancer pathology images | C11: 2024 | D11: BIOCYBERNETICS AND BIOMEDICAL ENGINEERING | E11: 62 | F11: Shandong University of Traditional Chinese Medicine | G11: Breast cancer is a prevalent malignant tumour with high global incidence. Its diagnosis relies primarily on the analysis of pathological breast images. Owing to the complex organisation of the tumour microenvironment, neural network models are essential as efficient classification tools in the field of pathological image analysis. This study introduced spatially-aware attention swift parallel convolution network (SPA-SPCNet), a lightweight and low-latency model for classifying breast pathologies. A novel module for multi-scale feature extraction was constructed using a depthwise separable convolution method. It focuses on the multi-scale features of pathological images to alleviate recognition problems caused by similar local features in breast cancer tissues. The module concatenates the convolutions of different kernels from three branches. Second, a lightweight dynamic spatially-aware attention module was introduced to integrate the visual graph convolutional architecture in a branch. This allowed the model to capture the spatial structure and relationships in image, enabling better handling of the unique spatial distribution relationship between breast cancer tissue structures. The other branch utilises a self-attention mechanism in the transformer. The module can dynamically adjust the attention of the model to different regions in the image, allowing it to focus on the key features of the complex spatial distribution of breast cancer tissue. This feature fusion method enabled the model to capture both global semantics and local details. Compared with existing lightweight models, the proposed model has advantages in terms of tissue structure classification accuracy, parameter quantity, floating-point operations, and real-time inference speed, providing a powerful tool for computer-aided breast pathological image classification. | H11: Breast cancer classification; Multi-scale features; Graph convolutional network; Feature fusion; Lightweight network | I11: TRANSFORMER | J11: ELSEVIER | K11: Article | M11: P | N11: Y
A12: Kolla, B; Venugopal, P | B12: breast cancer diagnosis through knowledge distillation of swin transformer-based teacher-student models | C12: 2023 | D12: MACHINE LEARNING-SCIENCE AND TECHNOLOGY | E12: 26 | F12: Vellore Institute of Technology (VIT); VIT Vellore | G12: Breast cancer is a significant global health concern, emphasizing the crucial need for a timely and accurate diagnosis to enhance survival rates. Traditional diagnostic methods rely on pathologists analyzing whole-slide images (WSIs) to identify and diagnose malignancies. However, this task is complex, demanding specialized expertise and imposing a substantial workload on pathologists. Additionally, existing deep learning models, commonly employed for classifying histopathology images, often need enhancements to ensure their suitability for real-time deployment on WSI, especially when trained for small regions of interest (ROIs). This article introduces two Swin transformer-based architectures: the teacher model, characterized by its moderate size, and the lightweight student model. Both models are trained using a publicly available dataset of breast cancer histopathology images, focusing on ROIs with varying magnification factors. Transfer learning is applied to train the teacher model, and knowledge distillation (KD) transfers its capabilities to the student model. To enhance validation accuracy and minimize the total loss in KD, we employ the state-action-reward-state-action (SARSA) reinforcement learning algorithm. The algorithm dynamically computes temperature and a weighting factor throughout the KD process to achieve high accuracy within a considerably shorter training timeframe. Additionally, the student model is deployed to analyze malignancies in WSI. Despite the student model being only one-third the size and flops of the teacher model, it achieves an impressive accuracy of 98.71%, slightly below the teacher's accuracy of 98.91%. Experimental results demonstrate that the student model can process WSIs at a throughput of 1.67 samples s-1 with an accuracy of 82%. The proposed student model, trained using KD and the SARSA algorithm, exhibits promising breast cancer classification and WSI analysis performance. These findings indicate its potential for assisting pathologists in diagnosing breast cancer accurately and effectively. | H12: teacher model; student model; Swin-transformers; transfer learning; knowledge distillation; breast cancer histopathology | J12: IOP Publishing Ltd | K12: Article | L12: Green Submitted, gold | M12: P | N12: Y
A13: Ling, DC; Jiao, X | B13: mvkd-trans: a multi-view knowledge distillation vision transformer architecture for breast cancer classification based on ultrasound images | C13: 2025 | D13: ULTRASONIC IMAGING | E13: 38 | F13: Taiyuan University of Technology | G13: Breast cancer is the leading cancer threatening women's health. In recent years, deep neural networks have outperformed traditional methods in terms of both accuracy and efficiency for breast cancer classification. However, most ultrasound-based breast cancer classification methods rely on single-perspective information, which may lead to higher misdiagnosis rates. In this study, we propose a multi-view knowledge distillation vision transformer architecture (MVKD-Trans) for the classification of benign and malignant breast tumors. We utilize multi-view ultrasound images of the same tumor to capture diverse features. Additionally, we employ a shuffle module for feature fusion, extracting channel and spatial dual-attention information to improve the model's representational capability. Given the limited computational capacity of ultrasound devices, we also utilize knowledge distillation (KD) techniques to compress the multi-view network into a single-view network. The results show that the accuracy, area under the ROC curve (AUC), sensitivity, specificity, precision, and F1 score of the model are 88.15%, 91.23%, 81.41%, 90.73%, 78.29%, and 79.69%, respectively. The superior performance of our approach, compared to several existing models, highlights its potential to significantly enhance the understanding and classification of breast cancer. | H13: breast ultrasound; deep learning; knowledge distillation; multi-view learning; medical image analysis | I13: CONVOLUTIONAL NEURAL-NETWORK; FUSION | J13: SAGE PUBLICATIONS INC | K13: Article | M13: NA | N13: new | O13: Not accessible
A14: Sepahvand, M; Abdali-Mohammadi, F | B14: overcoming limitation of dissociation between md and mi classifications of breast cancer histopathological images through a novel decomposed feature-based knowledge distillation method | C14: 2022 | D14: COMPUTERS IN BIOLOGY AND MEDICINE | E14: 42 | F14: Razi University | G14: Magnification-independent (MI) classification is considered a promising method for detecting the histopathological images of breast cancer. However, it has too many parameters for real implementation due to dependence on input images in different magnification factors. In addition, magnification-dependent (MD) classification usually performs poorly on unseen samples, although it has lower input image sizes and fewer parameters. This paper proposes a novel method based on knowledge distillation (KD) to overcome the limitation of dissociation between MI classification and MD classification of breast cancer in histopathological images. The proposed KD method includes a pre-trained MI teacher model that is responsible for training an unprepared MD student model developed through only one magnification factor. In the proposed method, the decomposed feature maps of a teacher's intermediate layers are transferred as dark knowledge to a student. According to the experimental results, the student model developed through 40X images yielded accuracy rates of 99.41%, 99.26%, 99.14%, and 99.09% in response to unseen samples of 40X, 100X, 200X, and 400X images, respectively. Moreover, comparison results indicated the competitive performance of the proposed student model as opposed to the stateof-the-art method based on deep learning on BreakHis. | H14: Breast cancer; Histopathology; BreakHis; Knowledge distillation; Convolutional neural network | I14: DEEP NEURAL-NETWORKS; COMPRESSION; DIAGNOSIS; ALGORITHM | J14: PERGAMON-ELSEVIER SCIENCE LTD | K14: Article | M14: P | N14: Y
A15: Tang, YD; Zhou, DP; Flesch, RCC; Jin, T | B15: a multi-input lightweight convolutional neural network for breast cancer detection considering infrared thermography | C15: 2025 | D15: EXPERT SYSTEMS WITH APPLICATIONS | E15: 37 | F15: Fuzhou University; Universidade Federal de Santa Catarina (UFSC); Fuzhou University | G15: Although deep convolutional neural network (CNN) has been widely used in the breast cancer detection based on thermal imaging technology, this scenario still did not receive enough attention in the mobile devices with limited resource. In addition, there still exists challenge on how to assist front view thermal imaging by side one during breast cancer detection. This study proposes a multi-input lightweight CNN named Multi-light Net in order to achieve more accurate early detection for breast cancer, which combines the thermal image from multiple perspectives with the lightweight CNN on the basis of model performance and scale. In addition, a new weighted label smoothing regularization (WLSR) is proposed for the Multi-light Net with the purpose of increasing the network's generalization ability and classification accuracy. The experimental results demonstrate that the proposed approach by combining front view with side view can achieve more significant results than the common one using only front view during breast cancer detection, and the proposed Multi-light Net also exhibits an excellent performance with respect to the currently popular lightweight CNN. Furthermore, the proposed WLSR loss function can also lead to both faster convergence rate and more stable training process during network training and ultimately higher diagnostic accuracy for breast cancer. | H15: Breast cancer; Thermography; Multi-input; Lightweight; CNN | J15: PERGAMON-ELSEVIER SCIENCE LTD | K15: Article | M15: {=IFERROR( INDEX(survey_paper_2026!$F:$F, MATCH(LOWER(TRIM(B15)), LOWER(TRIM(survey_paper_2026!$B:$B)),0) ), "New" )} -> P | N15: {=IFERROR( INDEX(survey_paper_2026!$G:$G, MATCH(LOWER(TRIM(B15)), LOWER(TRIM(survey_paper_2026!$B:$B)),0) ), "New" )} -> Y
A16: Modu, F; Prasad, R; Aliyu, F | B16: lightweight cnn for resource-constrained bcd system using knowledge distillation | C16: 2025 | D16: IEEE ACCESS | E16: 94 | F16: African University of Science & Technology; King Fahd University of Petroleum & Minerals | G16: Breast cancer (BC) remains a leading cause of mortality among women worldwide, with over two million new cases annually. Early detection improves survival rates significantly, yet resource limitations in low- and middle-income countries (LMICs) hinder access to advanced diagnostic tools. While deep learning (DL) models have shown high accuracy in breast cancer detection (BCD), their computational complexity and hardware requirements make them impractical for deployment on low-power devices. To address this, we propose a lightweight convolutional neural network (CNN) for BCD, leveraging knowledge distillation (KD) to transfer knowledge from a complex teacher model (TM) to a smaller student model (SM). Our approach achieves up to 99.3% accuracy, 100% precision, and 99% recall while reducing the number of trainable parameters by 87% compared to conventional deep models. The proposed model successfully runs on a Raspberry Pi 4B with an inference time of 500 ms and memory usage of just 12% (of 8GB RAM), demonstrating its suitability for telemedicine and mobile diagnostics. Additionally, resource utilization experiments confirm that inference remains stable at 10% CPU usage and 40 degrees C when using a heat sink and fan, ensuring sustained deployment. Future work will explore federated learning for decentralized training, integration of multimodal data for enhanced diagnosis, and cloud-based model updates using delay-tolerant networks (DTNs) for remote healthcare applications. | H16: Computational modeling; Breast cancer; Convolutional neural networks; Accuracy; Medical services; Knowledge engineering; Internet of Things; Hardware; Deep learning; Data models; convolutional neural network; deep learning; Keras; knowledge distillation; teacher-student model; SDG3 | I16: BREAST-CANCER | J16: IEEE-INST ELECTRICAL ELECTRONICS ENGINEERS INC | K16: Article | L16: Green Submitted, gold | M16: {=IFERROR( INDEX(survey_paper_2026!$F:$F, MATCH(LOWER(TRIM(B16)), LOWER(TRIM(survey_paper_2026!$B:$B)),0) ), "New" )} -> P | N16: {=IFERROR( INDEX(survey_paper_2026!$G:$G, MATCH(LOWER(TRIM(B16)), LOWER(TRIM(survey_paper_2026!$B:$B)),0) ), "New" )} -> Y
A17: Ma, XY; Sun, L; Gao, JP; Dong, YM | B17: lmcnet: a lightweight and efficient model for multi-classification of breast cancer images | C17: 2025 | D17: SIGNAL IMAGE AND VIDEO PROCESSING | E17: 35 | F17: Hebei University of Economics & Business | G17: Breast cancer is currently one of the most common cancers among women worldwide. Computer-aided diagnosis (CAD) is crucial in reducing diagnostic costs and improving subsequent cancer treatment. Convolutional neural networks are widely used in CAD, but most existing models are high-complexity and multi-parameter architectures, which limits their practical application. To address this issue, this paper proposes LMCNet, a lightweight breast cancer multi-classification model. LMCNet reduces the model complexity by refactoring the basic units of ShuffleNetV2, introducing PAConv parallel convolution layers and combining depthwise separable convolution. In order to further improve the feature extraction ability of the model, an SAE attention module containing channel and spatial dimensions is introduced. The proposed model achieves high recognition accuracy with low resource consumption. Our method requires only 275.69 K parameters and 51.19 M FLOPs. Compared to ShuffleNetV2, LMCNet reduces parameters by approximately 78.63% and FLOPs by 66.18%. Compared with other classical models, the proposed model achieves the best recognition efficiency and the fastest inference speed. | H17: Breast cancer; Medical image classification; Lightweight CNN; ShuffleNetV2 | J17: SPRINGER LONDON LTD | K17: Article | M17: P | N17: Y
A18: Kumar, A; Sharma, A; Bharti, V; Singh, AK; Singh, SK; Saxena, S | B18: mobihisnet: a lightweight cnn in mobile edge computing for histopathological image classification | C18: 2021 | D18: IEEE INTERNET OF THINGS JOURNAL | E18: 43 | F18: Indian Institute of Technology System (IIT System); Indian Institute of Technology BHU Varanasi (IIT BHU Varanasi); National Institute of Technology (NIT System); National Institute of Technology Patna; Indian Council of Agricultural Research (ICAR); ICAR - Indian Veterinary Research Institute | G18: Recent advances in artificial intelligence (AI), especially convolutional neural networks (CNNs), alongside the digitization of histopathological images, have made the computer-aided diagnosis of breast cancer a reality. However, deep learning-based approaches are computationally expensive and have huge parameters, which makes them less affordable for edge devices. In order to make them affordable for edge devices, the whole classification model needs to be compressed while maintaining accuracy. Providing a low-cost solution for histopathological diagnosis in the recent edge-computing world is of utmost importance. Therefore, in this study, we propose MobiHisNet, an efficient and lightweight CNN model for histopathological image classification (HIC) based on MobileNet. MobiHisNet was successfully deployed on a Raspberry Pi, as well as three mobile devices, demonstrating its ability to run on a lightweight and portable processor. Our studies indicated that a depth parameter (gamma = 0.5) and a 16-bit quantization are the optimum parameters for the proposed model while balancing the accuracy, inference time, and memory peak requirements. Compared to the state-of-the-art, pretrained models, MobiHisNet has fewer parameters and calculations, resulting in faster image classification. This renders it more viable for production purposes and applications on edge devices. In addition, MobiHisNet is computationally faster than VGG16, ResNet50, Xception, and InceptionV3 by twenty-seven, eight, six, and five times, respectively. This also outperforms all the baseline models with the moderate model size and FLOP counts. Experiments on breast cancer HIC (BreakHis) data sets show superior performance of MobiHisNet on edge devices in terms of higher accuracy, lesser complexity, and lesser memory requirements. Thus, it has a high potential for deployment in mobile edge devices. | H18: Edge computing; histopathological classification; Internet of Everything (IoE); lightweight convolutional neural network (CNN); quantization | J18: IEEE-INST ELECTRICAL ELECTRONICS ENGINEERS INC | K18: Article | M18: P | N18: Y
A19: Liu, Y; Li, HP; Zhu, Z; Chen, C; Zhang, XJ; Jin, GS; Li, HT | B19: rsdcnet: an efficient and lightweight deep learning model for benign and malignant pathology detection in breast cancer | C19: 2025 | D19: DIGITAL HEALTH | E19: 29 | F19: Bengbu Medical University; Bengbu Medical University; Bengbu Medical University | G19: Background Breast cancer is a leading malignant tumor among women globally, with its pathological classification into benign or malignant directly influencing treatment strategies and prognosis. Traditional diagnostic methods, reliant on manual interpretation, are not only time-intensive and subjective but also susceptible to variability based on the pathologist's expertise and workload. Consequently, the development of an efficient, automated, and precise pathological detection method is crucial.Methods This study introduces RSDCNet, an enhanced lightweight neural network architecture designed for the automatic detection of benign and malignant breast cancer pathology. Utilizing the BreakHis dataset, which comprises 9109 microscopic images of breast tumors including various differentiation levels of benign and malignant samples, RSDCNet integrates depthwise separable convolution and SCSE modules. This integration aims to reduce model parameters while enhancing key feature extraction capabilities, thereby achieving both lightweight design and high efficiency.Results RSDCNet demonstrated superior performance across multiple evaluation metrics in the classification task. The model achieved an accuracy of 0.9903, a recall of 0.9897, an F1 score of 0.9888, and a precision of 0.9879, outperforming established deep learning models such as EfficientNet, RegNet, HRNet, and ViT. Notably, RSDCNet's parameter count stood at just 1,199,662, significantly lower than HRNet's 19,254,102 and ViT's 85,800,194, highlighting its enhanced resource efficiency.Conclusion The RSDCNet model presented in this study excels in the efficient and accurate classification of benign and malignant breast cancer pathology. Compared to traditional methods and other leading models, RSDCNet not only reduces computational resource consumption but also offers improved feature extraction and clinical interpretability. This advancement provides substantial technical support for the intelligent diagnosis of breast cancer, paving the way for more effective treatment planning and prognosis assessment. | H19: Breast cancer; pathological image; benign and malignant detection; deep learning; lightweight | J19: SAGE PUBLICATIONS LTD | K19: Article | L19: Green Submitted, gold | M19: {=IFERROR( INDEX(survey_paper_2026!$F:$F, MATCH(LOWER(TRIM(B19)), LOWER(TRIM(survey_paper_2026!$B:$B)),0) ), "New" )} -> P | N19: {=IFERROR( INDEX(survey_paper_2026!$G:$G, MATCH(LOWER(TRIM(B19)), LOWER(TRIM(survey_paper_2026!$B:$B)),0) ), "New" )} -> Y
A20: Chen, ZY; Zeng, XH; Cheng, K; Hong, Y; Liu, Y; Fang, R; Liao, CS; Plain, J | B20: a lightweight multi-scale efficient model for breast cancer detection and classification in mammograms | C20: 2025 | D20: NEURAL INFORMATION PROCESSING, ICONIP 2024, PT IV | E20: 25 | F20: Fudan University; Fudan University; Fudan University; Centre National de la Recherche Scientifique (CNRS); Universite de Technologie de Troyes | G20: Early detection and classification of breast tumors via mammographic images are critical for reducing mortality rates. We introduce a lightweight and efficient tumor detection model built on an enhanced YOLOv8 framework to support diagnosis. Firstly, we introduce a multi-scale lightweight convolution module named MSLConv. We further integrate batch normalization and the SILU activation function to create a comprehensive convolutional module called MSLCBS. To further enhance the model, we have restructured the detection head to substantially decrease the parameter count in this segment of the network. Additionally, to capture subtle features such as microcalcifications and irregular textures, we incorporate Focal Modulation to improve feature fusion capabilities. This approach aggregates and interacts with contextual information in a lightweight manner. Considering the diversity in the shape, texture, and size of breast tumors, we introduce WISE-IOU, a bounding box regression scheme to enhance the model's generalization capability. All of the extensive experiments on CBIS-DDSM and INBREAST datasets have proven that our method achieves the highest mAP50 score with the fewest parameters and computational load, which validate its reliability. | H20: Mammograms; Breast cancer; Mass detection; Computer aided detection | J20: SPRINGER-VERLAG SINGAPORE PTE LTD | K20: Proceedings Paper | M20: {=IFERROR( INDEX(survey_paper_2026!$F:$F, MATCH(LOWER(TRIM(B20)), LOWER(TRIM(survey_paper_2026!$B:$B)),0) ), "New" )} -> P | N20: {=IFERROR( INDEX(survey_paper_2026!$G:$G, MATCH(LOWER(TRIM(B20)), LOWER(TRIM(survey_paper_2026!$B:$B)),0) ), "New" )} -> Y
A21: Maisen, C; Auephanwiriyakul, S; Theera-Umpon, N | B21: a novel learning vector quantization inference classifier | C21: 2017 | D21: INTELLIGENT INFORMATION AND DATABASE SYSTEMS, ACIIDS 2017, PT I | E21: 35 | F21: Chiang Mai University; Chiang Mai University; Chiang Mai University; Chiang Mai University | G21: One of the popular tools in pattern recognition is a neuro-fuzzy system. Most of the neuro-fuzzy systems are based on a multi-layer perceptrons. In this paper, we incorporate learning vector quantization in a neuro-fuzzy system. The prototype update equation is based on the learning vector quantization while the gradient descent technique is used in the weight update equation. Since weights contain informative information, they are exploited to select a good feature set. There are 8 data sets used in the experiment, i.e., Iris Plants, Wisconsin Breast Cancer (WBC), Pima Indians Diabetes, Wine, Ionosphere, Colon Tumor, Diffuse Large B-Cell Lymphoma (DLBCL), and Glioma Tumor (GLI_85). The results show that our algorithm provides good classification rates on all data sets. It is able to select a good feature set with a small number of features. We compare our results indirectly with the existing algorithms as well. The comparison result shows that our algorithm performs better than those existing ones. | H21: Neuro-fuzzy classifier; Learning vector quantization; Prototype-based rule; Rule extraction; Feature selection | I21: FEATURE-SELECTION; FUZZY; SYSTEMS | J21: SPRINGER INTERNATIONAL PUBLISHING AG | K21: Proceedings Paper | M21: SA | N21: {=IFERROR( INDEX(survey_paper_2026!$G:$G, MATCH(LOWER(TRIM(B21)), LOWER(TRIM(survey_paper_2026!$B:$B)),0) ), "New" )} -> New
A22: Raiaan, MAK; Fahad, NM; Mukta, MSH; Shatabda, S | B22: mammo-light: a lightweight convolutional neural network for diagnosing breast cancer from mammography images | C22: 2024 | D22: BIOMEDICAL SIGNAL PROCESSING AND CONTROL | E22: 67 | F22: United International University (UIU); Lappeenranta-Lahti University of Technology LUT | G22: People of all countries, developed and developing alike endure cancer-related fatal diseases. The rate of breast cancer in females is increasing daily, partly due to ignorance and misdiagnosis in the early stages. Diagnosis of breast cancer accurately during its earlier stages of development can result in proper initial treatment for breast cancer. Artificial intelligence can aid in the acceleration and automation of breast cancer detection. Deep learning is decisive in effectively recognizing and classifying cancer on large datasets of medical images. In this paper, we propose a novel computer-aided classification approach, Mammo-Light for breast cancer prediction. Preprocessing strategies have been utilized to eradicate the noise and enhance mammogram lesions. Photometric augmentation techniques adapted to the preprocessed classes to balance and increase the size of the dataset. After that, a lightweight yet intuitive convolutional neural network is applied to classify breast cancer on the publicly available dataset CBIS-DDSM. For further validation of the proposed approach, we have used the MIAS dataset. Mammo-Light attained a 99.17% and 98.42% test accuracy respectively for CBISDDSM and MIAS datasets and outperformed state-of-the-art methods in terms of accuracy and other metrics. Due to being the lightweight model, Mammo-Light performs exceptionally well with fewer parameters and computational time, which can potentially contribute to the field of breast cancer early diagnosis and enable fast treatment. | H22: Mammograms; Image preprocessing; Breast cancer classification; Data augmentation; Lightweight CNN; Transfer learning models | I22: CLASSIFICATION; SEGMENTATION; SYSTEM; MODEL; CNN | J22: ELSEVIER SCI LTD | K22: Article | M22: {=IFERROR( INDEX(survey_paper_2026!$F:$F, MATCH(LOWER(TRIM(B22)), LOWER(TRIM(survey_paper_2026!$B:$B)),0) ), "New" )} -> P | N22: {=IFERROR( INDEX(survey_paper_2026!$G:$G, MATCH(LOWER(TRIM(B22)), LOWER(TRIM(survey_paper_2026!$B:$B)),0) ), "New" )} -> Y
A23: Choudhary, T; Mishra, V; Goswami, A; Sarangapani, J | B23: a transfer learning with structured filter pruning approach for improved breast cancer classification on point-of-care devices | C23: 2021 | D23: COMPUTERS IN BIOLOGY AND MEDICINE | E23: 58 | F23: University of Missouri System; Missouri University of Science & Technology | G23: Background and objective: A significant progress has been made in automated medical diagnosis with the advent of deep learning methods in recent years. However, deploying a deep learning model for mobile and small-scale, low-cost devices is a major bottleneck. Further, breast cancer is more prevalent currently, and ductal carcinoma being its most common type. Although many machine/deep learning methods have already been investigated, still, there is a need for further improvement. Method: This paper proposes a novel deep convolutional neural network (CNN) based transfer learning approach complemented with structured filter pruning for histopathological image classification, and to bring down the run-time resource requirement of the trained deep learning models. In the proposed method, first, the less important filters are pruned from the convolutional layers and then the pruned models are trained on the histopathological image dataset. Results: We performed extensive experiments using three popular pre-trained CNNs, VGG19, ResNet34, and ResNet50. With VGG19 pruned model, we achieved an accuracy of 91.25% outperforming earlier methods on the same dataset and architecture while reducing 63.46% FLOPs. Whereas, with the ResNet34 pruned model, the accuracy increases to 91.80% with 40.63% fewer FLOPs. Moreover, with the ResNet50 model, we achieved an accuracy of 92.07% with 30.97% less FLOPs. Conclusion: The experimental results reveal that the pre-trained model's performance complemented with filter pruning exceeds original pre-trained models. Another important outcome of the research is that the pruned model with reduced resource requirements can be deployed in point-of-care devices for automated diagnosis applications with ease. | H23: Breast cancer; Invasive ductal carcinoma; Efficient inference; Convolutional neural network; Filter pruning | I23: IMAGE CLASSIFICATION; NEURAL-NETWORK | J23: PERGAMON-ELSEVIER SCIENCE LTD | K23: Article | M23: P | N23: Y
A24: Yan, CX; Zeng, XY; Xi, R; Ahmed, A; Hou, MS; Tunio, MH | B24: pla-a privacy-embedded lightweight and efficient automated breast cancer accurate diagnosis framework for the internet of medical things | C24: 2023 | D24: ELECTRONICS | E24: 55 | F24: University of Electronic Science & Technology of China; Chengdu Technological University | G24: The Internet of Medical Things (IoMT) can automate breast tumor detection and classification with the potential of artificial intelligence. However, the leakage of sensitive data can cause harm to patients. To address this issue, this study proposed an intrauterine breast cancer diagnosis method, namely Privacy-Embedded Lightweight and Efficient Automated (PLA), for IoMT, which represents an approach that combines privacy-preserving techniques, efficiency, and automation to achieve our goals. Firstly, our model is designed to achieve lightweight classification prediction and global information processing of breast cancer by utilizing an advanced IoMT-friendly ViT backbone. Secondly, PLA protects patients' privacy by federated learning, taking the classification task of breast cancer as the main task and introducing the texture analysis task of breast cancer images as the auxiliary task to train the model. For our PLA framework, the classification accuracy is 0.953, the recall rate is 0.998 for the best, the F1 value is 0.969, the precision value is 0.988, and the classification time is 61.9 ms. The experimental results show that the PLA model performs better than all of the comparison methods in terms of accuracy, with an improvement of more than 0.5%. Furthermore, our proposed model demonstrates significant advantages over the comparison methods regarding time and memory. | H24: PLA; privacy-embedded; federated learning; breast cancer classification; Internet of Medical Things; lightweight | I24: DEEP; CLASSIFICATION | J24: MDPI | K24: Article | L24: gold | M24: P | N24: Y
A25: Oliveira, HS; Teixeira, JF; Oliveira, HP | B25: lightweight deep learning pipeline for detection, segmentation and classification of breast cancer anomalies | C25: 2019 | D25: IMAGE ANALYSIS AND PROCESSING - ICIAP 2019, PT II | E25: 11 | F25: Universidade do Porto; Universidade do Porto; INESC TEC | G25: The small amount of public available medical images hinders the use of deep learning techniques for mammogram automatic diagnosis. Deep learning methods require large annotated training sets to be effective, however medical datasets are costly to obtain and suffer from large variability. In this work, a lightweight deep learning pipeline to detect, segment and classify anomalies in mammogram images is presented. First, data augmentation using the ground-truth annotation is performed and used by a cascade segmentation and classification methods. Results are obtained using the INbreast public database in the context of lesion detection and BI-RADS classification. Moreover, a pre-trained Convolutional Neural Network using ResNet50 is modified to generate the lesion regions proposals followed by a false positive reduction and contour refinement stages while a pre-trained VGG16 network is fine-tuned to classify mammograms. The detection and segmentation stage results show that the cascade configuration achieves a DICE of 0.83 without massive training while the multi-class classification exhibits an MAE of 0.58 with data augmentation. | H25: Lesion detection; Segmentation; Classification; Deep learning | I25: MASSES | J25: SPRINGER INTERNATIONAL PUBLISHING AG | K25: Proceedings Paper | M25: {=IFERROR( INDEX(survey_paper_2026!$F:$F, MATCH(LOWER(TRIM(B25)), LOWER(TRIM(survey_paper_2026!$B:$B)),0) ), "New" )} -> P | N25: {=IFERROR( INDEX(survey_paper_2026!$G:$G, MATCH(LOWER(TRIM(B25)), LOWER(TRIM(survey_paper_2026!$B:$B)),0) ), "New" )} -> Y
A26: Zhu, C; Song, FZ; Wang, Y; Dong, HH; Guo, Y; Liu, J | B26: breast cancer histopathology image classification through assembling multiple compact cnns | C26: 2019 | D26: BMC MEDICAL INFORMATICS AND DECISION MAKING | E26: 37 | F26: Beijing University of Posts & Telecommunications; Capital Medical University | G26: Background Breast cancer causes hundreds of thousands of deaths each year worldwide. The early stage diagnosis and treatment can significantly reduce the mortality rate. However, the traditional manual diagnosis needs intense workload, and diagnostic errors are prone to happen with the prolonged work of pathologists. Automatic histopathology image recognition plays a key role in speeding up diagnosis and improving the quality of diagnosis. Methods In this work, we propose a breast cancer histopathology image classification by assembling multiple compact Convolutional Neural Networks (CNNs). First, a hybrid CNN architecture is designed, which contains a global model branch and a local model branch. By local voting and two-branch information merging, our hybrid model obtains stronger representation ability. Second, by embedding the proposed Squeeze-Excitation-Pruning (SEP) block into our hybrid model, the channel importance can be learned and the redundant channels are thus removed. The proposed channel pruning scheme can decrease the risk of overfitting and produce higher accuracy with the same model size. At last, with different data partition and composition, we build multiple models and assemble them together to further enhance the model generalization ability. Results Experimental results show that in public BreaKHis dataset, our proposed hybrid model achieves comparable performance with the state-of-the-art. By adopting the multi-model assembling scheme, our method outperforms the state-of-the-art in both patient level and image level accuracy for BACH dataset. Conclusions We propose a novel compact breast cancer histopathology image classification scheme by assembling multiple compact hybrid CNNs. The proposed scheme achieves promising results for the breast cancer image classification task. Our method can be used in breast cancer auxiliary diagnostic scenario, and it can reduce the workload of pathologists as well as improve the quality of diagnosis. | H26: Breast cancer; Channel pruning; Histopathology; Hybrid CNN | I26: DIAGNOSIS | J26: BMC | K26: Article | L26: Green Submitted, gold | M26: P | N26: Y
A27: Chi, TN; Thu, HL; Quang, TD; Taniar, D | B27: a lightweight method for breast cancer detection using thermography images with optimized cnn feature and efficient classification | C27: 2025 | D27: JOURNAL OF IMAGING INFORMATICS IN MEDICINE | E27: 41 | F27: Vietnam Academy of Science & Technology (VAST); Monash University; FPT University | G27: Breast cancer is a prominent cause of death among women worldwide. Infrared thermography, due to its cost-effectiveness and non-ionizing radiation, has emerged as a promising tool for early breast cancer diagnosis. This article presents a hybrid model approach for breast cancer detection using thermography images, designed to process and classify these images into healthy or cancerous categories, thus supporting disease diagnosis. Multiple pre-trained convolutional neural networks are employed for image feature extraction, and feature filter methods are proposed for feature selection, with diverse classifiers utilized for image classification. Evaluating the DRM-IR test set revealed that the combination of ResNet34, Chi-square (chi 2\documentclass[12pt]{minimal} \usepackage{amsmath} \usepackage{wasysym} \usepackage{amsfonts} \usepackage{amssymb} \usepackage{amsbsy} \usepackage{mathrsfs} \usepackage{upgreek} \setlength{\oddsidemargin}{-69pt} \begin{document}$$\varvec{\chi }<^>{\varvec{2}}$$\end{document}) filter, and SVM classifier demonstrated superior performance, achieving the highest accuracy at 99.62%\documentclass[12pt]{minimal} \usepackage{amsmath} \usepackage{wasysym} \usepackage{amsfonts} \usepackage{amssymb} \usepackage{amsbsy} \usepackage{mathrsfs} \usepackage{upgreek} \setlength{\oddsidemargin}{-69pt} \begin{document}$$\varvec{99.62\%}$$\end{document}. Furthermore, the highest accuracy improvement obtained was 18.3%\documentclass[12pt]{minimal} \usepackage{amsmath} \usepackage{wasysym} \usepackage{amsfonts} \usepackage{amssymb} \usepackage{amsbsy} \usepackage{mathrsfs} \usepackage{upgreek} \setlength{\oddsidemargin}{-69pt} \begin{document}$$\varvec{18.3\%}$$\end{document} when using the SVM classifier and Chi-square filter compared to regular convolutional neural networks. The results confirmed that the proposed method, with its high accuracy and lightweight model, outperforms state-of-the-art breast cancer detection from thermography image methods, making it a good choice for computer-aided diagnosis. | H27: Breast cancer; Breast thermal image; CNN feature exactor; Feature optimization; Classifiers | J27: SPRINGER | K27: Article | L27: Green Accepted | M27: {=IFERROR( INDEX(survey_paper_2026!$F:$F, MATCH(LOWER(TRIM(B27)), LOWER(TRIM(survey_paper_2026!$B:$B)),0) ), "New" )} -> P | N27: {=IFERROR( INDEX(survey_paper_2026!$G:$G, MATCH(LOWER(TRIM(B27)), LOWER(TRIM(survey_paper_2026!$B:$B)),0) ), "New" )} -> Y
A28: Agrawal, K; Borthakur, A; Singh, AK; Srikaran, P; Nandi, D; Pujari, O | B28: neural decision tree for bio-tinyml | C28: 2024 | D28: 2024 IEEE BIOMEDICAL CIRCUITS AND SYSTEMS CONFERENCE, BIOCAS 2024 | E28: 14 | F28: Indian Institute of Technology System (IIT System); Indian Institute of Technology (IIT) - Guwahati; Indian Institute of Technology System (IIT System); Indian Institute of Technology (IIT) - Hyderabad | G28: Deep neural networks(NN) are widely popular candidates for introducing machine learning in resource-constrained devices(tinyML). However, NNs in tinyML applications come with constraints such as high memory footprint and power consumption. Another popular candidate is decision trees (DT), which are lightweight, but in DT - choosing the tree depth, the best feature, and the threshold for subsetting data is not end-to-end as in parameter tuning of NNs. Hence, we here design a Neural Decision Tree (NDT), which can be trained using backpropagation in an end-to-end fashion and is simultaneously lightweight. We evaluate NDT for potential healthcare applications in Epileptic Seizure, Cervical Cancer, Breast Cancer, Parkinson's, and Heart Disease Detection. Careful studies reveal that NDT performs at par with NNs but is computationally simpler with fewer neurons and with a hugely reduced number of multiply-accumulate operations(MACs). In addition, we propose methods for interpreting NDT behavior. Moreover, we perform systematic ablation studies on NDT to justify the design choices. | H28: tinyML; Low power; Deep Learning; Decision Tree; Healthcare | J28: IEEE | K28: Proceedings Paper | M28: SA
A29: Ahmmed, J; Ahmed, F; Kabir, MA; Ahad, MT; Jadoon, MA; Rehman, AU; Bermak, A | B29: lbnet: an optimized lightweight cnn for mammographic breast cancer classification with xai-based interpretability | C29: 2025 | D29: SCIENTIFIC REPORTS | E29: 50 | F29: Daffodil International University; Daffodil International University; Independent University Bangladesh (IUB); Qatar Foundation (QF); Hamad Bin Khalifa University-Qatar; Qatar Foundation (QF); Hamad Bin Khalifa University-Qatar | G29: Breast cancer represents a major worldwide health burden, marked by high incidence and mortality rates across diverse socioeconomic populations. While deep learning has enabled advances in automated mammographic analysis, existing models often suffer from high computational complexity. They also face limited generalizability and a lack of interpretability. To overcome these challenges, this research introduces LBNet, a lightweight and interpretable convolutional neural network (CNN) built for accurate and efficient breast cancer detection, particularly in resource-constrained settings. With only 2.4 million trainable parameters, LBNet consists of five convolutional layers, leveraging ReLU activation, batch normalization, and max-pooling to optimize feature extraction while maintaining computational efficiency. LBNet was trained on the RSNA dataset using the Adam optimizer and five-fold cross-validation. It achieved 97.28% accuracy. For cancer cases, precision was 99% and recall was 96%. For non-cancer cases, precision was 96% and recall was 99%. In comparison, baseline models such as VGG19, SE-ResNet152, and ResNet152V2 yielded lower accuracies of 87.54%, 87.50%, and 85.24%, respectively, while transfer learning approaches peaked at 87.37% accuracy. LBNet's generalizability was validated in external datasets, achieving 99.54% accuracy on CBIS-DDSM and 98.50% on MIAS. To enhance clinical trust, this work integrated SHAP (SHapley Additive exPlanations) and Grad-CAM (Gradient-weighted Class Activation Mapping). These methods effectively highlighted diagnostically relevant regions in mammograms. This improved prediction transparency. LBNet demonstrates strong potential as an accurate, efficient, and interpretable solution for breast cancer screening, and future studies could explore its extension to multi-view mammography and real-time clinical deployment. | H29: Breast cancer; Mammography; Lightweight CNN; Explainable AI; SHAP; Grad-CAM; Transfer learning | J29: NATURE PORTFOLIO | K29: Article | L29: Green Submitted, gold | M29: P | N29: Y
A30: Sanghavi, F; Kezebou, L; Panetta, K; Agaian, S | B30: breast cancer classification using parametric free thresholding adjacency statistics based fibonacci patterns | C30: 2020 | D30: MOBILE MULTIMEDIA/IMAGE PROCESSING, SECURITY, AND APPLICATIONS 2020 | E30: 50 | F30: Tufts University; City University of New York (CUNY) System | G30: According to the American cancer society, the average risk of women getting diagnosed with breast cancer during their life is 13%. The World Health Organization also reports that the number of cancer cases is projected to rise to 19.3 million by 2025. Recent research works point out that physicians can only diagnose cancer with 79% accuracy while machine learning procedures achieve 91% accuracy or more. The current challenges are early cancer detection and the efficient and accurate diagnosis of histopathology tissue samples. Several Deep Learning breast cancer classification models have been developed to assist medical practitioners. However, these methods are data hungry and require thousands of training image samples, often coupled with data augmentation to achieve satisfactory results with long training hours. In this paper, we propose a machine learning classification model by integrating the Parameter free Thresholding Adjacency Statistics (PFTAS) with Fibonacci-p patterns for breast cancer detection. Computer simulations on BreakHis cancer datasets in comparison to other machine learning and deep learning-based methods show that (i) the presented method helps eliminate dependence on large training data and data augmentation. (ii) robustness to noise and background stains, and (iii) lightweight model easy to train and deploy. | H30: Breast cancer; cancer detection; Fibonacci; machine learning fir cancer classification; BreakHis | I30: BINARY PATTERN; MULTICLASS | J30: SPIE-INT SOC OPTICAL ENGINEERING | K30: Proceedings Paper | M30: {=IFERROR( INDEX(survey_paper_2026!$F:$F, MATCH(LOWER(TRIM(B30)), LOWER(TRIM(survey_paper_2026!$B:$B)),0) ), "New" )} -> P | N30: {=IFERROR( INDEX(survey_paper_2026!$G:$G, MATCH(LOWER(TRIM(B30)), LOWER(TRIM(survey_paper_2026!$B:$B)),0) ), "New" )} -> Y
A31: Addo, D; Zhou, SJ; Sarpong, K; Nartey, OT; Abdullah, MA; Ukwuoma, CC; Al-antari, MA | B31: a hybrid lightweight breast cancer classification framework using the histopathological images | C31: 2024 | D31: BIOCYBERNETICS AND BIOMEDICAL ENGINEERING | E31: 103 | F31: University of Electronic Science & Technology of China; Chengdu University of Technology; Sejong University | G31: A crucial element in the diagnosis of breast cancer is the utilization of a classification method that is efficient, lightweight, and precise. Convolutional neural networks (CNNs) have garnered attention as a viable approach for classifying histopathological images. However, deeper and wider models tend to rely on first-order statistics, demanding substantial computational resources and struggling with fixed kernel dimensions that limit encompassing diverse resolution data, thereby degrading the model's performance during testing. This study introduces BCHI-CovNet, a novel lightweight artificial intelligence (AI) model for histopathological breast image classifi-cation. Firstly, a novel multiscale depth-wise separable convolution is proposed. It is introduced to split input tensors into distinct tensor fragments, each subject to unique kernel sizes integrating various kernel sizes within one depth-wise convolution to capture both low-and high-resolution patterns. Secondly, an additional pooling module is introduced to capture extensive second-order statistical information across the channels and spatial dimensions. This module works in tandem with an innovative multi-head self-attention mechanism to capture the long-range pixels contributing significantly to the learning process, yielding distinctive and discriminative features that further enrich representation and introduce pixel diversity during training. These novel designs substantially reduce computational complexities regarding model parameters and FLOPs, which is crucial for resource-constrained medical devices. The outcomes achieved by employing the suggested model on two openly accessible datasets for breast cancer histopathological images reveal noteworthy performance. Specifically, the proposed approach attains high levels of accuracy: 99.15 % at 40x magnification, 99.08 % at 100x magnification, 99.22 % at 200x magnification, and 98.87 % at 400x magnification on the BreaKHis dataset. Additionally, it achieves an accuracy of 99.38 % on the BACH dataset. These results highlight the exceptional effectiveness and practical promise of BCHI-CovNet for the classification of breast cancer histopathological images. | H31: Breast cancer; Histopathological images; Depth-wise separable convolutional network; Second-order pooling module; Visual explainable saliency maps | I31: CONVOLUTION; MAMMOGRAMS; DIAGNOSIS; ATTENTION; ALGORITHM; SYSTEM | J31: ELSEVIER | K31: Article | M31: P | N31: Y
A32: Vinod, A; Guddati, P; Panda, AK; Tripathy, RK | B32: a lightweight deep convolutional neural network implemented on fpga and android devices for detection of breast cancer using ultrasound images | C32: 2024 | D32: IEEE ACCESS | E32: 45 | F32: Birla Institute of Technology & Science Pilani (BITS Pilani) | G32: Breast cancer (BC) continues to be the primary cause of high mortality rates among women globally. Early and automated detection of this disease plays a significant role in clinical standards for better diagnosis and improved survival rates. Ultrasonography is a widely used non-invasive imaging test to diagnose BC. The traditional ultrasound-based automated diagnostic systems for detecting BC rely on cloud-based processing, which has high latency, requires constant internet connectivity, and raises the privacy of patient's ultrasound image data. This paper proposes a lightweight deep convolutional neural network (LWDCNN) implemented on edge devices (field programmable gate array (FPGA) and android devices) for real-time detection of BC using breast ultrasound (BUS) images. FPGA is used due to its parallel processing capability, low latency, and low power for the real-time processing of BUS images. Similarly, the Android device provides portability and a user-friendly system to process BUS images for automated detection of BC. The proposed LWDCNN is trained on the Google Cloud CPU-based framework to obtain the optimized model with weight and bias parameters. The compression methods (pruning and fixed-point precision-based representation of weight values) are applied to the LWDCNN model, and the inference of this model is performed on Android and PYNQ-Z2 FPGA-based edge devices to detect malignant tumor classes using BUS images. The proposed approach is evaluated using BUS images from Kaggle and breast ultrasound imaging databases. The experimental results reveal that the LWDCNN achieved average accuracy values of 94.15% on Google Cloud CPU and 93.16% on FPGA-based edge devices for detecting malignant tumors in the inference phase using hold-out validation. Similarly, the post-training quantization of LWDCNN with an integer 8-bit (INT8) case implemented on an Android device has yielded an accuracy value of 93.76% for detecting malignant tumors using BUS images. The presented deep-learning approach has demonstrated higher classification accuracy than different transfer-learning techniques and existing methods using the BUS images from the same database. | H32: Malignant tumors; Accuracy; Databases; Field programmable gate arrays; Transfer learning; Training; Feature extraction; Convolution; Breast tissue; Image edge detection; Ultrasound images; breast cancer; deep learning; edge computing; FPGA; android | J32: IEEE-INST ELECTRICAL ELECTRONICS ENGINEERS INC | K32: Article | L32: Green Submitted, gold | M32: {=IFERROR( INDEX(survey_paper_2026!$F:$F, MATCH(LOWER(TRIM(B32)), LOWER(TRIM(survey_paper_2026!$B:$B)),0) ), "New" )} -> P | N32: {=IFERROR( INDEX(survey_paper_2026!$G:$G, MATCH(LOWER(TRIM(B32)), LOWER(TRIM(survey_paper_2026!$B:$B)),0) ), "New" )} -> Y
A33: Chen, GB; Xie, XZ | B33: a light weight snp detection algorithm for the breast cancer targeted sequencing data. | C33: 2017 | D33: BIOMEDICAL RESEARCH-INDIA | E33: 30 | F33: Chongqing University of Posts & Telecommunications | G33: Many methods have been developed for Single Nucleotide Polymorphism (SNP) detection, but these methods are based on BWA or Bowtie matching software, because of the existence of this high false positive software, resulting in the test results Incorrect. The sequencing target region covered the entire coding region, exon-intron junction region (20-50 bp) and partial intron region of BRCA1/2 genes, 328 exon, 101.3k regions (http://pan.baidu.com/s/1kVNlWQb). A SNP detection algorithm based on breast cancer target DNA sequencing data is proposed, which has more advantages than Bcftools and IGV, which are the most commonly tools. | H33: SNP; Breast cancer; Sequencing | I33: RISK; ASSOCIATION; MUTATIONS; VARIANTS; PROTEIN | J33: ALLIED ACAD | K33: Article | M33: ST | N33: {=IFERROR( INDEX(survey_paper_2026!$G:$G, MATCH(LOWER(TRIM(B33)), LOWER(TRIM(survey_paper_2026!$B:$B)),0) ), "New" )} -> New
A34: Han, K; Li, ZG; Cai, MJ | B34: yolov9-agma: an enhanced knowledge distillation network for breast ultrasound image classification | C34: 2026 | D34: BIOMEDICAL SIGNAL PROCESSING AND CONTROL | E34: 29 | F34: University of Science & Technology Liaoning | G34: Ultrasound imaging has become one of the primary methods for diagnosing breast cancer in women. The YOLOv9e network, a real-time algorithm balancing speed and accuracy, is widely used in breast imaging analysis requiring efficient processing. However, the YOLOv9e network suffers from a high parameter count and model complexity. To address this, we removed the original model's CBLinear and CBFuse modules, constructing a new lightweight network, YOLOv9-AGMA, to reduce computational resource consumption. Furthermore, this paper proposes a novel module, AGMA (Adaptive Gated Multi-scale Attention Module), to further enhance accuracy. This module dynamically adjusts the adaptive association of features across different scales after channel splitting in the original network. Integrated into the neck layer, it optimizes the feature representation capability for learning global contextual semantic information across spaces, thereby reducing information loss caused by unreasonable channel combinations and further improving precision. Secondly, a dense prediction-based Channel-Wise Knowledge Distillation (CWD) method is employed to enhance the model's robustness to noise, enabling the student network to learn key feature knowledge from the lesion foreground regions of the teacher network. Subsequently, the LayerCAM method is used for model introspection, enhancing the interpretability of AGMA's ability to precisely locate sensitive regions. Experimental results show that the model's precision is improved by 9.9%, while the proposed architecture has only 3.17% of the original model's parameter size and 3.81% of its model complexity, significantly reducing computational demands. | H34: Ultrasound imaging; Feature correlation; Channel-wise knowledge distillation | J34: ELSEVIER SCI LTD | K34: Article | M34: {=IFERROR( INDEX(survey_paper_2026!$F:$F, MATCH(LOWER(TRIM(B34)), LOWER(TRIM(survey_paper_2026!$B:$B)),0) ), "New" )} -> P | N34: {=IFERROR( INDEX(survey_paper_2026!$G:$G, MATCH(LOWER(TRIM(B34)), LOWER(TRIM(survey_paper_2026!$B:$B)),0) ), "New" )} -> Y
A35: Bedi, P; Rani, S; Gupta, B; Bhasin, V; Gole, P | B35: epibrcan-lite: a lightweight deep learning model for breast cancer subtype classification using epigenomic data | C35: 2025 | D35: COMPUTER METHODS AND PROGRAMS IN BIOMEDICINE | E35: 59 | F35: University of Delhi; University of Delhi; University of Delhi | G35: Background and objectives: Early breast cancer subtypes classification improves the survival rate as it facilitates prognosis of the patient. In literature this problem was prominently solved by various Machine Learning and Deep Learning techniques. However, these studies have three major shortcomings: huge Trainable Weight Parameters (TWP), suffer from low performance and class imbalance problem. Methods: This paper proposes a lightweight model named EpiBrCan-Lite for classifying breast cancer subtypes using DNA methylation data. This model encompasses three blocks namely Data Encoding, TransGRU, and Classification blocks. In Data Encoding block, the input features are encoded into equal sized chunks and then passed down to TransGRU block which is a modified version of traditional Transformer Encoder (TE). In TransGRU block, MLP module of traditional TE is replaced by GRU module, consisting of two GRU layers to reduce TWP and capture the long-range dependencies of input feature data. Furthermore, output of TransGRU block is passed to Classification block for classifying breast cancer into their subtypes. Results: The proposed model is validated using Accuracy, Precision, Recall, F1-score, FPR, and FNR metrics on TCGA breast cancer dataset. This dataset suffers from the class imbalance problem which is mitigated using Synthetic Minority Oversampling Technique (SMOTE). Experimentation results demonstrate that EpiBrCan-Lite model attained 95.85 % accuracy, 95.96 % recall, 95.85 % precision, 95.90 % F1-score, 1.03 % FPR, and 4.12 % FNR despite of utilizing only 1/1500 of TWP than other state-of-the-art models. Conclusion: EpiBrCan-Lite model is efficiently classifying breast cancer subtypes, and being lightweight, it is suitable to be deployed on low computational powered devices. | H35: Breast cancer disease; Transformer encoder; Gated recurrent unit; Epigenomic; DNA methylation data; SMOTE | I35: EXPRESSION SIGNATURE | J35: ELSEVIER IRELAND LTD | K35: Article | M35: P | N35: Y
A36: Douangnoulack, P; Boonjing, V | B36: building minimal classification rules for breast cancer diagnosis | C36: 2018 | D36: 2018 10TH INTERNATIONAL CONFERENCE ON KNOWLEDGE AND SMART TECHNOLOGY (KST 2018) - CYBERNETICS IN THE NEXT DECADES | E36: 14 | F36: King Mongkuts Institute of Technology Ladkrabang | G36: A rule based classifier is widely applied in breast cancer diagnosis. The classifier with a good performance of disease classification have been developed and highly required over the past decades. Since classification rules are derived from previous diagnosis with a large amount of features, it challenges to build a minimal number of rules with high performance while retaining all diagnosis information. The Principal Component Analysis (PCA) is known as a lossless data reduction technique with good classification performance. Therefore, this paper aims at finding the best performance classifier giving minimal classification rules by employing PCA. Based on experiment result on Wisconsin Breast Cancer data set, the J48 decision tree classifier is found to be the best among the three classifiers: J48 decision tree, Reduced Error Pruning Tree, and Random Tree. | H36: Rule Based Classifier; Decision Tree; PCA; Breast Cancer Diagnosis | J36: IEEE | K36: Proceedings Paper | M36: SA | N36: {=IFERROR( INDEX(survey_paper_2026!$G:$G, MATCH(LOWER(TRIM(B36)), LOWER(TRIM(survey_paper_2026!$B:$B)),0) ), "New" )} -> New
A37: Shim, SO; Hussain, L; Alsolami, E; Alkinani, MH | B37: an intelligent smart dynamic feature analysis based approach by utilizing deep learning to improve the breast cancer detection | C37: 2025 | D37: IEEE ACCESS | E37: 106 | F37: University of Jeddah; University of Azad Jammu & Kashmir; University of Jeddah; University of Jeddah | G37: Breast cancer remains one of the important global health concerns with high rates of mortality, highlighting the significance of more sophisticated diagnostic methods. Conventional methods, generally comprised of costly imaging and invasive biopsies, are of high burdens. Motivated by the limitations, the present study comes up with an innovative automated solution for the identification of breast cancer using deep learning analysis of mammograms. Moving away from the traditional approaches with inherent pre-processing and feature extraction constraints, this research focuses on a two-pronged improvement strategy: improved mammogram quality and highly optimized deep learning architecture. Specifically, we present a new Optimized InceptionResNetV2 model significantly optimized through the thoughtful addition of large data augmentation to increase robustness, LeakyReLU activation to facilitate gradient flow and accelerate learning, and MeanDropout regularization to mitigate overfitting and improve generalization. The model was also trained using Quantization aware training (QAT) to enable efficient deployment on low-resource devices without significant performance degradation. The performance on our proposed approach for the massive mammogram dataset reflects an evident improvement in detection performance over traditional techniques. Our InceptionResNetV2 optimized achieved state-of-the-art accuracy with outstanding measures of 98.06% sensitivity, 97.05%, positive predictive value (PPV) and specificity of 99.60%, negative predictive value (NPV) of 86.83%, 97.94% accuracy, F1-score of 96.90%, Matthew's correlation coefficient (MCC) of 90.67%, and AUC of 0.9939. The benefits of proposed system are that it can deliver a more efficient, precise, and possibly cost-effective diagnostic tool for breast cancer. Through synergistic integration of architectural optimization, sophisticated regularization methods, and deployment-aware training, our proposed system enables earlier and more accurate detection. This innovation has the potential to greatly enhance healthcare delivery by equipping radiologists and clinicians with a strong second opinion and initial read capability, ultimately leading to improved patient outcomes and decreased mortality related to this widespread disease. | H37: Breast cancer; post-training quantization; post-training quantization; smart model; smart model; dynamics feature engineering; dynamics feature engineering; optimized deep learning; optimized deep learning | I37: CONVOLUTIONAL NEURAL-NETWORKS; COMPUTER-AIDED DETECTION; SCREENING MAMMOGRAPHY; EYE OPEN; CLASSIFICATION; STATISTICS; HEIGHT; MODEL | J37: IEEE-INST ELECTRICAL ELECTRONICS ENGINEERS INC | K37: Article | L37: Green Submitted, gold | M37: SA | N37: {=IFERROR( INDEX(survey_paper_2026!$G:$G, MATCH(LOWER(TRIM(B37)), LOWER(TRIM(survey_paper_2026!$B:$B)),0) ), "New" )} -> New
A38: Liu, SX; Himel, GMS; Wang, JH | B38: breast cancer classification with enhanced interpretability: dalaresnet50 and dt grad-cam | C38: 2024 | D38: IEEE ACCESS | E38: 63 | F38: Mokwon University; Universiti Sains Malaysia | G38: Automatic classification of breast cancer in histopathology images is crucial for accurate diagnosis and effective treatment planning. Recently, classification methods based on the ResNet architecture have gained prominence due to their ability to improve accuracy significantly. This is achieved by employing skip connections to mitigate vanishing gradient issues, enabling the integration of low-level and high-level feature information. However, the conventional ResNet architecture faces challenges such as data imbalance and limited interpretability, which necessitate cross-domain knowledge and collaboration among medical experts. To address these challenges, this study proposes a novel method for breast cancer classification: the Dual-Activated Lightweight Attention ResNet50 (DALAResNet50) model. This model integrates a pre-trained ResNet50 architecture with a lightweight attention mechanism, embedding an attention module in the fourth layer of ResNet50, and incorporates two fully connected layers with LeakyReLU and ReLU activation functions to enhance feature learning capabilities. Extensive experiments conducted on the BreakHis, BACH, and Mini-DDSM datasets demonstrate that DALAResNet50 outperforms state-of-the-art models in accuracy, F1 score, IBA, and GMean, particularly excelling in classification tasks involving imbalanced datasets. Furthermore, the proposed Dynamic Threshold Grad-CAM (DT Grad-CAM) method provides clearer and more focused visualizations, enhancing interpretability and assisting medical experts in identifying key features. | H38: Breast cancer; Accuracy; Feature extraction; Computational modeling; Adaptation models; Residual neural networks; Histopathology; Medical diagnostic imaging; Image classification; Deep learning; Lightweight attention mechanism; grad-cam; breast cancer classification | J38: IEEE-INST ELECTRICAL ELECTRONICS ENGINEERS INC | K38: Article | L38: Green Submitted, gold | M38: SA | N38: {=IFERROR( INDEX(survey_paper_2026!$G:$G, MATCH(LOWER(TRIM(B38)), LOWER(TRIM(survey_paper_2026!$B:$B)),0) ), "New" )} -> New
A39: Nneji, GU; Monday, HN; Mgbejime, GT; Pathapati, VSR; Nahar, S; Ukwuoma, CC | B39: lightweight separable convolution network for breast cancer histopathological identification | C39: 2023 | D39: DIAGNOSTICS | E39: 33 | F39: Chengdu University of Technology; University of Electronic Science & Technology of China; University of Missouri System; University of Missouri Saint Louis; University of Missouri System; University of Missouri Saint Louis; University of Electronic Science & Technology of China | G39: Breast cancer is one of the leading causes of death among women worldwide. Histopathological images have proven to be a reliable way to find out if someone has breast cancer over time, however, it could be time consuming and require much resources when observed physically. In order to lessen the burden on the pathologists and save lives, there is need for an automated system to effectively analysis and predict the disease diagnostic. In this paper, a lightweight separable convolution network (LWSC) is proposed to automatically learn and classify breast cancer from histopathological images. The proposed architecture aims to treat the problem of low quality by extracting the visual trainable features of the histopathological image using a contrast enhancement algorithm. LWSC model implements separable convolution layers stacked in parallel with multiple filters of different sizes in order to obtain wider receptive fields. Additionally, the factorization and the utilization of bottleneck convolution layers to reduce model dimension were introduced. These methods reduce the number of trainable parameters as well as the computational cost sufficiently with greater non-linear expressive capacity than plain convolutional networks. The evaluation results depict that the proposed LWSC model performs optimally, obtaining 97.23% accuracy, 97.71% sensitivity, and 97.93% specificity on multi-class categories. Compared with other models, the proposed LWSC obtains comparable performance. | H39: CNN; breast cancer; deep learning; histopathological image; image identification; lightweight network | I39: IMAGE CLASSIFICATION; NEURAL-NETWORK; SEGMENTATION; PREDICTION | J39: MDPI | K39: Article | L39: Green Submitted, gold | M39: P | N39: Y
A40: Hamed, G; Marey, M; Amin, SE; Tolba, MF | B40: automated breast cancer detection and classification in full field digital mammograms using two full and cropped detection paths approach | C40: 2021 | D40: IEEE ACCESS | E40: 42 | F40: Egyptian Knowledge Bank (EKB); Ain Shams University | G40: Breast cancer is one of the most severe diseases that threaten women's life results in increasing the death rate annually as confirmed by the World Health Organization. Breast cancer early detection is one of the main reasons behind reducing cancer severity. However, with the huge number of mammograms taken daily, the checking process conducted by radiologists becomes lengthy, tiring, and pruning to errors process. Hence, with the tremendous success achieved by utilizing CNNs in bioinformatics, the development of Computer-Aided Detection (CAD) systems has proved its necessity to solve the challenging cases for the biopsies missed by the ordinary checking leads to decreasing the false positive and negative rates. In this paper, we present a YOLOV4 based CAD system to localize lesions in full and cropped mammograms and then classify them to obtain their pathology type. The proposed method mainly consists of three phases that are applied on the full-field digital mammograms of the INbreast dataset. First, the mammograms are preprocessed to remove any extra artifacts and then cropped into small, overlapped slices. Second, masses are localized through two paths: the full mammograms and the cropped slices detection after configuring the YOLO-V4 model. Third, other feature extractors like ResNet, VGG, Inception, etc. are used to classify the localized lesions to compare their performance against YOLO. The proposed method proved using the experimental results the impact of utilizing YOLO-V4 as a detector with the 2-paths of detection of a full mammogram and the cropped slices in a trial to avoid any data loss by resizing the large-sized mammograms. Our system succeeds in detecting the masses' location with an overall accuracy of approximate to 98% which is more than the recently introduced breast cancer detection methods. Moreover, its ability to distinguish between benign and malignant tumors with an accuracy of approximate to 95%. | H40: Mammography; Breast cancer; Lesions; Cancer; Solid modeling; Feature extraction; Tumors; Breast cancer; breast mammograms; breast masses classification; lesions detection; You Only Look Once | I40: COMPUTER-AIDED DETECTION; DIAGNOSIS; RADIOLOGISTS; MASSES; SYSTEM | J40: IEEE-INST ELECTRICAL ELECTRONICS ENGINEERS INC | K40: Article | L40: Green Submitted, gold | M40: SA | N40: {=IFERROR( INDEX(survey_paper_2026!$G:$G, MATCH(LOWER(TRIM(B40)), LOWER(TRIM(survey_paper_2026!$B:$B)),0) ), "New" )} -> New
A41: Elaraby, A; Saad, A; Elmannai, H; Alabdulhafith, M; Hadjouni, M; Hamdi, M | B41: an approach for classification of breast cancer using lightweight deep convolution neural network | C41: 2024 | D41: HELIYON | E41: 33 | F41: Egyptian Knowledge Bank (EKB); Qena University; Al-Furat Al-Awsat Technical University; Princess Nourah bint Abdulrahman University; Princess Nourah bint Abdulrahman University | G41: The rapid advancement of deep learning has generated considerable enthusiasm regarding its utilization in addressing medical imaging issues. Machine learning (ML) methods can help radiologists to diagnose breast cancer (BCs) barring invasive measures. Informative hand-crafted features are essential prerequisites for traditional machine learning classifiers to achieve accurate results, which are time-consuming to extract. In this paper, our deep learning algorithm is created to precisely identify breast cancers on screening mammograms, employing a training method that effectively utilizes training datasets with either full clinical annotation or solely the cancer status of the entire image. The proposed approach utilizes Lightweight Convolutional Neural Network (LWCNN) that allows automatic extraction features in an end-to-end manner. We have tested LWCNN model in two experiments. In the first experiment, the model was tested with two cases' original and enhancement datasets 1. It achieved 95 %, 93 %, 99 % and 98 % for training and testing accuracy respectively. In the second experiment, the model has been tested with two cases' original and enhancement datasets 2. It achieved 95 %, 91 %, 99 % and 92 % for training and testing accuracy respectively. Our proposed method, which uses various convolutional network to classify screening mammograms achieved exceptional performance when compared to other methods. The findings from these experiments clearly indicate that automatic deep learning techniques can be trained effectively to attain remarkable accuracy across a wide range of mammography datasets. This holds significant promise for improving clinical tools and reducing both false positive and false negative outcomes in screening mammography. | H41: Deep learning; Lightweight convolutional neural networks; (LWCNN); Image processing; Breast cancer | I41: MACHINE LEARNING TECHNIQUES; BENIGN; IMAGES | J41: CELL PRESS | K41: Article | L41: Green Submitted, gold | M41: P | N41: Y
A42: Nehary, EA; Rajan, S | B42: improved breast cancer classification using prior information and decentralized training approach | C42: 2025 | D42: 2025 IEEE SENSORS APPLICATIONS SYMPOSIUM, SAS | E42: 24 | F42: Carleton University | G42: Breast ultrasound (US) datasets are often small in size and contain tumors of varying sizes and shapes that make classification of breast US images as benign or malignant non-trivial, and learning and generalization of such classification models challenging. This challenge can be alleviated to some extent by incorporating prior information, such as breast tumour masks. However, tumour masks are not available for all US datasets. This paper proposes a novel method that adopts a decentralized training procedure inspired by federated learning, where a server provides the backbone to two clients which train local models using their own datasets. One of the clients uses the prior information for its learning and transfers this information via the weights of the updated backbone to the second client (through the server) which only uses US images for training its head and the backbone. This novel method outperforms other training approaches, including training from scratch, transfer learning, and knowledge distillation, by at least 3% and 8% in terms of accuracy and Matthews correlation coefficient, respectively. | H42: Breast cancer; classification; ultrasound images; deep learning; transfer learning; knowledge distillation; prior information; tumour masks | J42: IEEE | K42: Proceedings Paper | M42: SA | N42: {=IFERROR( INDEX(survey_paper_2026!$G:$G, MATCH(LOWER(TRIM(B42)), LOWER(TRIM(survey_paper_2026!$B:$B)),0) ), "New" )} -> New
A43: Ruza, N; Hussain, SI; Mohamed, SKC; Arzmi, MH | B43: early detection of breast cancer in mammograms using the lightweight modification of efficientnet b3 | C43: 2023 | D43: REVISTA INTERNACIONAL DE METODOS NUMERICOS PARA CALCULO Y DISENO EN INGENIERIA | E43: 30 | F43: Universiti Kebangsaan Malaysia; Universiti Kebangsaan Malaysia; International Islamic University Malaysia; International Islamic University Malaysia; International Islamic University Malaysia | G43: Breast cancer is one of the leading causes of death in women worldwide and early detection is critical to improving survival rates. In this study, we present a modified deep learning method for automatic feature detection for breast mass classification on mammograms. We propose to use EfficientNet, a Convolutional Neural Network (CNN) architecture that requires minimal parameters. The main advantage of EfficientNet is the small number of parameters, which allows efficient and accurate classification of mammogram images. Our experiments show that EfficientNet, with an overall accuracy of 86.5 percent, has the potential to be the basis for a fully automated and effective breast cancer detection system in the future. Our results demonstrate the potential of EfficientNet to improve the accuracy and efficiency of breast cancer detection compared to other approaches. | H43: EfficientNet; Transfer Learning; Breast Mass Classification | I43: DEEP; COVID-19 | J43: SCIPEDIA S L | K43: Article | L43: gold | M43: {=IFERROR( INDEX(survey_paper_2026!$F:$F, MATCH(LOWER(TRIM(B43)), LOWER(TRIM(survey_paper_2026!$B:$B)),0) ), "New" )} -> P | N43: {=IFERROR( INDEX(survey_paper_2026!$G:$G, MATCH(LOWER(TRIM(B43)), LOWER(TRIM(survey_paper_2026!$B:$B)),0) ), "New" )} -> Y
A44: Abdel-Hamid, L; Yogarajah, P; Tealab, SHA | B44: lightweight deep models based on domain adaptation and network pruning for breast cancer her2 scoring: ihc vs. h&e histopathological images | C44: 2025 | D44: PLOS ONE | E44: 50 | F44: Egyptian Knowledge Bank (EKB); Misr International University; Ulster University; Egyptian Knowledge Bank (EKB); Cairo University | G44: Human epidermal growth factor receptor 2 (HER2)-positive breast cancer is an aggressive cancer type that requires special diagnosis and treatment methods. Immunohistochemistry (IHC) staining effectively highlights relevant morphological structures within histopathological images yet can be expensive in terms of both labor and required laboratory equipment. Hematoxylin and eosin (H&E) images are more readily available and less expensive than IHC images as they are routinely performed for all patient samples. Lightweight models are well-suited for deployment on resource-constrained devices such as mobile phones and embedded systems, making them ideal for real-time diagnosis in rural regions and developing countries. In this study, IHC images are compared to H&E images for automatic HER2 scoring using lightweight deep models that incorporate several advanced techniques including network pruning, domain adaptation, and attention mechanisms. Two lightweight models are presented: PrunEff4 and ATHER2. PrunEff4 is a subset of EfficientNetV2B0 pruned to reduce the network parameters by similar to 80%. ATHER2 is a customized lightweight network that employs different sized convolutional filters along with a convolutional block attention module (CBAM). For PrunEff4 and ATHER2, transfer learning (pretraining on ImageNet) and domain-specific pretraining were employed, respectively. Different datasets were utilized in the development and final testing phases in order to effectively evaluate their generalization capability. In all experiments, both networks resulted in accuracies ranging from 97% to 100% for binary classifications and from 95.5% to 98.5% for multiclass classifications regardless of whether IHC or H&E images were utilized. Network pruning significantly reduced the network parameters whilst maintaining reliable performance. Domain-specific pretraining significantly enhanced performance, particularly in complex classification tasks such as HER2 scoring using H&E images and multiclass classifications. Both IHC and H&E stained images were suitable for deep learning-based HER2 scoring, given that the deep networks are efficiently trained for the specified task. | J44: PUBLIC LIBRARY SCIENCE | K44: Article | L44: Green Submitted, gold | M44: P | N44: Y
A45: Li, XM; Chen, JM; Luo, B; Xia, MY; Zhang, X; Zhu, HJ; Yutian, ZC; Chen, YS; Yang, Y; Wen, YF | B45: classifying breast intraductal proliferative lesions via a knowledge distillation framework using convolutional neural network-based nuclei-segmentation-assisted classification (kdcnn-nsac) | C45: 2025 | D45: HELIYON | E45: 43 | F45: Shanghai Dianji University; Wuhan University; Huazhong University of Science & Technology; Shanghai Jiao Tong University; Shanghai Jiao Tong University | G45: Background and objective: Diagnosis of breast intraductal proliferative lesions (BIDPLs) in hematoxylin-eosin (HE) images remains a time-consuming and intractable topic because of subjective processes and subtle morphological differences. Convolutional neural networks (CNNs) show great potential for providing objective analysis strategies for HE images. In this study, we proposed a novel knowledge distillation (KD) framework using CNN-based nuclei segmentation-assisted classification (KDCNN-NSAC). Methods: The diagnosis of BIDPLs is treated as multiple class classification tasks in the BReAst Carcinoma Subtyping dataset. The KDCNN-NSAC fully leveraged the epithelial and stromal nuclei-level features in training phases and performed region-of-interest (ROI)-level classifications in predicting phases. Then, the whole slide image (WSI) was diagnosed based on the risk ratings of the ROIs within it, instead of processing a WSI. Results: The principal results showed that in ROI-level classifications, KDCNN-NSAC outperformed the state-of-the-art methods for 7-class classification with an average F1 score of 63.26 % and achieves F1 score of 98.36 % and 94.21 %, respectively, in distinguishing BIDPLs from invasive cancer and normal tissue. The WSI-level predictions obtained a high degree of consistency with the pathologists' annotation (kappa value of 0.88). Ablation experiments showed that nuclei segmentation and classification components improve the performance of the baseline model in KDCNN-NSAC by 3 %. Conclusions: The KDCNN-NSAC makes the model focus on important cellular information and predicts the WSI in accordance with the pathologists' diagnostic thinking, thus improving model explainability. Moreover, the introduce of KDCNN-NSAC will help achieve superior performance in diagnosing BIDPLs. | H45: Breast intraductal proliferative lesions; Breast cancer; Knowledge distillation; Convolutional neural network; Nuclei segmentation; Classification | I45: ARTIFICIAL-INTELLIGENCE; CANCER; PATHOLOGY; DIAGNOSIS; FEATURES; ATYPIA | J45: CELL PRESS | K45: Article | L45: Green Submitted, gold | M45: SA | N45: {=IFERROR( INDEX(survey_paper_2026!$G:$G, MATCH(LOWER(TRIM(B45)), LOWER(TRIM(survey_paper_2026!$B:$B)),0) ), "New" )} -> New
A46: Alwidian, J; Hammo, BH; Obeid, N | B46: wcba: weighted classification based on association rules algorithm for breast cancer disease | C46: 2018 | D46: APPLIED SOFT COMPUTING | E46: 39 | F46: University of Jordan | G46: Breast cancer is the second most frequent human neoplasm that accounts for one quarter of all cancers in females. Among the other types of cancers, it is considered to be the main cause of death in women in most countries. An efficient classifier for accurately helping physicians to predict this chronic disease is in high demand. One approach for solving this problem has been tackled by many scholars using Association Classification (AC) techniques to enhance the classification process through applying association rules. However, most AC algorithms are suffering from the estimated measures used in the rule evaluation process and the prioritization techniques used at the attributes level, which could play a critical role in the rule generation process. In this article we attempt to solve this problem through an efficient weighted classification based on association rules algorithm, named WCBA. We also present a new pruning and prediction technique based on statistical measures to generate more accurate association rules to enhance the accuracy level of the AC classifiers. As a case study, we used WCBA to classify breast cancer instances with the help of subject matter experts from King Hussein Cancer Center (KHCC) located in Amman, Jordan. We compare WCBA with five well-known AC algorithms: CBA, CMAR, MCAR, FACA and ECBA running on two breast cancer datasets from UCI machine learning data repository. Experimental results show that WCBA, in most cases, outperformed the other AC algorithms for this case study. In addition, WCBA generates more accurate rules that contain the most efficient attributes for predicting breast cancer. WCBA algorithm aims to predict breast cancer in a patient. It serves all breast cancer patients by reducing the fear of the possibility of the recurrence of the disease and takes the necessary measures to prevent the progression of the disease and to predict breast cancer in a patient. The algorithm can be generalized to work on different domains with the help of subject matter experts. (C) 2017 Elsevier B.V. All rights reserved. | H46: Data mining; Association classification; Association rules; Apriori; Breast cancer | J46: ELSEVIER | K46: Article | M46: SA | N46: {=IFERROR( INDEX(survey_paper_2026!$G:$G, MATCH(LOWER(TRIM(B46)), LOWER(TRIM(survey_paper_2026!$B:$B)),0) ), "New" )} -> New
A47: Meenalochini, G; Ramkumar, S | B47: a deep learning based breast cancer classification system using mammograms | C47: 2024 | D47: JOURNAL OF ELECTRICAL ENGINEERING & TECHNOLOGY | E47: 72 | F47: Kalasalingam Academy of Research & Education | G47: An automatic breast cancer detection and classification system plays an essential role in medical imaging applications. But accurate disease identification is one of the complicated processes due to the existence of noisy contents and irrelevant structure of the original images. In conventional works, various medical image processing techniques have been developed for accurately classifying the types of breast cancer. Still, it confronts difficulties due to the aspects of increased complexity in computations, error values, false positives, and misclassification outputs. Hence, this research work proposes to develop an optimization-based classification system for the breast cancer identification system. Here, the Gaussian filtering and Adaptive Histogram Equalization (AHE) techniques are utilized for preprocessing the original mammogram images by eliminating the noisy contents and enhancing the contrast of an image. Then, the Markov Random Adaptive Segmentation (MRAS) technique is employed for detecting the boundary region based on the random value selection. To make the classifying procedure easier, the set of features is optimally extracted from the segmented region with the help of a Genetic Algorithm (GA). In which, the global best fitness value is estimated by using the crossover, mutation, and selection operations. Finally, the Convolutional Neural Network (CNN) classification technique is utilized for categorizing the image as to whether normal or abnormal with its type. The entire performance analysis of the suggested model is validated and compared using multiple measures during the evaluation. In the proposed method GA performs feature selection and prunes unnecessary features. The major goal is to improve the classification performance while reducing the number of features used. The proposed system GA-CNN provides improved performance results with a reduced error rate.The suggested GA-CNN increases accuracy (98.5), sensitivity (99.38), and specificity values (98.4) as compared to the existing technique by effectively identifying the classed label. | H47: Breast cancer detection; Preprocessing; Contrast enhancement; Genetic algorithm; Markov random adaptive segmentation (MRAS); Genetic algorithm (GA) based optimization; Convolutional neural network (CNN) based classification | I47: LARGE-SAMPLE INFERENCE; SEGMENTATION; PREDICTION; ALGORITHM; RATIO | J47: SPRINGER SINGAPORE PTE LTD | K47: Article | M47: SA | N47: {=IFERROR( INDEX(survey_paper_2026!$G:$G, MATCH(LOWER(TRIM(B47)), LOWER(TRIM(survey_paper_2026!$B:$B)),0) ), "New" )} -> New
A48: Elbashir, MK; Ezz, M; Mohammed, M; Saloum, SS | B48: lightweight convolutional neural network for breast cancer classification using rna-seq gene expression data | C48: 2019 | D48: IEEE ACCESS | E48: 49 | F48: Al Jouf University; Egyptian Knowledge Bank (EKB); Al Azhar University; University of Kwazulu Natal | G48: Gene expressions are considered among the most used features in cancer classification. The available gene expression data has a small number of samples and a relatively big number of dimensions, and that makes it not suitable for deep Convolutional Neural Networks (CNN) architectures, which exhibit state-of-the-art performance in many fields. In this paper, we propose a lightweight CNN architecture for breast cancer classification using gene expression data downloaded from Pan-Cancer Atlas using Illumina HiSeq platform. The downloaded gene expression data is preprocessed and then transformed into 2D-images. We started the preprocessing by removing the outlier samples, which are determined based on the Array-Array Intensity Correlation (AAIC), which defines a symmetric square matrix of Spearman correlation. Then we applied a normalization process on the gene expression data to ensure that we can infer the expression level from it correctly and avoid biases in the expression measures. Finally, filtering is applied on the data. Model selection or a parameters search strategy is conducted to choose the values of the CNN hyper-parameters that give optimal performance. Our experiments show that our proposed method achieves an accuracy of 98.76%, which is the highest compared to other competing methods. | H48: Tumor type classification; RNA-Seq; gene expression; convolutional neural network; edge detection | I48: SUPPORT VECTOR MACHINE | J48: IEEE-INST ELECTRICAL ELECTRONICS ENGINEERS INC | K48: Article | L48: Green Submitted, gold | M48: {=IFERROR( INDEX(survey_paper_2026!$F:$F, MATCH(LOWER(TRIM(B48)), LOWER(TRIM(survey_paper_2026!$B:$B)),0) ), "New" )} -> P | N48: {=IFERROR( INDEX(survey_paper_2026!$G:$G, MATCH(LOWER(TRIM(B48)), LOWER(TRIM(survey_paper_2026!$B:$B)),0) ), "New" )} -> Y
A49: Kim, E; Lee, YJ; Lee, J; Lee, H; Bappy, DM; Ahn, S; Lee, SH | B49: fusing domains for tumor detection in frozen section histopathology using joint feature alignment and self-knowledge distillation | C49: 2025 | D49: IEEE ACCESS | E49: 53 | F49: Korea University; Korea University Medicine (KU Medicine); Korea University; Korea University Medicine (KU Medicine); University of Pennsylvania; Pennsylvania Medicine; Catholic University of Korea; Seoul St. Mary's Hospital | G49: Robustness in neural networks is of paramount importance in the field of image classification. Domain shift remains a major challenge particularly prevalent in whole-slide image (WSI) data within the context of histopathology, which is exacerbated by differences in WSI scanners and the status of WSIs. This study focuses on the domain shift encountered in tumor detection in breast lymph nodes by leveraging the publicly available Camelyon16 dataset and an in-house dataset. We propose a simple yet effective self-knowledge distillation approach with contrastive embedding alignment across domains. By transferring knowledge from the source data to the target data, the experimental results demonstrated remarkable adjustments in the domain shift. These findings have significant implications for the advancement of tumor detection accuracy and reliability of histopathological WSI analysis. | H49: Lymph nodes; Tumors; Biomedical imaging; Breast cancer; Semantics; Knowledge transfer; Robustness; Reviews; Hospitals; Histopathology; domain adaptation; knowledge distillation | I49: IMAGE-ANALYSIS; DIGITAL PATHOLOGY; CHALLENGES | J49: IEEE-INST ELECTRICAL ELECTRONICS ENGINEERS INC | K49: Article | L49: Green Submitted, gold | M49: SA | N49: {=IFERROR( INDEX(survey_paper_2026!$G:$G, MATCH(LOWER(TRIM(B49)), LOWER(TRIM(survey_paper_2026!$B:$B)),0) ), "New" )} -> New
A50: Roslidar, R; Rahman, A; Muharar, R; Syahputra, MR; Arnia, F; Syukri, M; Pradhan, B; Munadi, K | B50: a review on recent progress in thermal imaging and deep learning approaches for breast cancer detection | C50: 2020 | D50: IEEE ACCESS | E50: 125 | F50: Universitas Syiah Kuala; Universitas Syiah Kuala; Universitas Syiah Kuala; University of Technology Sydney; Sejong University | G50: Developing a breast cancer screening method is very important to facilitate early breast cancer detection and treatment. Building a screening method using medical imaging modality that does not cause body tissue damage (non-invasive) and does not involve physical touch is challenging. Thermography, a non-invasive and non-contact cancer screening method, can detect tumors at an early stage even under precancerous conditions by observing temperature distribution in both breasts. The thermograms obtained on thermography can be interpreted using deep learning models such as convolutional neural networks (CNNs). CNNs can automatically classify breast thermograms into categories such as normal and abnormal. Despite their demostrated utility, CNNs have not been widely used in breast thermogram classification. In this study, we aimed to summarize the current work and progress in breast cancer detection based on thermography and CNNs. We first discuss of breast thermography potential in early breast cancer detection, providing an overview of the availability of breast thermal datasets together with publicly accessible. We also discuss characteristics of breast thermograms and the differences between healthy and cancerous thermographic patterns. Breast thermogram classification using a CNN model is described step by step including a simulation example illustrating feature learning. We cover most research related to the implementation of deep neural networks for breast thermogram classification and propose future research directions for developing representative datasets, feeding the segmented image, assigning a good kernel, and building a lightweight CNN model to improve CNN performance. | H50: Breast cancer; convolutional neural network; deep learning; early detection; thermogram | I50: CONVOLUTIONAL NEURAL-NETWORKS; COMPUTER-AIDED DETECTION; TEXTURE FEATURES; TUMOR SIZE; SEGMENTATION; THERMOGRAPHY; CLASSIFICATION; IMAGES; RISK; MAMMOGRAPHY | J50: IEEE-INST ELECTRICAL ELECTRONICS ENGINEERS INC | K50: Review | L50: Green Submitted, gold | M50: {=IFERROR( INDEX(survey_paper_2026!$F:$F, MATCH(LOWER(TRIM(B50)), LOWER(TRIM(survey_paper_2026!$B:$B)),0) ), "New" )} -> P | N50: {=IFERROR( INDEX(survey_paper_2026!$G:$G, MATCH(LOWER(TRIM(B50)), LOWER(TRIM(survey_paper_2026!$B:$B)),0) ), "New" )} -> Y
A51: Hu, MZ; Yang, XF | B51: breastlightsam: a lightweight pipeline for fast and accurate breast cancer diagnosis and tumor segmentation | C51: 2025 | D51: MEDICAL IMAGING 2025: ULTRASONIC IMAGING AND TOMOGRAPHY | E51: 15 | F51: Emory University; Emory University; Emory University | G51: BreastLightSAM presents an innovative, lightweight pipeline tailored to tackle the challenges associated with rapid and precise diagnosis of breast cancer in 2D ultrasound images. The model integrates a modified Segmentation Anything Model (SAM) with an optimized RepViT-based image encoder for efficient segmentation and incorporates a compact classification module based on GhostNet to accurately classify breast tumors. This design allows for high segmentation accuracy and classification precision while significantly reducing latency, making it suitable for deployment on computationally limited devices like mobile phones. The proposed pipeline features a point-based prompt design that emulates human interaction, enhancing the model's generalization and robustness. Results show that BreastLightSAM achieves a mean Dice Similarity Coefficient (DSC) of 0.812 and a mean pixel accuracy of 0.943, with a latency of just 28.6 milliseconds, while the classification module delivers high precision and recall across tumor types. However, the study's focus on 2D ultrasound images limits its exploration of the impact of 3D imaging on performance. Additionally, the influence of human expertise and pre-processing techniques such as contrast enhancement and image sharpening on segmentation results requires further investigation. These aspects present valuable avenues for future research to enhance the clinical applicability of BreastLightSAM in diverse healthcare settings. | H51: Segmentation Anything Model; Breast Cancer; Lightweight Segmentation; Interactive Prompt | J51: SPIE-INT SOC OPTICAL ENGINEERING | K51: Proceedings Paper | M51: P | N51: Y
A52: Pei, ZY; Li, JR | B52: breast cancer image recognition based on a lightweight densenet model | C52: 2024 | D52: 2024 4TH INTERNATIONAL CONFERENCE ON ARTIFICIAL INTELLIGENCE, AUTOMATION AND ALGORITHMS, AI2A 2024 | E52: 22 | F52: Henan University of Traditional Chinese Medicine | G52: Breast cancer remains a significant global threat to women's health, making early diagnosis and treatment vital for reducing mortality rates. Traditional methods for classifying breast cancer pathology images are time-consuming, labor-intensive, and often lack accuracy. While deep learning models have made remarkable strides in breast cancer image classification, they typically require extensive computational resources, including high-performance GPUs and large memory capacities, which can be prohibitive for many healthcare institutions.To address this challenge, this paper presents an enhanced DenseNet model that integrates Depthwise Separable Convolutions and Squeeze-and-Excitation blocks, aiming to improve classification performance while reducing computational costs. The proposed model is validated on the publicly available BreakHis dataset, which automatically classifies breast cancer pathology images into benign and malignant categories. Comparative experiments were conducted with other deep learning models, including VGGNet, DenseNet, ResNet, and MobileNetv2. The results demonstrate that the proposed model exhibits superior learning capability and achieves the best recognition performance, with an accuracy exceeding 99%, a recall of 99%, and a precision of 99% on this dataset. | H52: Breast cancer classification; DenseNet121; Depthwise Separable Convolution; Channel Attention Mechanism; Transfer Learning | J52: ASSOC COMPUTING MACHINERY | K52: Proceedings Paper | M52: SF | N52: {=IFERROR( INDEX(survey_paper_2026!$G:$G, MATCH(LOWER(TRIM(B52)), LOWER(TRIM(survey_paper_2026!$B:$B)),0) ), "New" )} -> New | O52: It provided a general depthwise-convolution formulation but no measured model-level efficiency indicator or quantified reduction.
A53: Huang, J; Mei, LY; Long, MP; Liu, YQ; Sun, W; Li, XX; Shen, H; Zhou, FL; Ruan, XL; Wang, D; Wang, S; Hu, TB; Lei, C | B53: bm-net: cnn-based mobilenet-v3 and bilinear structure for breast cancer detection in whole slide images | C53: 2022 | D53: BIOENGINEERING-BASEL | E53: 44 | F53: Wuhan University; Peking University; Wuhan University; Wuhan University; Peking University | G53: Breast cancer is one of the most common types of cancer and is the leading cause of cancer-related death. Diagnosis of breast cancer is based on the evaluation of pathology slides. In the era of digital pathology, these slides can be converted into digital whole slide images (WSIs) for further analysis. However, due to their sheer size, digital WSIs diagnoses are time consuming and challenging. In this study, we present a lightweight architecture that consists of a bilinear structure and MobileNet-V3 network, bilinear MobileNet-V3 (BM-Net), to analyze breast cancer WSIs. We utilized the WSI dataset from the ICIAR2018 Grand Challenge on Breast Cancer Histology Images (BACH) competition, which contains four classes: normal, benign, in situ carcinoma, and invasive carcinoma. We adopted data augmentation techniques to increase diversity and utilized focal loss to remove class imbalance. We achieved high performance, with 0.88 accuracy in patch classification and an average 0.71 score, which surpassed state-of-the-art models. Our BM-Net shows great potential in detecting cancer in WSIs and is a promising clinical tool. | H53: lightweight; MobileNet-V3; bilinear structure; whole slide image; breast cancer detection | J53: MDPI | K53: Article | L53: Green Submitted, gold | M53: {=IFERROR( INDEX(survey_paper_2026!$F:$F, MATCH(LOWER(TRIM(B53)), LOWER(TRIM(survey_paper_2026!$B:$B)),0) ), "New" )} -> P | N53: {=IFERROR( INDEX(survey_paper_2026!$G:$G, MATCH(LOWER(TRIM(B53)), LOWER(TRIM(survey_paper_2026!$B:$B)),0) ), "New" )} -> Y
A54: Oladimeji, O; Ayaz, H; McLoughlin, I; Unnikrishnan, S | B54: lightweight deep learning for breast cancer diagnosis based on slice selection techniques | C54: 2023 | D54: 2023 31ST IRISH CONFERENCE ON ARTIFICIAL INTELLIGENCE AND COGNITIVE SCIENCE, AICS | E54: 16 | F54: Atlantic Technological University (ATU) | G54: Breast cancer is a prevalent form of cancer with significant mortality and morbidity rates among women worldwide. Early detection is vital in increasing the chances of survival and one of the major approaches for breast cancer screening and detection is medical imaging. Advancements in technology have given rise to 3D medical imaging such as Abbreviated Breast MRI and DBT, overcoming the challenges of tissue overlapping in 2D modalities. However, deep learning model development using this 3D medical imaging comes with higher computational costs and complexity. This study proposes a lightweight deep learning technique based on three slice selection techniques using entropy, variance, and gradient magnitude values from DBT medical imaging modality. The selection techniques help select only the most informative slices making computational cost and complexity reduced. Entropy value-based slice selection performed best with an accuracy of 91%. The results obtained using the slice selection techniques for lightweight deep learning model development show that it can diagnose breast cancer with a lower number of slices and less computational complexity compared to existing methods. | H54: Information Entropy; Gradient Magnitude; DBT Slice Selection; Breast Cancer; CADs | J54: IEEE | K54: Proceedings Paper | M54: {=IFERROR( INDEX(survey_paper_2026!$F:$F, MATCH(LOWER(TRIM(B54)), LOWER(TRIM(survey_paper_2026!$B:$B)),0) ), "New" )} -> P | N54: {=IFERROR( INDEX(survey_paper_2026!$G:$G, MATCH(LOWER(TRIM(B54)), LOWER(TRIM(survey_paper_2026!$B:$B)),0) ), "New" )} -> Y
A55: Chaudhury, S; Shelke, N; Sau, K; Prasanalakshmi, B; Shabaz, M | B55: retracted: a novel approach to classifying breast cancer histopathology biopsy images using bilateral knowledge distillation and label smoothing regularization (retracted article) | C55: 2021 | D55: COMPUTATIONAL AND MATHEMATICAL METHODS IN MEDICINE | E55: 32 | F55: King Khalid University; Arba Minch University | G55: Breast cancer is the most common invasive cancer in women and the second main cause of cancer death in females, which can be classified benign or malignant. Research and prevention on breast cancer have attracted more concern of researchers in recent years. On the other hand, the development of data mining methods provides an effective way to extract more useful information from complex databases, and some prediction, classification, and clustering can be made according to the extracted information. The generic notion of knowledge distillation is that a network of higher capacity acts as a teacher and a network of lower capacity acts as a student. There are different pipelines of knowledge distillation known. However, previous work on knowledge distillation using label smoothing regularization produces experiments and results that break this general notion and prove that knowledge distillation also works when a student model distils a teacher model, i.e., reverse knowledge distillation. Not only this, but it is also proved that a poorly trained teacher model trains a student model to reach equivalent results. Building on the ideas from those works, we propose a novel bilateral knowledge distillation regime that enables multiple interactions between teacher and student models, i.e., teaching and distilling each other, eventually improving each other's performance and evaluating our results on BACH histopathology image dataset on breast cancer. The pretrained ResNeXt29 and MobileNetV2 models which are already tested on ImageNet dataset are used for transfer learning in our dataset, and we obtain a final accuracy of more than 96% using this novel approach of bilateral KD. | I55: DIAGNOSIS | J55: HINDAWI LTD | K55: Article; Retracted Publication | L55: Green Submitted, hybrid | M55: RT | N55: {=IFERROR( INDEX(survey_paper_2026!$G:$G, MATCH(LOWER(TRIM(B55)), LOWER(TRIM(survey_paper_2026!$B:$B)),0) ), "New" )} -> New
A56: Guo, C; Zhou, QJ; Jiao, J; Li, QY; Zhu, L | B56: a modified mobilenetv3 model using an attention mechanism for eight-class classification of breast cancer pathological images | C56: 2024 | D56: APPLIED SCIENCES-BASEL | E56: 24 | F56: Dalian Minzu University | G56: Addressing the challenge of achieving precise subtype classification of breast cancer histopathology images with limited resources, a lightweight model incorporating multi-stage information fusion and an attention mechanism is proposed for this task. Using MobileNetV3 as the backbone, a multi-stage fusion strategy captures the rich image information in breast cancer histopathology images. Additionally, the selective kernel (SK) attention mechanism is introduced in the initial stages of feature extraction, while an improved squeeze-and-excitation coordinate attention (SCA) mechanism is integrated in the later stages to enhance the extraction of both underlying and semantic features. The final feature representations for subtype classification are determined based on the attention map weights computed at each stage. The experimental results demonstrate the model's outstanding recognition performance on the BreakHis dataset, achieving subtype classification accuracies of 96.259%, 94.763%, 95.511%, and 94.015% at four different magnifications. | H56: MobileNetV3; breast cancer; image classification; attention mechanism | J56: MDPI | K56: Article | L56: gold | M56: P | N56: {=IFERROR( INDEX(survey_paper_2026!$G:$G, MATCH(LOWER(TRIM(B56)), LOWER(TRIM(survey_paper_2026!$B:$B)),0) ), "New" )} -> New
A57: Wang, D | B57: toward improving the performance of learning by joining feature selection and ensemble classification techniques: an application for cancer diagnosis | C57: 2023 | D57: JOURNAL OF CANCER RESEARCH AND CLINICAL ONCOLOGY | E57: 53 | G57: IntroductionBreast cancer is known as the most common type of cancer in women, and this has raised the importance of its diagnosis in medical science as one of the most important issues. In addition to reducing costs, the diagnosis of benign or malignant breast cancer is very important in determining the treatment method.ObjectiveThe purpose of this paper is to present a model based on data mining techniques including feature selection and ensemble classification that can accurately predict breast cancer patients in the early stages.MethodologyThe proposed breast cancer detection model is developed by joining Adaptive Differential Evolution (ADE) algorithm for feature selection and Learning Vector Quantization (LVQ) neural network for classification. Our proposed model as ADE-LVQ has the ability to automatically and quickly diagnose breast cancer patients into two classes, benign and malignant. As a new evolutionary approach, ADE performs optimal configuration for LVQ neural network in addition to selecting effective features from breast cancer data. Meanwhile, we configure an ensemble classification technique based on LVQ, which significantly improves the prediction performance.ResultsADE-LVQ has been analyzed from different perspectives on different datasets from Wisconsin breast cancer database. We apply different approaches to handle missing values and improve data quality on this database. The results of the simulations showed that the ADE-LVQ model is more successful than the equivalent and state-of-the-art models in diagnosing breast cancer patients. Also, ADE-LVQ provides better performance with less complexity, considering feature selection and ensemble learning. In particular, ADE-LVQ improves accuracy (up to 3.4%) and runtime (up to 2.3%) on average compared to the existing best method.ConclusionCombined methods based on data mining techniques for breast cancer diagnosis can help doctors in making better decisions for disease treatment. | H57: Cancer diagnosis; Feature selection; Ensemble classification; Adaptive Differential Evolution; Learning Vector Quantization | I57: SUPPORT VECTOR MACHINE; BREAST-CANCER; SYSTEMS | J57: SPRINGER | K57: Article | L57: Green Accepted | M57: SA | N57: {=IFERROR( INDEX(survey_paper_2026!$G:$G, MATCH(LOWER(TRIM(B57)), LOWER(TRIM(survey_paper_2026!$B:$B)),0) ), "New" )} -> New
A58: Sureshkumar, V; Prasad, RSN; Balasubramaniam, S; Jagannathan, D; Daniel, J; Dhanasekaran, S | B58: breast cancer detection and analytics using hybrid cnn and extreme learning machine | C58: 2024 | D58: JOURNAL OF PERSONALIZED MEDICINE | E58: 43 | F58: SRM Institute of Science & Technology Chennai; Sona College of Technology; Rajalakshmi Engineering College; UiT The Arctic University of Tromso | G58: Early detection of breast cancer is essential for increasing survival rates, as it is one of the primary causes of death for women globally. Mammograms are extensively used by physicians for diagnosis, but selecting appropriate algorithms for image enhancement, segmentation, feature extraction, and classification remains a significant research challenge. This paper presents a computer-aided diagnosis (CAD)-based hybrid model combining convolutional neural networks (CNN) with a pruned ensembled extreme learning machine (HCPELM) to enhance breast cancer detection, segmentation, feature extraction, and classification. The model employs the rectified linear unit (ReLU) activation function to enhance data analytics after removing artifacts and pectoral muscles, and the HCPELM hybridized with the CNN model improves feature extraction. The hybrid elements are convolutional and fully connected layers. Convolutional layers extract spatial features like edges, textures, and more complex features in deeper layers. The fully connected layers take these features and combine them in a non-linear manner to perform the final classification. ELM performs classification and recognition tasks, aiming for state-of-the-art performance. This hybrid classifier is used for transfer learning by freezing certain layers and modifying the architecture to reduce parameters, easing cancer detection. The HCPELM classifier was trained using the MIAS database and evaluated against benchmark methods. It achieved a breast image recognition accuracy of 86%, outperforming benchmark deep learning models. HCPELM is demonstrating superior performance in early detection and diagnosis, thus aiding healthcare practitioners in breast cancer diagnosis. | H58: computer-aided diagnosis (CAD); mammogram; pectoral muscle removal; breast cancer; convoluted neural networks; extreme learning machine | I58: CLASSIFICATION | J58: MDPI | K58: Article | L58: Green Submitted, gold | M58: SF | N58: {=IFERROR( INDEX(survey_paper_2026!$G:$G, MATCH(LOWER(TRIM(B58)), LOWER(TRIM(survey_paper_2026!$B:$B)),0) ), "New" )} -> New | O58: Pruning was mentioned, but no quantitative efficiency evidence was reported—no pruning ratio, parameter reduction, FLOPs, memory, model size, or execution time.
A59: Muthukrishnan, R; Balasubramaniam, A; Krishnasamy, V; Ravichandran, SK | B59: an efficient lightweight multi head attention gannet convolutional neural network based mammograms classification | C59: 2025 | D59: INTERNATIONAL JOURNAL OF MEDICAL ROBOTICS AND COMPUTER ASSISTED SURGERY | E59: 32 | F59: Sri Krishna College of Engineering & Technology; Karpagam College of Engineering | G59: BackgroundThis research aims to use deep learning to create automated systems for better breast cancer detection and categorisation in mammogram images, helping medical professionals overcome challenges such as time consumption, feature extraction issues and limited training models. MethodsThis research introduced a Lightweight Multihead attention Gannet Convolutional Neural Network (LMGCNN) to classify mammogram images effectively. It used wiener filtering, unsharp masking, and adaptive histogram equalisation to enhance images and remove noise, followed by Grey-Level Co-occurrence Matrix (GLCM) for feature extraction. Ideal feature selection is done by a self-adaptive quantum equilibrium optimiser with artificial bee colony. ResultsThe research assessed on two datasets, CBIS-DDSM and MIAS, achieving impressive accuracy rates of 98.2% and 99.9%, respectively, which highlight the superior performance of the LMGCNN model while accurately detecting breast cancer compared to previous models. ConclusionThis method illustrates potential in aiding initial and accurate breast cancer detection, possibly leading to improved patient outcomes. | H59: attention mechanism; breast cancer; graphical user interface; lightweight neural network; mammograms | J59: WILEY | K59: Article | L59: Bronze | M59: {=IFERROR( INDEX(survey_paper_2026!$F:$F, MATCH(LOWER(TRIM(B59)), LOWER(TRIM(survey_paper_2026!$B:$B)),0) ), "New" )} -> P | N59: {=IFERROR( INDEX(survey_paper_2026!$G:$G, MATCH(LOWER(TRIM(B59)), LOWER(TRIM(survey_paper_2026!$B:$B)),0) ), "New" )} -> Y
A60: Ural, AB | B60: systematical analysis and pathological classification of breast cancer from mammographic images with using specific machine learning methods | C60: 2022 | D60: TRAITEMENT DU SIGNAL | E60: 29 | F60: Kafkas University | G60: For years, breast cancer has been a serious problem and malignant tumor case primarily causes death of women all around the world. In this paper, a computer based breast tumor analysis and pathological case classification system has been achieved and some novelties are included to the image processing methods, especially in segmentation and base frequency distribution acquisition of the processed image and classification part. First, the possible noises and artifacts are eliminated by using common filtering. Second, the filtered images are segmented with integrating gray level Image Processing methods. Then, these images (ROIs) are converted to the base frequency distribution images with using Fast Fourier Transform (FFT) and Lab&HSV color spaces. The most important key for these images is frequency distribution can be obtained with specific color tones and totally 100 images (50 benign-50 malignant) are accumulated to fed the two different Machine Learning models in literature such as Probabilistic Neural Network as Learning Vector Quantization (LVQ) and Support Vector Regression (SVR) for classification of Benign and Malignant cases without the need for additional medical data. Then the performance of the proposed system is analyzed with 30 different test images (15 benign-15 malignant) according to the metrics like accuracy, sensitivity, specificity, precision, F-score and area under the ROC curve (AUC score). The experimental results on the open access mammogram image set show that discriminating between Benign and Malignant cases can be achieved with an important success rate as 91.38% with LVQ and %.92 with SVR. | H60: breast cancer; benign tumor; malign tumor; image classification; feature extraction; machine learning | I60: TUMOR DETECTION | J60: INT INFORMATION & ENGINEERING TECHNOLOGY ASSOC | K60: Article | L60: hybrid | M60: SA | N60: {=IFERROR( INDEX(survey_paper_2026!$G:$G, MATCH(LOWER(TRIM(B60)), LOWER(TRIM(survey_paper_2026!$B:$B)),0) ), "New" )} -> New
A61: Zhang, XS; Lin, XN; Zhang, ZH; Dong, LC; Sun, XL; Sun, DS; Yuan, KH | B61: artificial intelligence medical ultrasound equipment: application of breast lesions detection | C61: 2020 | D61: ULTRASONIC IMAGING | E61: 38 | F61: Tsinghua University; Tsinghua Shenzhen International Graduate School; Peking University | G61: Breast cancer ranks first among cancers affecting women's health. Our work aims to realize the intelligence of the medical ultrasound equipment with limited computational capability, which is used for the assistant detection of breast lesions. We embed the high-computational deep learning algorithm into the medical ultrasound equipment with limited computational capability by two techniques: (1) lightweight neural network: considering the limited computational capability of ultrasound equipment, a lightweight neural network is designed, which greatly reduces the amount of calculation. And we use the technique of knowledge distillation to train the low-precision network helped with the high-precision network; (2) asynchronous calculations: consider four frames of ultrasound images as a group; the image of the first frame of each group is used as the input of the network, and the result is respectively fused with the images of the fourth to seventh frames. An amount of computation of 30 GFLO/frame is required for the proposed lightweight neural network, about 1/6 of that of the large high-precision network. After trained from scratch using the knowledge distillation technique, the detection performance of the lightweight neural network (sensitivity = 89.25%, specificity = 96.33%, the average precision [AP] = 0.85) is close to that of the high-precision network (sensitivity = 98.3%, specificity = 88.33%, AP = 0.91). By asynchronous calculation, we achieve real-time automatic detection of 24 fps (frames per second) on the ultrasound equipment. Our work proposes a method to realize the intelligence of the low-computation-power ultrasonic equipment, and successfully achieves the real-time assistant detection of breast lesions. The significance of the study is as follows: (1) The proposed method is of practical significance in assisting doctors to detect breast lesions; (2) our method provides some practical and theoretical support for the development and engineering of intelligent equipment based on artificial intelligence algorithms. | H61: artificial intelligence algorithm; medical ultrasound equipment; breast lesions; lightweight neural network; real-time detection; knowledge distillation | I61: CONVOLUTIONAL NEURAL-NETWORKS; CANCER; CLASSIFICATION; NODULES | J61: SAGE PUBLICATIONS INC | K61: Article | M61: {=IFERROR( INDEX(survey_paper_2026!$F:$F, MATCH(LOWER(TRIM(B61)), LOWER(TRIM(survey_paper_2026!$B:$B)),0) ), "New" )} -> P | N61: {=IFERROR( INDEX(survey_paper_2026!$G:$G, MATCH(LOWER(TRIM(B61)), LOWER(TRIM(survey_paper_2026!$B:$B)),0) ), "New" )} -> Y
A62: Mustafa, MA; Erdem, OA; Sögüt, E | B62: hybrid optimization and explainable deep learning for breast cancer detection | C62: 2025 | D62: APPLIED SCIENCES-BASEL | E62: 71 | F62: Gazi University; Northern Technical University; Gazi University | G62: Breast cancer continues to be one of the leading causes of women's deaths around the world, and this has emphasized the necessity to have novel and interpretable diagnostic models. This work offers a clear learning deep learning model that integrates the mobility of MobileNet and two bio-driven optimization operators, the Firefly Algorithm (FLA) and Dingo Optimization Algorithm (DOA), in an effort to boost classification appreciation and the convergence of the model. The suggested model demonstrated excellent findings as the DOA-optimized MobileNet acquired the highest performance of 98.96 percent accuracy on the fusion test, and the FLA-optimized MobileNet scaled up to 98.06 percent and 95.44 percent accuracies on mammographic and ultrasound tests, respectively. Further to good quantitative results, Grad-CAM visualizations indeed showed clinically consistent localization of the lesions, which strengthened the interpretability and model diagnostic reliability of Grad-CAM. These results show that lightweight, compact CNNs can be used to do high-performance, multimodal breast cancer diagnosis. | H62: deep learning; transfer learning; breast cancer detection; optimization algorithms; explainable AI (XAI); Grad-CAM | I62: ARTIFICIAL-INTELLIGENCE; CLASSIFICATION | J62: MDPI | K62: Article | L62: Green Submitted, gold | M62: {=IFERROR( INDEX(survey_paper_2026!$F:$F, MATCH(LOWER(TRIM(B62)), LOWER(TRIM(survey_paper_2026!$B:$B)),0) ), "New" )} -> P | N62: {=IFERROR( INDEX(survey_paper_2026!$G:$G, MATCH(LOWER(TRIM(B62)), LOWER(TRIM(survey_paper_2026!$B:$B)),0) ), "New" )} -> Y
A63: Sait, ARW; Nagaraj, R; Zhou, ZH | B63: an enhanced lightgbm-based breast cancer detection technique using mammography images | C63: 2024 | D63: DIAGNOSTICS | E63: 41 | F63: King Faisal University | G63: Breast cancer (BC) is the leading cause of mortality among women across the world. Earlier screening of BC can significantly reduce the mortality rate and assist the diagnostic process to increase the survival rate. Researchers employ deep learning (DL) techniques to detect BC using mammogram images. However, these techniques are resource-intensive, leading to implementation complexities in real-life environments. The performance of convolutional neural network (CNN) models depends on the quality of mammogram images. Thus, this study aimed to build a model to detect BC using a DL technique. Image preprocessing techniques were used to enhance image quality. The authors developed a CNN model using the EfficientNet B7 model's weights to extract the image features. Multi-class classification of BC images was performed using the LightGBM model. The Optuna algorithm was used to fine-tune LightGBM for image classification. In addition, a quantization-aware training (QAT) strategy was followed to implement the proposed model in a resource-constrained environment. The authors generalized the proposed model using the CBIS-DDSM and CMMD datasets. Additionally, they combined these two datasets to ensure the model's generalizability to diverse images. The experimental findings revealed that the suggested BC detection model produced a promising result. The proposed BC detection model obtained an accuracy of 99.4%, 99.9%, and 97.0%, and Kappa (K) values of 96.9%, 96.9%, and 94.1% in the CBIS-DDSM, CMMD, and combined datasets. The recommended model streamlined the BC detection process in order to achieve an exceptional outcome. It can be deployed in a real-life environment to support physicians in making effective decisions. Graph convolutional networks can be used to improve the performance of the proposed model. | H63: breast cancer; deep learning; EfficientNet; ensemble learning; feature engineering | J63: MDPI | K63: Article | L63: Green Submitted, gold | M63: P | N63: Y
A64: Liu, JJ; Zhang, ST; Liu, W; Deng, C; Zheng, YJ; Metaxas, DN | B64: scalable mammogram retrieval using composite anchor graph hashing with iterative quantization | C64: 2017 | D64: IEEE TRANSACTIONS ON CIRCUITS AND SYSTEMS FOR VIDEO TECHNOLOGY | E64: 74 | F64: Rutgers University System; Rutgers University New Brunswick; University of North Carolina; University of North Carolina Charlotte; Tencent; Xidian University; Shandong Normal University | G64: Content-based image retrieval (CBIR) shows great significance in clinical decision-making, which explores the visual content of medical images rather than keywords, tags, or descriptions. It provides doctors an image-guided approach to explore relevant cases that could offer doctors instructive reference. Mammogram screening has been known to be widely used in the early stage diagnosis of breast cancer and could reduce its morbidity and mortality. In this paper, we aim to develop a scalable CBIR method for a large repository of mammogram. To this end, we extend the original Anchor Graph Hashing (AGH) and propose a new unsupervised hashing algorithm, named as composite AGH with iterative quantization (C-AGH-ITQ), which compresses mammographic regions of interest (ROIs) into compact binary codes and enables real-time searching in Hamming space. Multimodal features and different distance metrics are integrated, performing upon a composite Anchor Graph. To improve the effectiveness of the hash code, quantization error is further iteratively minimized by introducing an orthogonal rotation matrix. We evaluate the presented C-AGH-ITQ algorithm on a data set of 11 533 mammographic ROIs obtained from the Digital Database for Screening-Mammography. Our method obtains more than 84% retrieval precision and 93% classification accuracy (using kNN prediction), which demonstrates that hash codes produced by C-AGH-ITQ well capture the visual similarities between mammographic images. In addition, since C-AGH-ITQ ensures linear complexity of the training procedure and constant time for query, our system is readily applicable to large-scale mammogram databases and has the potential to provide abundant clinical cases as reference. | H64: Composite hashing; content-based image retrieval (CBIR); digital mammogram; feature fusion; scalable | I64: COMPUTER-AIDED DIAGNOSIS; HISTOPATHOLOGICAL IMAGE-ANALYSIS; BREAST-CANCER; CAD-SYSTEM; MASSES; MICROCALCIFICATIONS; CLASSIFICATION; SEGMENTATION; ENHANCEMENT; SIMILARITY | J64: IEEE-INST ELECTRICAL ELECTRONICS ENGINEERS INC | K64: Article | M64: ST | N64: {=IFERROR( INDEX(survey_paper_2026!$G:$G, MATCH(LOWER(TRIM(B64)), LOWER(TRIM(survey_paper_2026!$B:$B)),0) ), "New" )} -> New
A65: Edafetanure-Ibeh, FT; Mogbogu, SB; Mogbogu, R | B65: a lightweight and interpretable ensemble of cnn and transformer models for idc breast cancer classification | C65: 2025 | D65: 2025 IEEE 11TH INTERNATIONAL CONFERENCE ON BIG DATA COMPUTING SERVICE AND MACHINE LEARNING APPLICATIONS, BIGDATASERVICE | E65: 35 | G65: The human eye often struggles to interpret complex visual patterns found in medical images; tasks better handled by intelligent machines. Machine learning and deep learning techniques are widely used in medical applications, including detecting, and diagnosing tumors as benign or malignant. Histopathology plays a vital role in the diagnosis and management of breast cancer, particularly through image analysis obtained via needle biopsy techniques. This diagnostic method enables researchers and clinicians to assess the microscopic characteristics of breast tissue for early intervention. This study applies advanced deep learning techniques to classify invasive ductal carcinoma (IDC) in breast histological images. An ensemble model consisting of three lightweight yet robust architectures, EfficientNet-B3, ConvNeXt-Tiny, and SwinTiny Transformer, is built and evaluated. The model trains on the publicly available Kaggle Breast Histopathology Images dataset using focal loss to manage class imbalance and test-time augmentation (TTA) for robust inference. The images undergo processing and augmentation to enhance model performance, and predictions are combined using soft voting. Additionally, GradCAM visualizes regions of diagnostic importance within the images. According to the performance metrics, the proposed ensemble model achieves a validation accuracy of 92.94% and an F1-score of 93.0%, outperforming baseline models. With this level of performance, the model can help pathologists detect breast cancer in tissue samples more quickly and reliably. | H65: Breast cancer; invasive ductal carcinoma; deep learning; convolutional neural network; vision transformer; ensemble learning; histopathology; Grad-CAM | J65: IEEE COMPUTER SOC | K65: Proceedings Paper | M65: P | N65: Y
A66: Li, FZ; Ma, JM; Wen, TX; Tian, ZB; Liang, HN | B66: hi-net: a novel histopathologic image segmentation model for metastatic breast cancer via lightweight dataset construction | C66: 2024 | D66: HELIYON | E66: 46 | F66: University of Liverpool; Xi'an Jiaotong-Liverpool University | G66: Since 2020, breast cancer has remained the most prevalent cancer worldwide and the World Health Organisation projects significant increases by 2040, with new cases expected to exceed 3 million annually (a 40% increase) and deaths to surpass 1 million (a 50% increase), highlighting the urgent need for advancements in detection and treatment. Current detection of metastasis is highly dependent on labour-intensive and error-prone pathological examination of large-scale biotissue. Given the high-resolution (100,000 & times; 100,000 gigapixels) but limited quantity of open-source pathological slide datasets, existing deep learning models face preprocessing challenges. This paper introduces HI-Net, a high-speed panoramic feature-extraction pyramid network for rapid and accurate detection of metastatic breast cancer, balancing panoramic segmentation and local attention. Additionally, a lightweight pathological slide dataset optimised for 512 x 512-pixel resolution, derived from downsampled and reassembled competitive datasets, accelerates training and reduces computational costs. HI-Net demonstrates superior performance on existing medical imaging competition datasets and our lightweight dataset, evidencing its effectiveness across datasets and potential for contributing to the generalisation of intelligent diagnostics. | H66: Breast cancer; Histopathology slide; Deep learning; Medical imaging; Intelligent diagnosis | J66: CELL PRESS | K66: Article | L66: Green Submitted, gold | M66: {=IFERROR( INDEX(survey_paper_2026!$F:$F, MATCH(LOWER(TRIM(B66)), LOWER(TRIM(survey_paper_2026!$B:$B)),0) ), "New" )} -> SF | N66: {=IFERROR( INDEX(survey_paper_2026!$G:$G, MATCH(LOWER(TRIM(B66)), LOWER(TRIM(survey_paper_2026!$B:$B)),0) ), "New" )} | O66: “Lightweight” referred to dataset construction rather than a lightweight model, and the study did not provide qualifying model-level efficiency evidence.
A67: Liu, SY; Ren, JD; Chen, ZN; Hu, K; Xiao, F; Li, XY; Gao, XP | B67: effidiag: an efficient framework for breast cancer diagnosis in multi-gigapixel whole slide images | C67: 2020 | D67: 2020 IEEE INTERNATIONAL CONFERENCE ON BIOINFORMATICS AND BIOMEDICINE | E67: 28 | F67: Chinese Academy of Sciences; Institute of Automation, CAS; Chinese Academy of Sciences; University of Chinese Academy of Sciences, CAS; Xiangtan University; Baidu; Xiangnan University | G67: Breast cancer diagnosis in multi-gigapixel whole slide images (WSIs) is an important task that highly relevant to cancer grading and prognosis. In recent years, many computer-aided diagnosis methods were proposed and achieved promising performance. However, they mostly suffer from heavy computational burden that becomes a significant barrier to clinical practice. Efficient solutions are urgently demanded but still less studied. In this paper, we propose a novel framework named EffiDiag for a fast and lightweight breast cancer diagnosis. To this end, a loss-modified U-net is developed at first to enable a fast suspected cancer Region Of Interest (ROI) localization. Therefore the subsequent patch-based classification, which commonly executes at the finest magnification hundreds of thousands times per WSI for cancer identification, could be carried out on these ROIs only rather than the whole WSI for speedup. Meanwhile, a super-efficient convolutional neural network (CNN) is devised to optimize the classification speed and resource consumption per classification. Experiments on the Camelyon16 benchmark demonstrate, by integrating the two contributions into a well-established approach, 47x inference acceleration is obtained with limited accuracy drop, yet with much less resource consumption even compared to popular lightweight networks. | H67: Breast cancer; computer-aided diagnosis; lightweight CNN; ROI detection; whole slide image | J67: IEEE COMPUTER SOC | K67: Proceedings Paper | M67: {=IFERROR( INDEX(survey_paper_2026!$F:$F, MATCH(LOWER(TRIM(B67)), LOWER(TRIM(survey_paper_2026!$B:$B)),0) ), "New" )} -> P | N67: {=IFERROR( INDEX(survey_paper_2026!$G:$G, MATCH(LOWER(TRIM(B67)), LOWER(TRIM(survey_paper_2026!$B:$B)),0) ), "New" )} -> Y
A68: Khan, HU; Raza, B; Waheed, A; Shah, HB | B68: msf-model: multi-scale feature fusion-based domain adaptive model for breast cancer classification of histopathology images | C68: 2022 | D68: IEEE ACCESS | E68: 47 | F68: COMSATS University Islamabad (CUI); Seoul National University (SNU); King Khalid University | G68: One of the most common causes of mortality for women globally is breast cancer. Early breast cancer identification could make it possible for people to receive the appropriate treatment to save their lives and return to their routine lives. Breast cancer diagnosis by histopathology is referred to as the gold standard. In recent years, convolutional neural network-based techniques are used for breast cancer classification. However, they faced domain adaptation, small objects retention, and feature extraction issues of complex microscopic images. In this study, we introduced multi-scale feature fusion-based domain adaptive model for breast cancer classification using histopathology images. It has two blocks and six lightweight sub-models where each block contains three models. Dilated layers are used in sub-models to overcome the disappearing of small objects in deep layers. Reducing the disappearing of small objects helped to extract better features for higher performance. Multiple heterogeneous feature extractors are used in this study which helped to extract various features. Extracted features are fused and reduced by retaining better features. Learning of model from natural images to complex microscopic images has limitation of domain adaptation. Same domain transfer learning is used in this study to overcome the limitations of different domain transfer learning. Model is trained on patchcamelyon17 dataset and weights of this training are further used for same domain transfer learning. Pre-trained weights are further used for the training of proposed model on BreaKHis dataset. A number of conventional data augmentation techniques are used as complex models require higher number of samples for the tuning of weights. Local window based CLAHE contrast enhancement technique is used to increase foreground-background contrast and remove noise. The proposed model achieved 98.00% precision, 98.15% recall, 98.08% f-measure, and 98.23% accuracy on test data. To best of our knowledge, it surpassed state-of-the-art models. | H68: Deep learning; convolutional neural networks; breast cancer classification; histopathology images | I68: NETWORK; CNN | J68: IEEE-INST ELECTRICAL ELECTRONICS ENGINEERS INC | K68: Article | L68: gold | M68: SA | N68: {=IFERROR( INDEX(survey_paper_2026!$G:$G, MATCH(LOWER(TRIM(B68)), LOWER(TRIM(survey_paper_2026!$B:$B)),0) ), "New" )} -> New
A69: Li, YH; Shen, YQ; Zhang, JD; Song, SJ; Li, ZH; Ke, J; Shen, DG | B69: a hierarchical graph v-net with semi-supervised pre-training for histological image based breast cancer classification | C69: 2023 | D69: IEEE TRANSACTIONS ON MEDICAL IMAGING | E69: 48 | F69: ShanghaiTech University; Johns Hopkins University; Kunming Medical University; Kunming Medical University; Shanghai Jiao Tong University | G69: Numerous patch-based methods have recently been proposed for histological image based breast cancer classification. However, their performance could be highly affected by ignoring spatial contextual information in the whole slide image (WSI). To address this issue, we propose a novel hierarchical Graph V-Net by integrating 1) patch-level pre-training and 2) context-based fine-tuning, with a hierarchical graph network. Specifically, a semi-supervised framework based on knowledge distillation is first developed to pre-train a patch encoder for extracting disease-relevant features. Then, a hierarchical Graph V-Net is designed to construct a hierarchical graph representation from neighboring/similar individual patches for coarse-to-fine classification, where each graph node (corresponding to one patch) is attached with extracted disease-relevant features and its target label during training is the average label of all pixels in the corresponding patch. To evaluate the performance of our proposed hierarchical Graph V-Net, we collect a large WSI dataset of 560 WSIs, with 30 labeled WSIs from the BACH dataset (through our further refinement), 30 labeled WSIs and 500 unlabeled WSIs from Yunnan Cancer Hospital. Those 500 unlabeled WSIs are employed for patch-level pre-training to improve feature representation, while 60 labeled WSIs are used to train and test our proposed hierarchical Graph V-Net. Both comparative assessment and ablation studies demonstrate the superiority of our proposed hierarchical Graph V-Net over state-of-the-art methods in classifying breast cancer from WSIs. The source code and our annotations for the BACH dataset have been released at https://github.com/lyhkevin/Graph-V-Net. | H69: Breast cancer classification; digital pathology; semi-supervised learning; graph neural network | J69: IEEE-INST ELECTRICAL ELECTRONICS ENGINEERS INC | K69: Article | M69: SA | N69: {=IFERROR( INDEX(survey_paper_2026!$G:$G, MATCH(LOWER(TRIM(B69)), LOWER(TRIM(survey_paper_2026!$B:$B)),0) ), "New" )} -> New
A70: Madhukar, BN; Bharathi, SH; Ashwin, MP | B70: classification of breast cancer using ensemble filter feature selection with triplet attention based efficient net classifier | C70: 2024 | D70: INTERNATIONAL ARAB JOURNAL OF INFORMATION TECHNOLOGY | E70: 40 | F70: REVA University | G70: In medical imaging, the effective detection and classification of Breast Cancer (BC) is a current research important task because of the still existing difficulty to distinguish abnormalities from normal breast tissues due to their subtle appearance and ambiguous margins and distinguish abnormalities from the normal breast. Moreover, BC detection based on an automated detection model is needed, because manual diagnosis faces problems due to cost and shortage of skilled manpower, and also takes a very long time. Using deep learning and ensemble feature selection techniques, in this paper, a novel framework is introduced for classifying BC from histopathology images. The five primary steps of the suggested framework are as follows: 1) to make the largest original dataset and then deep learning model with data augmentation to improve the learning. 2) The best features are selected by an Ensemble Filter Feature selection Method (EFFM) which combines the best feature subsets to produce the final feature subsets. 3) Then the pruned Convolution Neural Network (CNN) model is utilized to extract the optimal features. 4) Finally, the classification is done through the Triplet Attention based Efficient Network (TAENet) classifier. The suggested model produces a 98% accuracy rate after being trained and tested on two different histopathology imaging datasets including images from four different data cohorts. Subsequently, the suggested strategy outperforms the conventional ones since the ensemble filter habitually acquires the best features, and experimental results demonstrate the importance of the proposed approach . | H70: Breast cancer classification; histopathology image; ensemble filter feature selection; triplet attention based EfficientNet; TAENet | I70: MAMMOGRAPHY; NETWORK; IMAGE | J70: ZARKA PRIVATE UNIV | K70: Article | L70: gold | M70: SA | N70: {=IFERROR( INDEX(survey_paper_2026!$G:$G, MATCH(LOWER(TRIM(B70)), LOWER(TRIM(survey_paper_2026!$B:$B)),0) ), "New" )} -> New
A71: Yan, LJ; Wu, L; Xia, M; He, L | B71: a hybrid deep learning model for mammographic breast cancer detection: multi-autoencoder and attention mechanisms | C71: 2025 | D71: JOURNAL OF RADIATION RESEARCH AND APPLIED SCIENCES | E71: 52 | G71: Objective: This study aims to develop a robust diagnostic framework for breast cancer detection in mammographic images by integrating multi-autoencoder-based feature extraction with attention mechanisms. The objective is to address key limitations in traditional and state-of-the-art methods, including limited adaptability, manual feature dependency, and lack of interpretability, ensuring enhanced diagnostic accuracy and clinical utility. Materials and methods: This study utilizes a multi-center dataset of 5987 mammograms (malignant: 36 %, benign: 31.9 %, normal: 32.1 %). Images were standardized to 256 x 256 pixels, with intensity normalization and augmentation. A multi-autoencoder framework with six independently pre-trained autoencoders extracted diagnostic features. Recursive Feature Elimination (RFE) with XGBoost was applied for feature selection. Attention mechanisms prioritized diagnostically significant regions. Classification performance was evaluated using accuracy, sensitivity, specificity, F1-score, and AUC-ROC, while segmentation was assessed using IoU, Dice score, and localization accuracy. Five-fold cross-validation ensured robustness, and Adam optimizer with early stopping was used for optimal model training. Results: The proposed framework demonstrates high accuracy in both segmentation and classification for breast cancer detection. Attention-based segmentation achieved 91.5 % localization accuracy, with IoU = 0.87 and a Dice score of 0.89, ensuring precise identification of diagnostic regions. The multi-autoencoder classification model attained 94.2 % sensitivity and 96.4 % AUC in training, with 92.4 % sensitivity and 95.8 % AUC on independent testing, outperforming traditional statistical features. XGBoost surpassed other classifiers, including Random Forest, SVM, and Logistic Regression. These results validate the model's robustness, interpretability, and clinical applicability, establishing an AI-driven diagnostic tool for accurate breast cancer segmentation and classification. Conclusions: The proposed framework advances breast cancer detection by offering high accuracy, adaptability, and interpretability. Future work should explore multimodal imaging integration and lightweight implementations for real-time deployment in clinical environments. | H71: Breast cancer; Multi-autoencoder; Attention mechanisms; Mammographic imaging | J71: ELSEVIER | K71: Article | L71: gold | M71: SA | N71: {=IFERROR( INDEX(survey_paper_2026!$G:$G, MATCH(LOWER(TRIM(B71)), LOWER(TRIM(survey_paper_2026!$B:$B)),0) ), "New" )} -> New
A72: Kausar, T; Lu, Y; Kausar, A | B72: breast cancer diagnosis using lightweight deep convolution neural network model | C72: 2023 | D72: IEEE ACCESS | E72: 72 | F72: Huizhou University | G72: In the past few decades, breast cancer has rapidly increased the death rate among women worldwide. An early diagnosis of such fatal disease is important for the best treatment and death rate reduction. Automatic diagnosis of breast cancer from histopathological images using artificial intelligence (AI) based methods is a top-priority research area in the biomedical field. However, automatic detection is challenging due to high resolution of histopathology images and the tremendous amount of parameters required by deep AI models. Due to high computational complexity and bulky memory usage, deep models suffer from inefficient inference that limits their application in resource-constrained platforms. To address this problem, a fast cancer detection strategy has been proposed to overcome the computational cost issue of deep automatic systems. Instead of directly using input images the wavelet transform (WT) is applied to decompose the images into different frequency bands and then only low frequency bands are subjected to our proposed lightweight deep convolutional neural network (CNN). The lightweight deep model is designed using invertible residual block module. The incorporation of invertible residual block module in the deep CNN model and the use of WT considerably reduces the computational cost of the proposed model, without a noticeable accuracy downgrade Further, the effect of various machine vision classifiers i.e. support vector machine (SVM), softmax, and K nearest neighbor classifier (KNN) on model performance is analyzed. Experiments are performed using three publicly available benchmark histopathology image datasets. The proposed model has shown multi-class classification accuracy of 96.25%, and 99.8% and 72.2%, on the international conference on image analysis and recognition (ICIAR 2018), BreakHis and Bracs datasets, respectively. The reported inference time per image of the proposed model is 0.67s, and 0.21s for ICIAR 2018 and BreakHis and Bracs images, respectively. | H72: Breast histopathology; wavelet transform; convolution neural networks; support vector machine; inverted residual block; softmax | I72: IMAGES; SYSTEM | J72: IEEE-INST ELECTRICAL ELECTRONICS ENGINEERS INC | K72: Article | L72: Green Submitted, gold | M72: {=IFERROR( INDEX(survey_paper_2026!$F:$F, MATCH(LOWER(TRIM(B72)), LOWER(TRIM(survey_paper_2026!$B:$B)),0) ), "New" )} -> P | N72: {=IFERROR( INDEX(survey_paper_2026!$G:$G, MATCH(LOWER(TRIM(B72)), LOWER(TRIM(survey_paper_2026!$B:$B)),0) ), "New" )} -> Y
A73: Bin Ashraf, F; Alam, SMM; Sakib, SM | B73: enhancing breast cancer classification via histopathological image analysis: leveraging self-supervised contrastive learning and transfer learning | C73: 2024 | D73: HELIYON | E73: 25 | F73: University of California System; University of California Riverside | G73: Breast cancer, a significant threat to women's health, demands early detection. Automating histopathological image analysis offers a promising solution to enhance efficiency and accuracy in diagnosis. This study addresses the challenge of breast cancer histopathological image classification by leveraging the ResNet architecture, known for its depth and skip connections. In this work, two distinct approaches were pursued, each driven by unique motivations. The first approach aimed to improve the learning process through self-supervised contrastive learning. It utilizes a small subset of the training data for initial model training and progressively expands the training set by incorporating confidently labeled data from the unlabeled pool, ultimately achieving a reliable model with limited training data. The second approach focused on optimizing the architecture by combining ResNet50 and Inception module to get a lightweight and efficient classifier. The dataset utilized in this work comprises histopathological images categorized into benign and malignant classes at varying magnification levels (40X, 100X, 200X, 400X), all originating from the same source image. The results demonstrate state-of-the-art performance, achieving 98% accuracy for images magnified at 40X and 200X, and 94% for 100X and 400X. Notably, the proposed architecture boasts a substantially reduced parameter count of approximately 3.6 million, contrasting with existing leading architectures, which possess parameter sizes at least twice as large. | H73: Breast cancer classification; Histopathology image; Transfer learning; Contrastive learning; Medical image processing | J73: CELL PRESS | K73: Article | L73: Green Submitted, gold | M73: {=IFERROR( INDEX(survey_paper_2026!$F:$F, MATCH(LOWER(TRIM(B73)), LOWER(TRIM(survey_paper_2026!$B:$B)),0) ), "New" )} -> P | N73: {=IFERROR( INDEX(survey_paper_2026!$G:$G, MATCH(LOWER(TRIM(B73)), LOWER(TRIM(survey_paper_2026!$B:$B)),0) ), "New" )} -> Y
A74: Pan, X; Wang, P; Jia, SY; Wang, YH; Liu, Y; Zhang, Y; Jiang, CJ | B74: multi-contrast learning-guided lightweight few-shot learning scheme for predicting breast cancer molecular subtypes | C74: 2024 | D74: MEDICAL & BIOLOGICAL ENGINEERING & COMPUTING | E74: 47 | F74: Jiangnan University; University of Macau; Jiangnan University; Fudan University | G74: Invasive gene expression profiling studies have exposed prognostically significant breast cancer subtypes: normal-like, luminal, HER-2 enriched, and basal-like, which is defined in large part by human epidermal growth factor receptor 2 (HER-2), progesterone receptor (PR), and estrogen receptor (ER). However, while dynamic contrast-enhanced magnetic resonance imaging (DCE-MRI) has been generally employed in the screening and therapy of breast cancer, there is a challenging problem to noninvasively predict breast cancer molecular subtypes, which have extremely low-data regimes. In this paper, a novel few-shot learning scheme, which combines lightweight contrastive convolutional neural network (LC-CNN) and multi-contrast learning strategy (MCLS), is worthwhile to be developed for predicting molecular subtype of breast cancer in DCE-MRI. Moreover, MCLS is designed to construct One-vs-Rest and One-vs-One classification tasks, which addresses inter-class similarity among normal-like, luminal, HER-2 enriched, and basal-like. Extensive experiments demonstrate the superiority of our proposed scheme over state-of-the-art methods. Furthermore, our scheme is able to achieve competitive results on few samples due to joint LC-CNN and MCLS for excavating contrastive correlations of a pair of DCE-MRI. | H74: Breast cancer; Few-shot learning; One-vs-Rest; One-vs-One | J74: SPRINGER HEIDELBERG | K74: Article | M74: P | N74: Y
A75: Tummala, S; Chauhdary, SH; Singh, V; Kumar, R; Kadry, S; Kim, J | B75: lightweight residual multi-head convolution with channel attention (resmhcnn) for end-to-end classification of medical images | C75: 2025 | D75: CMES-COMPUTER MODELING IN ENGINEERING & SCIENCES | E75: 45 | F75: SRM University-AP; Huzhou Normal University; Manipal Academy of Higher Education (MAHE); Henan University; Lebanese American University; Inha University | G75: Lightweight deep learning models are increasingly required in resource-constrained environments such as mobile devices and the Internet of Medical Things (IoMT). Multi-head convolution with channel attention can facilitate learning activations relevant to different kernel sizes within a multi-head convolutional layer. Therefore, this study investigates the capability of novel lightweight models incorporating residual multi-head convolution with channel attention (ResMHCNN) blocks to classify medical images. We introduced three novel lightweight deep learning models (BT-Net, LCC-Net, and BC-Net) utilizing the ResMHCNN block as their backbone. These models were cross-validated and tested on three publicly available medical image datasets: a brain tumor dataset from Figshare consisting of T1-weighted magnetic resonance imaging slices of meningioma, glioma, and pituitary tumors; the LC25000 dataset, which includes microscopic images of lung and colon cancers; and the BreaKHis dataset, containing benign and malignant breast microscopic images. The lightweight models achieved accuracies of 96.9% for 3-class brain tumor classification using BT-Net, and 99.7% for 5-class lung and colon cancer classification using LCC-Net. For 2-class breast cancer classification, BC-Net achieved an accuracy of 96.7%. The parameter counts for the proposed lightweight models-LCC-Net, BC-Net, and BT-Net-are 0.528, 0.226, and 1.154 million, respectively. The presented lightweight models, featuring ResMHCNN blocks, may be effectively employed for accurate medical image classification. In the future, these models might be tested for viability in resource-constrained systems such as mobile devices and IoMT platforms. | H75: Lightweight models; brain tumor; breast cancer; lung cancer; colon cancer; multi-head CNN | J75: TECH SCIENCE PRESS | K75: Article | L75: gold | M75: SA | N75: {=IFERROR( INDEX(survey_paper_2026!$G:$G, MATCH(LOWER(TRIM(B75)), LOWER(TRIM(survey_paper_2026!$B:$B)),0) ), "New" )} -> New
A76: Qasem, A; Abdullah, SNHS; Sahran, S; Albashish, D; Goudarzi, S; Arasaratnam, S | B76: an improved ensemble pruning for mammogram classification using modified bees algorithm | C76: 2022 | D76: NEURAL COMPUTING & APPLICATIONS | E76: 59 | F76: Universiti Kebangsaan Malaysia; Taiz University; Al-Balqa Applied University | G76: Ensemble learning has piqued the curiosity of the machine learning applications. It recently drawn serious attention in computer-aided diagnostic system (CADs) due to their potential to significantly increase the prediction performance, especially in mass classification in the mammogram. The ensemble pruning technique is used to reduce the ensemble size and improve its performance by selecting an optimal subset from a pool of individual classifiers. Among ensemble pruning techniques, the metaheuristic Bees algorithm (BA) showed reliable performance in terms of the selected ensemble's accuracy. However, BA's random initialization cannot guarantee whether the optimal ensemble will be selected, which leads to lesser classification results. Thus, this study introduces a selective Random Start Best step (RSB) initialization for BA to get an optimal ensemble pruning solution. Moreover, fusing ensemble members with equal weights will reduce the performance of the ensemble. To overcome this issue, a Local Weighted Majority Voting (L-WMV) is proposed beside the RSB. The proposed RSB(L-WMV) method for solving ensemble pruning and fussing issues was assessed on the mammogram image dataset that has been collected from Hospital Kuala Lumpur (HKL). Furthermore, the proposed RSB(L-WMV) was applied to the Mammographic Image Analysis Society (MIAS) benchmark dataset to show the proposed method's effectiveness. The obtained results using various evaluation metrics (accuracy, sensitivity, specificity, AUC) reveal the superiority of the proposed RSB(L-WMV) compared to similar methods in the literature. | H76: Bees algorithm; Medical image processing; Ensemble pruning; Ensemble fusion | I76: MULTIPLE FEATURE REPRESENTATIONS; COMPUTER-AIDED DETECTION; DIVERSITY; DIAGNOSIS | J76: SPRINGER LONDON LTD | K76: Article | M76: P | N76: Y
A77: Wu, YN; Zhou, L; Zhao, J; Peng, YQ; Li, XY; Wang, YT; Zhu, ST; Hou, CJ; Du, P; Ling, L; Wang, Y; Tian, JW; Sun, LT | B77: relation knowledge distillation 3d-resnet-based deep learning for breast cancer molecular subtypes prediction on ultrasound videos: a multicenter study | C77: 2025 | D77: BRITISH JOURNAL OF CANCER | E77: 35 | F77: Hangzhou Medical College; Zhejiang Provincial People's Hospital; Hangzhou Medical College; Zhejiang University; Harbin Medical University; Hangzhou Medical College; Zhejiang Provincial People's Hospital; Hebei Medical University | G77: BackgroundTo develop and test a relation knowledge distillation three-dimensional residual network (RKD-R3D) model for predicting breast cancer molecular subtypes using ultrasound (US) videos to aid clinical personalized management.MethodsThis multicentre study retrospectively included 882 breast cancer patients (2375 US videos and 9499 images) between January 2017 and December 2021, which was divided into training, validation, and internal test cohorts. Additionally, 86 patients was collected between May 2023 and November 2023 as the external test cohort. St. Gallen molecular subtypes (luminal A, luminal B, HER2-positive, and triple-negative) were confirmed via postoperative immunohistochemistry. The RKD-R3D based on US videos was developed and validated to predict four-classification molecular subtypes of breast cancer. The predictive performance of RKD-R3D was compared with RKD-R2D, traditional R3D, and preoperative core needle biopsy (CNB). The area under the receiver operating characteristic curve (AUC), sensitivity, specificity, accuracy, balanced accuracy, precision, recall, and F1-score were analyzed.ResultsRKD-R3D (AUC: 0.88, 0.95) outperformed RKD-R2D (AUC: 0.72, 0.85) and traditional R3D (AUC: 0.65, 0.79) in predicting four-classification breast cancer molecular subtypes in the internal and external test cohorts. RKD-R3D outperformed CNB (Accuracy: 0.87 vs. 0.79) in the external test cohort, achieved good performance in predicting triple negative from non-triple negative breast cancers (AUC: 0.98), and obtained satisfactory prediction performance for both T1 and non-T1 lesions (AUC: 0.96, 0.90).ConclusionsRKD-R3D when used with US videos becomes a potential supplementary tool to non-invasively assess breast cancer molecular subtypes. | J77: SPRINGERNATURE | K77: Article | L77: Green Submitted | M77: SA | N77: {=IFERROR( INDEX(survey_paper_2026!$G:$G, MATCH(LOWER(TRIM(B77)), LOWER(TRIM(survey_paper_2026!$B:$B)),0) ), "New" )} -> New
A78: Yu, F; Xiao, ZY; Liu, L; Liu, K; Tang, M; Jiang, MH; Hou, JX | B78: biacandet: bioelectrical impedance analysis for breast cancer detection with space-time attention neural network | C78: 2025 | D78: EXPERT SYSTEMS WITH APPLICATIONS | E78: 53 | F78: Wuhan Textile University; Nanyang Technological University; Wuhan Textile University; Wuhan Textile University; Wuhan University | G78: Breast cancer is a life-threatening disease and early detection plays a crucial role in improving survival However, current detection technologies face challenges such as invasiveness, radiation exposure, high and limited accessibility. To address these issues, a novel breast cancer detection system called BiaCanDet based on bioelectrical impedance analysis (BIA) signal and space-time attention network is proposed first time. The BiaCanDet system utilizes non-invasive BIA to measure signal changes in electrical impedance and phase angle (PHA) based on the normal and tumour breast tissue. We collect the first BIABC dataset BIA devices, which includes 2,444 samples from normal, benign, and malignant breast tissues. Professional physicians collect and annotate the samples through repeated tissue sampling with needle electrodes, combined with pathological analysis to ensure accuracy. This paper proposes a novel space-time attention network (STABFNet) for the complex bioelectrical impedance signal to obtain robust cancer signal feature, designs the impedance phase enhancement attention (IPEA) model to improve recognition performance. experimental results on the BIABC dataset confirm that the STABFNet network achieve the 93.37%, 90.64%, 89.37%, and 89.90% in terms of accuracy, precision, recall, and f1-score, respectively. Additionally, the also demonstrates real-time detection capabilities in the lightweight mobile terminal. The proposed and methodology introduce a pioneering approach for breast cancer detection that is low-cost and convenient, making it a promising solution for widespread adoption that has the potential to revolutionize early cancer detection worldwide. | H78: Breast cancer detection; Bioelectrical impedance analysis; Space-time network; Attention mechanism | I78: COMPLICATIONS | J78: PERGAMON-ELSEVIER SCIENCE LTD | K78: Article | M78: P | N78: Y
A79: Wang, CQ; Gong, WJ; Cheng, JL; Qian, YR | B79: dblcnn: dependency-based lightweight convolutional neural network for multi-classification of breast histopathology images | C79: 2022 | D79: BIOMEDICAL SIGNAL PROCESSING AND CONTROL | E79: 52 | F79: Xinjiang University; Sichuan University; Xinjiang University | G79: Breast histopathology analysis is the gold standard for diagnosing breast cancer. Convolutional neural network based methods for breast histology image classification have emerged in recent years to make the analysis process simple and fast. Due to the limitation of hardware devices, these classification methods still face the problem of difficult balance recognition performance and computational efficiency. In this paper, we propose the Dependency-based lightweight convolutional neural network (DBLCNN) for the multi-classification task of breast histopathology images. Firstly, we design a new network in which dependencies (magnification and binary classification probability) were used to guide subspecies features for better recognition. Secondly, we redesign the backbone MobileNet to greatly reduce the model parameters and computation while ensuring excellent recognition performance. At the same time, transfer learning based on ImageNet is applied to the DBLCNN network. Extensive experiments on the BreakHis dataset have shown that the DBLCNN network has state-of-theart effects in terms of recognition performance and computational utilization. | H79: Deep learning; Image classification; Computer vision; Medical imaging; Breast cancer | I79: DEEP; ENSEMBLE | J79: ELSEVIER SCI LTD | K79: Article | M79: P | N79: Y
A80: Wang, C; Chen, YH; Liu, YY; Tian, Y; Liu, FB; McCarthy, DJ; Elliott, M; Frazer, H; Carneiro, G | B80: knowledge distillation to ensemble global and interpretable prototype-based mammogram classification models | C80: 2022 | D80: MEDICAL IMAGE COMPUTING AND COMPUTER ASSISTED INTERVENTION, MICCAI 2022, PT III | E80: 24 | F80: Adelaide University; University of Adelaide; St. Vincent's Institute of Medical Research; St Vincent's Health; St Vincent's Hospital Melbourne | G80: State-of-the-art (SOTA) deep learning mammogram classifiers, trained with weakly-labelled images, often rely on global models that produce predictions with limited interpretability, which is a key barrier to their successful translation into clinical practice. On the other hand, prototype-based models improve interpretability by associating predictions with training image prototypes, but they are less accurate than global models and their prototypes tend to have poor diversity. We address these two issues with the proposal of BRAIxPro-toPNet++, which adds interpretability to a global model by ensembling it with a prototype-based model. BRAIxProtoPNet++ distills the knowledge of the global model when training the prototype-based model with the goal of increasing the classification accuracy of the ensemble. Moreover, we propose an approach to increase prototype diversity by guaranteeing that all prototypes are associated with different training images. Experiments on weakly-labelled private and public datasets show that BRAIxProtoPNet++ has higher classification accuracy than SOTA global and prototype-based models. Using lesion localisation to assess model interpretability, we show BRAIxProtoPNet++ is more effective than other prototype-based models and post-hoc explanation of global models. Finally, we show that the diversity of the prototypes learned by BRAIxProtoPNet++ is superior to SOTA prototype-based approaches. | H80: Interpretability; Explainability; Prototype-based model; Mammogram classification; Breast cancer diagnosis; Deep learning | I80: ATTENTION; MACHINE; IMAGES | J80: SPRINGER INTERNATIONAL PUBLISHING AG | K80: Proceedings Paper | L80: Green Submitted | M80: SA | N80: {=IFERROR( INDEX(survey_paper_2026!$G:$G, MATCH(LOWER(TRIM(B80)), LOWER(TRIM(survey_paper_2026!$B:$B)),0) ), "New" )} -> New
A81: Althobaiti, MM; Ashour, AA; Alhindi, NA; Althobaiti, A; Mansour, RF; Gupta, D; Khanna, A | B81: retracted: deep transfer learning-based breast cancer detection and classification model using photoacoustic multimodal images (retracted article) | C81: 2022 | D81: BIOMED RESEARCH INTERNATIONAL | E81: 26 | F81: Taif University; Taif University; King Abdulaziz University; New Valley University; Maharaja Agrasen Institute of Technology | G81: The rapid development of technologies in biomedical research has enriched and broadened the range of medical equipment. Magnetic resonance imaging, ultrasonic imaging, and optical imaging have been discovered by diverse research communities to design multimodal systems, which is essential for biomedical applications. One of the important tools is photoacoustic multimodal imaging (PAMI) which combines the concepts of optics and ultrasonic systems. At the same time, earlier detection of breast cancer becomes essential to reduce mortality. The recent advancements of deep learning (DL) models enable detection and classification the breast cancer using biomedical images. This article introduces a novel social engineering optimization with deep transfer learning-based breast cancer detection and classification (SEODTL-BDC) model using PAI. The intention of the SEODTL-BDC technique is to detect and categorize the presence of breast cancer using ultrasound images. Primarily, bilateral filtering (BF) is applied as an image preprocessing technique to remove noise. Besides, a lightweight LEDNet model is employed for the segmentation of biomedical images. In addition, residual network (ResNet-18) model can be utilized as a feature extractor. Finally, SEO with recurrent neural network (RNN) model, named SEO-RNN classifier, is applied to allot proper class labels to the biomedical images. The performance validation of the SEODTL-BDC technique is carried out using benchmark dataset and the experimental outcomes pointed out the supremacy of the SEODTL-BDC approach over the existing methods. | I81: DIAGNOSIS | J81: WILEY | K81: Article; Retracted Publication | L81: Green Submitted, hybrid | M81: RT | N81: {=IFERROR( INDEX(survey_paper_2026!$G:$G, MATCH(LOWER(TRIM(B81)), LOWER(TRIM(survey_paper_2026!$B:$B)),0) ), "New" )} -> New
A82: Rai, HM; Yoo, J; Agarwal, S; Agarwal, N | B82: lightweightunet: multimodal deep learning with gan-augmented imaging data for efficient breast cancer detection | C82: 2025 | D82: BIOENGINEERING-BASEL | E82: 73 | F82: Gachon University; Yeungnam University; Yeungnam University | G82: Breast cancer ranks as the second most prevalent cancer globally and is the most frequently diagnosed cancer among women; therefore, early, automated, and precise detection is essential. Most AI-based techniques for breast cancer detection are complex and have high computational costs. Hence, to overcome this challenge, we have presented the innovative LightweightUNet hybrid deep learning (DL) classifier for the accurate classification of breast cancer. The proposed model boasts a low computational cost due to its smaller number of layers in its architecture, and its adaptive nature stems from its use of depth-wise separable convolution. We have employed a multimodal approach to validate the model's performance, using 13,000 images from two distinct modalities: mammogram imaging (MGI) and ultrasound imaging (USI). We collected the multimodal imaging datasets from seven different sources, including the benchmark datasets DDSM, MIAS, INbreast, BrEaST, BUSI, Thammasat, and HMSS. Since the datasets are from various sources, we have resized them to the uniform size of 256 x 256 pixels and normalized them using the Box-Cox transformation technique. Since the USI dataset is smaller, we have applied the StyleGAN3 model to generate 10,000 synthetic ultrasound images. In this work, we have performed two separate experiments: the first on a real dataset without augmentation and the second on a real + GAN-augmented dataset using our proposed method. During the experiments, we used a 5-fold cross-validation method, and our proposed model obtained good results on the real dataset (87.16% precision, 86.87% recall, 86.84% F1-score, and 86.87% accuracy) without adding any extra data. Similarly, the second experiment provides better performance on the real + GAN-augmented dataset (96.36% precision, 96.35% recall, 96.35% F1-score, and 96.35% accuracy). This multimodal approach, which utilizes LightweightUNet, enhances the performance by 9.20% in precision, 9.48% in recall, 9.51% in F1-score, and a 9.48% increase in accuracy on the combined dataset. The LightweightUNet model we proposed works very well thanks to a creative network design, adding fake images to the data, and a multimodal training method. These results show that the model has a lot of potential for use in clinical settings. | H82: LightweightUNet; breast cancer detection; multimodal approach; GAN-augmentation; synthetic dataset generation; deep learning; lightweight architecture | J82: MDPI | K82: Article | L82: Green Submitted, gold | M82: {=IFERROR( INDEX(survey_paper_2026!$F:$F, MATCH(LOWER(TRIM(B82)), LOWER(TRIM(survey_paper_2026!$B:$B)),0) ), "New" )} -> P | N82: {=IFERROR( INDEX(survey_paper_2026!$G:$G, MATCH(LOWER(TRIM(B82)), LOWER(TRIM(survey_paper_2026!$B:$B)),0) ), "New" )} -> Y
A83: Gong, JQ; Ye, P; Chang, ZH | B83: the application of lightweight ai algorithms in postoperative rehabilitation of breast cancer | C83: 2025 | D83: COMPUTER METHODS IN BIOMECHANICS AND BIOMEDICAL ENGINEERING | E83: 26 | F83: University of Shanghai for Science & Technology; University of Shanghai for Science & Technology | G83: The prevalence of breast cancer as a major global cancer has underscored the importance of postoperative recovery for breast cancer patients. Among the issues, postoperative patients are prone to spinal deformities, including scoliosis, which has drawn significant attention from healthcare professionals. The primary aim of this study is to design a postoperative recovery platform for breast cancer patients that can effectively detect posture changes, provide feedback and support to medical staff, assist doctors in formulating recovery plans, and prevent spinal deformities. The feasibility of the recovery platform is also validated through experiments. The development and validation of the experimental recovery platform. The recovery platform includes instrument design, patient data collection, model training and fine-tuning, and postoperative body posture evaluation by comparing preoperative and postoperative conditions. The evaluation results are provided to doctors to facilitate the formulation of personalized postoperative recovery plans. This paper comprehensively designs and implements the recovery platform and verifies its feasibility through simulation experiments. Statistical methods were employed for the validation of the rehabilitation platform in simulated experiments, with a significance level of p < 0.05. In comparison to static assessments like CT scans, this paper introduces a dynamic detection method that provides a more insightful analysis of body posture. The experiments also demonstrate the preventive capability of this method against post-operative spinal deformities, ultimately enhancing patients' self-image, restoring their confidence, and enabling them to lead more fulfilling lives. | H83: Breast cancer; MobileNet-LSTM; gait recognition; spinal deformation; postoperative rehabilitation; dynamic detection | I83: WOMEN | J83: TAYLOR & FRANCIS LTD | K83: Article | M83: {=IFERROR( INDEX(survey_paper_2026!$F:$F, MATCH(LOWER(TRIM(B83)), LOWER(TRIM(survey_paper_2026!$B:$B)),0) ), "New" )} -> ST | N83: {=IFERROR( INDEX(survey_paper_2026!$G:$G, MATCH(LOWER(TRIM(B83)), LOWER(TRIM(survey_paper_2026!$B:$B)),0) ), "New" )}
A84: Maurya, R; Pandey, NN; Mahapatra, S | B84: bmea-vit: breast cancer classification using lightweight customized vision transformer architecture with multi-head external attention | C84: 2025 | D84: IEEE ACCESS | E84: 27 | F84: Madan Mohan Malaviya University of Technology; Sharda University; Manipal Academy of Higher Education (MAHE) | G84: Breast cancer is one of the primary concerns for women's mortality across the world. Breast cancer can be diagnosed by an expert pathologist through histopathological examination of the breast lesions. Manual analysis of histopathology images by an expert pathologist is time-consuming. Therefore, automated computer-aided diagnosis plays a significant role in breast cancer prognosis. State-of-the-art (SOTA) convolution neural networks (CNNs) have earlier been utilized in the development of such systems. However, CNNs have large inductive biases and cannot model long-term dependencies in terms of global features. In this proposed work, a customised Vision Transformer (ViT) architecture with multi-head external attention, termed as BMEA-ViT, has been developed for breast cancer diagnosis. The Transformer has much lesser inductive bias and can capture long-term dependencies using an attention mechanism. However, the multi-headed self-attention (MSA) unit used in the originally proposed ViT quadratically increases its computational complexity. Therefore, in the proposed customised ViT, the MSA unit has been replaced with the multi-head external attention (MEA) unit with linear complexity. In contrast to MSA, MEA is simply implemented using a sequence of two linear layers whose weights are shared across the whole dataset. This replacement of MSA with MEA results in better generalizability with fewer inductive biases. The proposed method achieves 95.74%, 96.96%, 98.18%, and 97.25% classification accuracy on the publicly available 'BreakHis' dataset at four different magnification levels: x40, x100, x200, and x400, respectively. The experimental results suggest that the proposed method outperforms other recent architectures. | H84: Transformers; Breast cancer; Histopathology; Cancer; Breast; Computer vision; Microscopy; Lesions; Computer architecture; Computational modeling; convolution neural network; deep learning; transfer learning; vision transformer | J84: IEEE-INST ELECTRICAL ELECTRONICS ENGINEERS INC | K84: Article | L84: Green Submitted, gold | M84: P | N84: Y
A85: Arbawa, YK; Pisefty, RAD; Bachtiar, FA | B85: wound classifications of breast tissues with electrical impedance spectroscopy (eis): comparison of lvq and ga-lvq | C85: 2019 | D85: 2019 5TH INTERNATIONAL CONFERENCE ON SCIENCE ININFORMATION TECHNOLOGY (ICSITECH): EMBRACING INDUSTRY 4.0 - TOWARDS INNOVATION IN CYBER PHYSICAL SYSTEM | E85: 14 | F85: Brawijaya University | G85: Deaths of people with breast diseases have reached 40% and are increasing every year. Breast Disease arises from wounds in breast tissue is breast cancer. Wounds of breast can be seen and discriminated the type of wound using Electrical Impedance Spectroscopy(EIS). The results of this EIS data can be used as an initial diagnosis before the doctor carries out treatment. This research tried to classify the types of wounds from breast tissue by using the Learning Vector Quantization (LVQ) method with the Genetic Algorithm (GA) to find out whether the solution provides the expected optimum results. The dataset we used for this study was very small which did not represent the existing class, with 106 data for 6 classes. The results of the comparison between LVQ and GA-LVQ obtained LVQ added by GA has higher accuracy values than LVQ with 73% accuracy and compared to LVQ, GA increased accuracy by +/- 50%. | H85: Breast tissue; Classification; Learning Vector Quantization; Genetic Algorithm-Learning Vector Quantization | J85: IEEE | K85: Proceedings Paper | M85: ST | N85: {=IFERROR( INDEX(survey_paper_2026!$G:$G, MATCH(LOWER(TRIM(B85)), LOWER(TRIM(survey_paper_2026!$B:$B)),0) ), "New" )} -> New
A86: Malathi, S; Shenbagavalli, A; Sriraam, N | B86: a novel dilated convolution light weight neural network (dclw-nn) for the classification of breast thermograms | C86: 2025 | D86: IEEE ACCESS | E86: 45 | F86: National Engineering College - India; Dayananda Sagar College of Engineering | G86: Breast cancer poses lots of challenges in the medical fraternity worldwide. Hence, it requires early diagnosis to treat the affected people. In this paper, we have presented a novel Dilated Convolution Light Weight Neural Network (DCLW-NN) to analyze the breast thermograms. Convolutional Neural Network (CNN) is a deep learning model to process the hierarchical feature of visual data to conduct image classification. DCLW-NN is a light weight architecture that uses dilation principle in standard convolution to reduce the model parameters and maintain accuracy. To reduce system complexity, dilated Convolution enables the integration of information from a wider range without the need for a large kernel. The proposed model is experimented with two different infrared thermography imaging datasets like DMR-IR and Proprietary Datasets. The model is tested under four cases by training and testing with similar and dissimilar datasets and obtain the classification accuracy. To solve the problem of data scarcity, the model is worked out with datasets at various augmentation level and their performance is compared. Lastly, the categorization layer of the CNN model is replaced with Support Vector Machine(SVM) classifier with L2 regularization and found the prospects of DCLW-NN Classifier. The significant improvement of the model is obtained by varying the hyper tuning parameters of the model. The classifier performance of the proposed model was compared with existing architecture like RESNET-50, AlexNet, VGG-16 and it was found that it produces better accuracy of 99%, Sensitivity of 100% and Specificity of 98%. | H86: Accuracy; Convolutional neural networks; Imaging; Convolution; Breast cancer; Infrared imaging; Support vector machines; Deep learning; Computational modeling; Data models; Dilated convolution light weight neural network (DCLW-NN); breast thermograms; data augmentation; support vector machine classifier; model parameters | J86: IEEE-INST ELECTRICAL ELECTRONICS ENGINEERS INC | K86: Article | L86: Green Submitted, gold | M86: P | N86: Y
A87: Wang, X; Zeng, WZ; Xu, JZ; Zhang, SH; Gu, YX; Li, BH; Wang, XY | B87: mm-3d unet: development of a lightweight breast cancer tumor segmentation network utilizing multi-task and depthwise separable convolution | C87: 2025 | D87: FRONTIERS IN ONCOLOGY | E87: 33 | F87: Chinese People's Liberation Army General Hospital; Chinese People's Liberation Army General Hospital; Hohai University; Capital Medical University; Nanjing University of Chinese Medicine; Nanjing University of Chinese Medicine | G87: Background and objectives This paper introduces a novel lightweight MM-3DUNet (Multi-task Mobile 3D UNet) network designed for efficient and accurate segmentation of breast cancer tumors masses from MRI images, which leverages depth-wise separable convolutions, channel expansion units, and auxiliary classification tasks to enhance feature representation and computational efficiency.Methods We propose a 3D depth-wise separable convolution, and construct channel expansional convolution (CEC) unit and inverted residual block (IRB) to reduce the parameter count and computational load, making the network more suitable for use in resource-constrained environments. In addition, an auxiliary classification task (ACT) is introduced in the proposed architecture to provide additional supervisory signals for the main task of segmentation. The network architecture features a contracting path for downsampling and an expanding path for precise localization, enhanced by skip connections that integrate multi-level semantic information.Results The network was evaluated using a dataset of Dynamic Contrast Enhanced MRI (DCE-MRI) breast cancer images, and the results show that compared to the classical 3DU-Net, MM-3DUNet could significantly reduce model parameters by 63.16% and computational demands by 80.90%, while increasing segmentation accuracy by 1.30% in IoU (Intersection over Union).Conclusions MM-3DUNet offers a substantial reduction in computational requirements of breast cancer mass segmentation network. This network not only enhances diagnostic precision but also supports deployment in diverse clinical settings, potentially improving early detection and treatment outcomes for breast cancer patients. | H87: multi-task mobile 3D UNet; dynamic contrast enhanced MRI; breast cancer images segmentation; resource-constrained environments; convolutional neural networks | J87: FRONTIERS MEDIA SA | K87: Article | L87: Green Submitted, gold | M87: {=IFERROR( INDEX(survey_paper_2026!$F:$F, MATCH(LOWER(TRIM(B87)), LOWER(TRIM(survey_paper_2026!$B:$B)),0) ), "New" )} -> P | N87: {=IFERROR( INDEX(survey_paper_2026!$G:$G, MATCH(LOWER(TRIM(B87)), LOWER(TRIM(survey_paper_2026!$B:$B)),0) ), "New" )} -> Y
A88: Sánchez-Gutiérrez, ME; González-Pérez, PP | B88: multi-class classification of medical data based on neural network pruning and information-entropy measures | C88: 2022 | D88: ENTROPY | E88: 28 | F88: Universidad Autonoma Metropolitana - Mexico; University Autonoma Metropolitana Cuajimalpa | G88: Medical data includes clinical trials and clinical data such as patient-generated health data, laboratory results, medical imaging, and different signals coming from continuous health monitoring. Some commonly used data analysis techniques are text mining, big data analytics, and data mining. These techniques can be used for classification, clustering, and machine learning tasks. Machine learning could be described as an automatic learning process derived from concepts and knowledge without deliberate system coding. However, finding a suitable machine learning architecture for a specific task is still an open problem. In this work, we propose a machine learning model for the multi-class classification of medical data. This model is comprised of two components-a restricted Boltzmann machine and a classifier system. It uses a discriminant pruning method to select the most salient neurons in the hidden layer of the neural network, which implicitly leads to a selection of features for the input patterns that feed the classifier system. This study aims to investigate whether information-entropy measures may provide evidence for guiding discriminative pruning in a neural network for medical data processing, particularly cancer research, by using three cancer databases: Breast Cancer, Cervical Cancer, and Primary Tumour. Our proposal aimed to investigate the post-training neuronal pruning methodology using dissimilarity measures inspired by the information-entropy theory; the results obtained after pruning the neural network were favourable. Specifically, for the Breast Cancer dataset, the reported results indicate a 10.68% error rate, while our error rates range from 10% to 15%; for the Cervical Cancer dataset, the reported best error rate is 31%, while our proposal error rates are in the range of 4% to 6%; lastly, for the Primary Tumour dataset, the reported error rate is 20.35%, and our best error rate is 31%. | H88: medical data and signals; machine learning; restricted Boltzmann machine; feature selection; discriminant pruning; information-entropy measures | J88: MDPI | K88: Article | L88: Green Submitted, gold | M88: SA | N88: {=IFERROR( INDEX(survey_paper_2026!$G:$G, MATCH(LOWER(TRIM(B88)), LOWER(TRIM(survey_paper_2026!$B:$B)),0) ), "New" )} -> New
